Workbook

Sheet RESUMEN SUBIDAS
A2: COMPARATIVO DE PRECIOS 2026 · LA MINA DE CHAMARTÍN 2 · PRODUCTOS CON SUBIDAS
A5: CATEGORÍA | B5: PROVEEDOR | C5: PRODUCTO (ver hoja) | D5: ENERO | E5: FEBRERO | F5: MARZO | G5: ABRIL | H5: MAYO | I5: JUNIO | J5: JULIO | K5: AGOSTO | L5: PRECIO INICIAL | M5: PRECIO ACTUAL | N5: VARIACIÓN TOTAL % | O5: Nº SUBIDAS | P5: CAMBIOS DE PRECIO (mes a mes) | Q5: ESTADO
A6: CARNE | B6: CARNICAS OPC / CRNAS SERVAN | C6: MORCILLA ASTURIANA | E6: =IFERROR(INDEX('MORCILLA ASTURIANA'!$D$7:$D$9,MATCH("FEBRERO",'MORCILLA ASTURIANA'!$A$7:$A$9,0)),"") -> 8 | G6: =IFERROR(INDEX('MORCILLA ASTURIANA'!$D$7:$D$9,MATCH("ABRIL",'MORCILLA ASTURIANA'!$A$7:$A$9,0)),"") -> 8 | K6: =IFERROR(INDEX('MORCILLA ASTURIANA'!$D$7:$D$9,MATCH("AGOSTO",'MORCILLA ASTURIANA'!$A$7:$A$9,0)),"") -> 9 | L6: ='MORCILLA ASTURIANA'!D7 -> 8 | M6: ='MORCILLA ASTURIANA'!D9 -> 9 | N6: =IFERROR(M6/L6-1,0) -> 0.125 | O6: 1 | P6: ABR 8,00 → AGO 9,00 (+12,5%) | Q6: SUBE
A7: ENVASADO / BEBIDA / OTROS | B7: VINS DES DIEUX | C7: CANTALAPIEDRA CHIVIRITERO 2023 | E7: =IFERROR(INDEX('CANTALAPIEDRA CHIVIRITERO 20'!$D$7:$D$11,MATCH("FEBRERO",'CANTALAPIEDRA CHIVIRITERO 20'!$A$7:$A$11,0)),"") -> 15.5 | F7: =IFERROR(INDEX('CANTALAPIEDRA CHIVIRITERO 20'!$D$7:$D$11,MATCH("MARZO",'CANTALAPIEDRA CHIVIRITERO 20'!$A$7:$A$11,0)),"") -> 15.5 | G7: =IFERROR(INDEX('CANTALAPIEDRA CHIVIRITERO 20'!$D$7:$D$11,MATCH("ABRIL",'CANTALAPIEDRA CHIVIRITERO 20'!$A$7:$A$11,0)),"") -> 15.5 | H7: =IFERROR(INDEX('CANTALAPIEDRA CHIVIRITERO 20'!$D$7:$D$11,MATCH("MAYO",'CANTALAPIEDRA CHIVIRITERO 20'!$A$7:$A$11,0)),"") -> 16.9 | J7: =IFERROR(INDEX('CANTALAPIEDRA CHIVIRITERO 20'!$D$7:$D$11,MATCH("JULIO",'CANTALAPIEDRA CHIVIRITERO 20'!$A$7:$A$11,0)),"") -> 16.9 | L7: ='CANTALAPIEDRA CHIVIRITERO 20'!D7 -> 15.5 | M7: ='CANTALAPIEDRA CHIVIRITERO 20'!D11 -> 16.9 | N7: =IFERROR(M7/L7-1,0) -> 0.090322581 | O7: 1 | P7: ABR 15,50 → MAY 16,90 (+9,0%) | Q7: SUBE
A8: ENVASADO / BEBIDA / OTROS | B8: CONSERVAS Y SALAZONES JIMENEZ | C8: ANCHOAS CANTABRICO RO 550 ETIQUETA ROJA | E8: =IFERROR(INDEX('ANCHOAS CANTABRICO RO 550 ET'!$D$7:$D$10,MATCH("FEBRERO",'ANCHOAS CANTABRICO RO 550 ET'!$A$7:$A$10,0)),"") -> 18.96 | G8: =IFERROR(INDEX('ANCHOAS CANTABRICO RO 550 ET'!$D$7:$D$10,MATCH("ABRIL",'ANCHOAS CANTABRICO RO 550 ET'!$A$7:$A$10,0)),"") -> 18.96 | H8: =IFERROR(INDEX('ANCHOAS CANTABRICO RO 550 ET'!$D$7:$D$10,MATCH("MAYO",'ANCHOAS CANTABRICO RO 550 ET'!$A$7:$A$10,0)),"") -> 20.6 | J8: =IFERROR(INDEX('ANCHOAS CANTABRICO RO 550 ET'!$D$7:$D$10,MATCH("JULIO",'ANCHOAS CANTABRICO RO 550 ET'!$A$7:$A$10,0)),"") -> 20.6 | L8: ='ANCHOAS CANTABRICO RO 550 ET'!D7 -> 18.96 | M8: ='ANCHOAS CANTABRICO RO 550 ET'!D10 -> 20.6 | N8: =IFERROR(M8/L8-1,0) -> 0.08649789 | O8: 1 | P8: ABR 18,96 → MAY 20,60 (+8,6%) | Q8: SUBE
A9: ENVASADO / BEBIDA / OTROS | B9: SUBMARINER | C9: ZACAPA X O | D9: =IFERROR(INDEX('ZACAPA X O'!$D$7:$D$8,MATCH("ENERO",'ZACAPA X O'!$A$7:$A$8,0)),"") -> 122.71 | H9: =IFERROR(INDEX('ZACAPA X O'!$D$7:$D$8,MATCH("MAYO",'ZACAPA X O'!$A$7:$A$8,0)),"") -> 132.94 | L9: ='ZACAPA X O'!D7 -> 122.71 | M9: ='ZACAPA X O'!D8 -> 132.94 | N9: =IFERROR(M9/L9-1,0) -> 0.083367289 | O9: 1 | P9: ENE 122,71 → MAY 132,94 (+8,3%) | Q9: SUBE
A10: ENVASADO / BEBIDA / OTROS | B10: CALIDOSCOPI | C10: OREMUS 3 | D10: =IFERROR(INDEX('OREMUS 3'!$D$7:$D$8,MATCH("ENERO",'OREMUS 3'!$A$7:$A$8,0)),"") -> 27.4 | H10: =IFERROR(INDEX('OREMUS 3'!$D$7:$D$8,MATCH("MAYO",'OREMUS 3'!$A$7:$A$8,0)),"") -> 29.25 | L10: ='OREMUS 3'!D7 -> 27.4 | M10: ='OREMUS 3'!D8 -> 29.25 | N10: =IFERROR(M10/L10-1,0) -> 0.067518248 | O10: 1 | P10: ENE 27,40 → MAY 29,25 (+6,8%) | Q10: SUBE
A11: ENVASADO / BEBIDA / OTROS | B11: DITEMA (DIST. TENA) | C11: GINEBRA MARTIN MILLER 3/4 | D11: =IFERROR(INDEX('GINEBRA MARTIN MILLER 3 4'!$D$7:$D$9,MATCH("ENERO",'GINEBRA MARTIN MILLER 3 4'!$A$7:$A$9,0)),"") -> 15.1 | H11: =IFERROR(INDEX('GINEBRA MARTIN MILLER 3 4'!$D$7:$D$9,MATCH("MAYO",'GINEBRA MARTIN MILLER 3 4'!$A$7:$A$9,0)),"") -> 16.1 | J11: =IFERROR(INDEX('GINEBRA MARTIN MILLER 3 4'!$D$7:$D$9,MATCH("JULIO",'GINEBRA MARTIN MILLER 3 4'!$A$7:$A$9,0)),"") -> 16.1 | L11: ='GINEBRA MARTIN MILLER 3 4'!D7 -> 15.1 | M11: ='GINEBRA MARTIN MILLER 3 4'!D9 -> 16.1 | N11: =IFERROR(M11/L11-1,0) -> 0.066225166 | O11: 1 | P11: ENE 15,10 → MAY 16,10 (+6,6%) | Q11: SUBE
A12: ENVASADO / BEBIDA / OTROS | B12: VOLDIS | C12: AQUARADE ZERO NARANJA VIDRIO 35CL | D12: =IFERROR(INDEX('AQUARADE ZERO NARANJA VIDRIO'!$D$7:$D$10,MATCH("ENERO",'AQUARADE ZERO NARANJA VIDRIO'!$A$7:$A$10,0)),"") -> 31.92 | E12: =IFERROR(INDEX('AQUARADE ZERO NARANJA VIDRIO'!$D$7:$D$10,MATCH("FEBRERO",'AQUARADE ZERO NARANJA VIDRIO'!$A$7:$A$10,0)),"") -> 33.84 | H12: =IFERROR(INDEX('AQUARADE ZERO NARANJA VIDRIO'!$D$7:$D$10,MATCH("MAYO",'AQUARADE ZERO NARANJA VIDRIO'!$A$7:$A$10,0)),"") -> 33.84 | J12: =IFERROR(INDEX('AQUARADE ZERO NARANJA VIDRIO'!$D$7:$D$10,MATCH("JULIO",'AQUARADE ZERO NARANJA VIDRIO'!$A$7:$A$10,0)),"") -> 33.84 | L12: ='AQUARADE ZERO NARANJA VIDRIO'!D7 -> 31.92 | M12: ='AQUARADE ZERO NARANJA VIDRIO'!D10 -> 33.84 | N12: =IFERROR(M12/L12-1,0) -> 0.060150376 | O12: 1 | P12: ENE 31,92 → FEB 33,84 (+6,0%) | Q12: SUBE
A13: ENVASADO / BEBIDA / OTROS | B13: CONSERVAS Y SALAZONES JIMENEZ | C13: VENTRESCA BONITO EXTRA | D13: =IFERROR(INDEX('VENTRESCA BONITO EXTRA'!$D$7:$D$12,MATCH("ENERO",'VENTRESCA BONITO EXTRA'!$A$7:$A$12,0)),"") -> 5.56 | E13: =IFERROR(INDEX('VENTRESCA BONITO EXTRA'!$D$7:$D$12,MATCH("FEBRERO",'VENTRESCA BONITO EXTRA'!$A$7:$A$12,0)),"") -> 5.56 | G13: =IFERROR(INDEX('VENTRESCA BONITO EXTRA'!$D$7:$D$12,MATCH("ABRIL",'VENTRESCA BONITO EXTRA'!$A$7:$A$12,0)),"") -> 5.56 | H13: =IFERROR(INDEX('VENTRESCA BONITO EXTRA'!$D$7:$D$12,MATCH("MAYO",'VENTRESCA BONITO EXTRA'!$A$7:$A$12,0)),"") -> 5.56 | J13: =IFERROR(INDEX('VENTRESCA BONITO EXTRA'!$D$7:$D$12,MATCH("JULIO",'VENTRESCA BONITO EXTRA'!$A$7:$A$12,0)),"") -> 5.86 | K13: =IFERROR(INDEX('VENTRESCA BONITO EXTRA'!$D$7:$D$12,MATCH("AGOSTO",'VENTRESCA BONITO EXTRA'!$A$7:$A$12,0)),"") -> 5.86 | L13: ='VENTRESCA BONITO EXTRA'!D7 -> 5.56 | M13: ='VENTRESCA BONITO EXTRA'!D12 -> 5.86 | N13: =IFERROR(M13/L13-1,0) -> 0.053956835 | O13: 1 | P13: MAY 5,56 → JUL 5,86 (+5,4%) | Q13: SUBE
A14: ENVASADO / BEBIDA / OTROS | B14: EIF DISTRIBUCIONES | C14: SOLAN CABRAS CON GAS | D14: =IFERROR(INDEX('SOLAN CABRAS CON GAS'!$D$7:$D$9,MATCH("ENERO",'SOLAN CABRAS CON GAS'!$A$7:$A$9,0)),"") -> 25.44 | J14: =IFERROR(INDEX('SOLAN CABRAS CON GAS'!$D$7:$D$9,MATCH("JULIO",'SOLAN CABRAS CON GAS'!$A$7:$A$9,0)),"") -> 26.8 | K14: =IFERROR(INDEX('SOLAN CABRAS CON GAS'!$D$7:$D$9,MATCH("AGOSTO",'SOLAN CABRAS CON GAS'!$A$7:$A$9,0)),"") -> 26.8 | L14: ='SOLAN CABRAS CON GAS'!D7 -> 25.44 | M14: ='SOLAN CABRAS CON GAS'!D9 -> 26.8 | N14: =IFERROR(M14/L14-1,0) -> 0.053459119 | O14: 1 | P14: ENE 25,44 → JUL 26,80 (+5,3%) | Q14: SUBE
A15: ENVASADO / BEBIDA / OTROS | B15: VOLDIS | C15: AGUA SOLAN CABRAS VIDRIO 50CL | D15: =IFERROR(INDEX('AGUA SOLAN CABRAS VIDRIO 50C'!$D$7:$D$10,MATCH("ENERO",'AGUA SOLAN CABRAS VIDRIO 50C'!$A$7:$A$10,0)),"") -> 11.68 | E15: =IFERROR(INDEX('AGUA SOLAN CABRAS VIDRIO 50C'!$D$7:$D$10,MATCH("FEBRERO",'AGUA SOLAN CABRAS VIDRIO 50C'!$A$7:$A$10,0)),"") -> 11.68 | H15: =IFERROR(INDEX('AGUA SOLAN CABRAS VIDRIO 50C'!$D$7:$D$10,MATCH("MAYO",'AGUA SOLAN CABRAS VIDRIO 50C'!$A$7:$A$10,0)),"") -> 11.68 | J15: =IFERROR(INDEX('AGUA SOLAN CABRAS VIDRIO 50C'!$D$7:$D$10,MATCH("JULIO",'AGUA SOLAN CABRAS VIDRIO 50C'!$A$7:$A$10,0)),"") -> 12.3 | L15: ='AGUA SOLAN CABRAS VIDRIO 50C'!D7 -> 11.68 | M15: ='AGUA SOLAN CABRAS VIDRIO 50C'!D10 -> 12.3 | N15: =IFERROR(M15/L15-1,0) -> 0.053082192 | O15: 1 | P15: MAY 11,68 → JUL 12,30 (+5,3%) | Q15: SUBE
A16: ENVASADO / BEBIDA / OTROS | B16: VOLDIS | C16: AGUA CON GAS SOLAN CABRAS VIDRIO 33CL | D16: =IFERROR(INDEX('AGUA CON GAS SOLAN CABRAS VI'!$D$7:$D$10,MATCH("ENERO",'AGUA CON GAS SOLAN CABRAS VI'!$A$7:$A$10,0)),"") -> 25.464 | E16: =IFERROR(INDEX('AGUA CON GAS SOLAN CABRAS VI'!$D$7:$D$10,MATCH("FEBRERO",'AGUA CON GAS SOLAN CABRAS VI'!$A$7:$A$10,0)),"") -> 25.464 | H16: =IFERROR(INDEX('AGUA CON GAS SOLAN CABRAS VI'!$D$7:$D$10,MATCH("MAYO",'AGUA CON GAS SOLAN CABRAS VI'!$A$7:$A$10,0)),"") -> 25.464 | J16: =IFERROR(INDEX('AGUA CON GAS SOLAN CABRAS VI'!$D$7:$D$10,MATCH("JULIO",'AGUA CON GAS SOLAN CABRAS VI'!$A$7:$A$10,0)),"") -> 26.81 | L16: ='AGUA CON GAS SOLAN CABRAS VI'!D7 -> 25.464 | M16: ='AGUA CON GAS SOLAN CABRAS VI'!D10 -> 26.81 | N16: =IFERROR(M16/L16-1,0) -> 0.052858938 | O16: 1 | P16: MAY 25,46 → JUL 26,81 (+5,3%) | Q16: SUBE
A17: ENVASADO / BEBIDA / OTROS | B17: CONSERVAS Y SALAZONES JIMENEZ | C17: MOJAMA EXTRA SUPERIOR CHANCA | D17: =IFERROR(INDEX('MOJAMA EXTRA SUPERIOR CHANCA'!$D$7:$D$10,MATCH("ENERO",'MOJAMA EXTRA SUPERIOR CHANCA'!$A$7:$A$10,0)),"") -> 34.6 | H17: =IFERROR(INDEX('MOJAMA EXTRA SUPERIOR CHANCA'!$D$7:$D$10,MATCH("MAYO",'MOJAMA EXTRA SUPERIOR CHANCA'!$A$7:$A$10,0)),"") -> 36.4 | J17: =IFERROR(INDEX('MOJAMA EXTRA SUPERIOR CHANCA'!$D$7:$D$10,MATCH("JULIO",'MOJAMA EXTRA SUPERIOR CHANCA'!$A$7:$A$10,0)),"") -> 36.4 | K17: =IFERROR(INDEX('MOJAMA EXTRA SUPERIOR CHANCA'!$D$7:$D$10,MATCH("AGOSTO",'MOJAMA EXTRA SUPERIOR CHANCA'!$A$7:$A$10,0)),"") -> 36.4 | L17: ='MOJAMA EXTRA SUPERIOR CHANCA'!D7 -> 34.6 | M17: ='MOJAMA EXTRA SUPERIOR CHANCA'!D10 -> 36.4 | N17: =IFERROR(M17/L17-1,0) -> 0.052023121 | O17: 1 | P17: ENE 34,60 → MAY 36,40 (+5,2%) | Q17: SUBE
A18: ENVASADO / BEBIDA / OTROS | B18: VOLDIS | C18: BITTER KAS VIDRIO 20CL | D18: =IFERROR(INDEX('BITTER KAS VIDRIO 20CL'!$D$7:$D$8,MATCH("ENERO",'BITTER KAS VIDRIO 20CL'!$A$7:$A$8,0)),"") -> 37.68 | H18: =IFERROR(INDEX('BITTER KAS VIDRIO 20CL'!$D$7:$D$8,MATCH("MAYO",'BITTER KAS VIDRIO 20CL'!$A$7:$A$8,0)),"") -> 39.6 | L18: ='BITTER KAS VIDRIO 20CL'!D7 -> 37.68 | M18: ='BITTER KAS VIDRIO 20CL'!D8 -> 39.6 | N18: =IFERROR(M18/L18-1,0) -> 0.050955414 | O18: 1 | P18: ENE 37,68 → MAY 39,60 (+5,1%) | Q18: SUBE
A19: ENVASADO / BEBIDA / OTROS | B19: VOLDIS | C19: AQUARADE ZERO LIMON VIDRIO 35CL | D19: =IFERROR(INDEX('AQUARADE ZERO LIMON VIDRIO 3'!$D$7:$D$10,MATCH("ENERO",'AQUARADE ZERO LIMON VIDRIO 3'!$A$7:$A$10,0)),"") -> 31.92 | E19: =IFERROR(INDEX('AQUARADE ZERO LIMON VIDRIO 3'!$D$7:$D$10,MATCH("FEBRERO",'AQUARADE ZERO LIMON VIDRIO 3'!$A$7:$A$10,0)),"") -> 33.84 | H19: =IFERROR(INDEX('AQUARADE ZERO LIMON VIDRIO 3'!$D$7:$D$10,MATCH("MAYO",'AQUARADE ZERO LIMON VIDRIO 3'!$A$7:$A$10,0)),"") -> 33.84 | J19: =IFERROR(INDEX('AQUARADE ZERO LIMON VIDRIO 3'!$D$7:$D$10,MATCH("JULIO",'AQUARADE ZERO LIMON VIDRIO 3'!$A$7:$A$10,0)),"") -> 33.54 | L19: ='AQUARADE ZERO LIMON VIDRIO 3'!D7 -> 31.92 | M19: ='AQUARADE ZERO LIMON VIDRIO 3'!D10 -> 33.54 | N19: =IFERROR(M19/L19-1,0) -> 0.05075188 | O19: 1 | P19: ENE 31,92 → FEB 33,84 (+6,0%) · MAY 33,84 → JUL 33,54 (-0,9%) | Q19: SUBE
A20: ENVASADO / BEBIDA / OTROS | B20: EL ESCRIBANO | C20: LOMO BELLOTA 100 SM | E20: =IFERROR(INDEX('LOMO BELLOTA 100 SM'!$D$7:$D$11,MATCH("FEBRERO",'LOMO BELLOTA 100 SM'!$A$7:$A$11,0)),"") -> 48.6 | G20: =IFERROR(INDEX('LOMO BELLOTA 100 SM'!$D$7:$D$11,MATCH("ABRIL",'LOMO BELLOTA 100 SM'!$A$7:$A$11,0)),"") -> 48.6 | H20: =IFERROR(INDEX('LOMO BELLOTA 100 SM'!$D$7:$D$11,MATCH("MAYO",'LOMO BELLOTA 100 SM'!$A$7:$A$11,0)),"") -> 48.6 | J20: =IFERROR(INDEX('LOMO BELLOTA 100 SM'!$D$7:$D$11,MATCH("JULIO",'LOMO BELLOTA 100 SM'!$A$7:$A$11,0)),"") -> 49.8 | K20: =IFERROR(INDEX('LOMO BELLOTA 100 SM'!$D$7:$D$11,MATCH("AGOSTO",'LOMO BELLOTA 100 SM'!$A$7:$A$11,0)),"") -> 51 | L20: ='LOMO BELLOTA 100 SM'!D7 -> 48.6 | M20: ='LOMO BELLOTA 100 SM'!D11 -> 51 | N20: =IFERROR(M20/L20-1,0) -> 0.049382716 | O20: 2 | P20: MAY 48,60 → JUL 49,80 (+2,5%) · JUL 49,80 → AGO 51,00 (+2,4%) | Q20: SUBE
A21: ENVASADO / BEBIDA / OTROS | B21: EIF DISTRIBUCIONES | C21: COCA COLA ZERO NAC | D21: =IFERROR(INDEX('COCA COLA ZERO NAC'!$D$7:$D$8,MATCH("ENERO",'COCA COLA ZERO NAC'!$A$7:$A$8,0)),"") -> 20.78 | K21: =IFERROR(INDEX('COCA COLA ZERO NAC'!$D$7:$D$8,MATCH("AGOSTO",'COCA COLA ZERO NAC'!$A$7:$A$8,0)),"") -> 21.78 | L21: ='COCA COLA ZERO NAC'!D7 -> 20.78 | M21: ='COCA COLA ZERO NAC'!D8 -> 21.78 | N21: =IFERROR(M21/L21-1,0) -> 0.048123195 | O21: 1 | P21: ENE 20,78 → AGO 21,78 (+4,8%) | Q21: SUBE
A22: ENVASADO / BEBIDA / OTROS | B22: MUNDELA | C22: MANZANILLA SOLEAR 3/8 | D22: =IFERROR(INDEX('MANZANILLA SOLEAR 3 8'!$D$7:$D$10,MATCH("ENERO",'MANZANILLA SOLEAR 3 8'!$A$7:$A$10,0)),"") -> 4.22 | E22: =IFERROR(INDEX('MANZANILLA SOLEAR 3 8'!$D$7:$D$10,MATCH("FEBRERO",'MANZANILLA SOLEAR 3 8'!$A$7:$A$10,0)),"") -> 4.42 | H22: =IFERROR(INDEX('MANZANILLA SOLEAR 3 8'!$D$7:$D$10,MATCH("MAYO",'MANZANILLA SOLEAR 3 8'!$A$7:$A$10,0)),"") -> 4.42 | K22: =IFERROR(INDEX('MANZANILLA SOLEAR 3 8'!$D$7:$D$10,MATCH("AGOSTO",'MANZANILLA SOLEAR 3 8'!$A$7:$A$10,0)),"") -> 4.42 | L22: ='MANZANILLA SOLEAR 3 8'!D7 -> 4.22 | M22: ='MANZANILLA SOLEAR 3 8'!D10 -> 4.42 | N22: =IFERROR(M22/L22-1,0) -> 0.047393365 | O22: 1 | P22: ENE 4,22 → FEB 4,42 (+4,7%) | Q22: SUBE
A23: ENVASADO / BEBIDA / OTROS | B23: DELIPAN | C23: PICOS ARTESANOS 500 GR | D23: =IFERROR(INDEX('PICOS ARTESANOS 500 GR'!$D$7:$D$10,MATCH("ENERO",'PICOS ARTESANOS 500 GR'!$A$7:$A$10,0)),"") -> 10.97 | E23: =IFERROR(INDEX('PICOS ARTESANOS 500 GR'!$D$7:$D$10,MATCH("FEBRERO",'PICOS ARTESANOS 500 GR'!$A$7:$A$10,0)),"") -> 10.97 | G23: =IFERROR(INDEX('PICOS ARTESANOS 500 GR'!$D$7:$D$10,MATCH("ABRIL",'PICOS ARTESANOS 500 GR'!$A$7:$A$10,0)),"") -> 11.48 | H23: =IFERROR(INDEX('PICOS ARTESANOS 500 GR'!$D$7:$D$10,MATCH("MAYO",'PICOS ARTESANOS 500 GR'!$A$7:$A$10,0)),"") -> 11.48 | L23: ='PICOS ARTESANOS 500 GR'!D7 -> 10.97 | M23: ='PICOS ARTESANOS 500 GR'!D10 -> 11.48 | N23: =IFERROR(M23/L23-1,0) -> 0.046490428 | O23: 1 | P23: FEB 10,97 → ABR 11,48 (+4,6%) | Q23: SUBE
A24: ENVASADO / BEBIDA / OTROS | B24: CONSERVAS Y SALAZONES JIMENEZ | C24: ANCHOAS CANTABRICO GRAN RESERVA | D24: =IFERROR(INDEX('ANCHOAS CANTABRICO GRAN RESE'!$D$7:$D$12,MATCH("ENERO",'ANCHOAS CANTABRICO GRAN RESE'!$A$7:$A$12,0)),"") -> 27.46 | E24: =IFERROR(INDEX('ANCHOAS CANTABRICO GRAN RESE'!$D$7:$D$12,MATCH("FEBRERO",'ANCHOAS CANTABRICO GRAN RESE'!$A$7:$A$12,0)),"") -> 27.46 | G24: =IFERROR(INDEX('ANCHOAS CANTABRICO GRAN RESE'!$D$7:$D$12,MATCH("ABRIL",'ANCHOAS CANTABRICO GRAN RESE'!$A$7:$A$12,0)),"") -> 28.66 | H24: =IFERROR(INDEX('ANCHOAS CANTABRICO GRAN RESE'!$D$7:$D$12,MATCH("MAYO",'ANCHOAS CANTABRICO GRAN RESE'!$A$7:$A$12,0)),"") -> 28.66 | J24: =IFERROR(INDEX('ANCHOAS CANTABRICO GRAN RESE'!$D$7:$D$12,MATCH("JULIO",'ANCHOAS CANTABRICO GRAN RESE'!$A$7:$A$12,0)),"") -> 28.66 | K24: =IFERROR(INDEX('ANCHOAS CANTABRICO GRAN RESE'!$D$7:$D$12,MATCH("AGOSTO",'ANCHOAS CANTABRICO GRAN RESE'!$A$7:$A$12,0)),"") -> 28.66 | L24: ='ANCHOAS CANTABRICO GRAN RESE'!D7 -> 27.46 | M24: ='ANCHOAS CANTABRICO GRAN RESE'!D12 -> 28.66 | N24: =IFERROR(M24/L24-1,0) -> 0.043699927 | O24: 1 | P24: FEB 27,46 → ABR 28,66 (+4,4%) | Q24: SUBE
A25: ENVASADO / BEBIDA / OTROS | B25: DITEMA (DIST. TENA) | C25: PEPE YLLERA 3/4 | D25: =IFERROR(INDEX('PEPE YLLERA 3 4'!$D$7:$D$9,MATCH("ENERO",'PEPE YLLERA 3 4'!$A$7:$A$9,0)),"") -> 7.15 | E25: =IFERROR(INDEX('PEPE YLLERA 3 4'!$D$7:$D$9,MATCH("FEBRERO",'PEPE YLLERA 3 4'!$A$7:$A$9,0)),"") -> 7.46 | H25: =IFERROR(INDEX('PEPE YLLERA 3 4'!$D$7:$D$9,MATCH("MAYO",'PEPE YLLERA 3 4'!$A$7:$A$9,0)),"") -> 7.46 | L25: ='PEPE YLLERA 3 4'!D7 -> 7.15 | M25: ='PEPE YLLERA 3 4'!D9 -> 7.46 | N25: =IFERROR(M25/L25-1,0) -> 0.043356643 | O25: 1 | P25: ENE 7,15 → FEB 7,46 (+4,3%) | Q25: SUBE
A26: ENVASADO / BEBIDA / OTROS | B26: EIF DISTRIBUCIONES | C26: SCHWEPPES TONICA 28 UDS | D26: =IFERROR(INDEX('SCHWEPPES TONICA 28 UDS'!$D$7:$D$8,MATCH("ENERO",'SCHWEPPES TONICA 28 UDS'!$A$7:$A$8,0)),"") -> 23.84 | K26: =IFERROR(INDEX('SCHWEPPES TONICA 28 UDS'!$D$7:$D$8,MATCH("AGOSTO",'SCHWEPPES TONICA 28 UDS'!$A$7:$A$8,0)),"") -> 24.84 | L26: ='SCHWEPPES TONICA 28 UDS'!D7 -> 23.84 | M26: ='SCHWEPPES TONICA 28 UDS'!D8 -> 24.84 | N26: =IFERROR(M26/L26-1,0) -> 0.041946309 | O26: 1 | P26: ENE 23,84 → AGO 24,84 (+4,2%) | Q26: SUBE
A27: ENVASADO / BEBIDA / OTROS | B27: VOLDIS | C27: CASERA LIMON 1L | D27: =IFERROR(INDEX('CASERA LIMON 1L'!$D$7:$D$10,MATCH("ENERO",'CASERA LIMON 1L'!$A$7:$A$10,0)),"") -> 23.64 | E27: =IFERROR(INDEX('CASERA LIMON 1L'!$D$7:$D$10,MATCH("FEBRERO",'CASERA LIMON 1L'!$A$7:$A$10,0)),"") -> 24.61 | H27: =IFERROR(INDEX('CASERA LIMON 1L'!$D$7:$D$10,MATCH("MAYO",'CASERA LIMON 1L'!$A$7:$A$10,0)),"") -> 24.61 | J27: =IFERROR(INDEX('CASERA LIMON 1L'!$D$7:$D$10,MATCH("JULIO",'CASERA LIMON 1L'!$A$7:$A$10,0)),"") -> 24.61 | L27: ='CASERA LIMON 1L'!D7 -> 23.64 | M27: ='CASERA LIMON 1L'!D10 -> 24.61 | N27: =IFERROR(M27/L27-1,0) -> 0.041032149 | O27: 1 | P27: ENE 23,64 → FEB 24,61 (+4,1%) | Q27: SUBE
A28: ENVASADO / BEBIDA / OTROS | B28: VOLDIS | C28: CASERA GASEOSA 1L | D28: =IFERROR(INDEX('CASERA GASEOSA 1L'!$D$7:$D$10,MATCH("ENERO",'CASERA GASEOSA 1L'!$A$7:$A$10,0)),"") -> 20.64 | E28: =IFERROR(INDEX('CASERA GASEOSA 1L'!$D$7:$D$10,MATCH("FEBRERO",'CASERA GASEOSA 1L'!$A$7:$A$10,0)),"") -> 21.48 | H28: =IFERROR(INDEX('CASERA GASEOSA 1L'!$D$7:$D$10,MATCH("MAYO",'CASERA GASEOSA 1L'!$A$7:$A$10,0)),"") -> 21.48 | J28: =IFERROR(INDEX('CASERA GASEOSA 1L'!$D$7:$D$10,MATCH("JULIO",'CASERA GASEOSA 1L'!$A$7:$A$10,0)),"") -> 21.48 | L28: ='CASERA GASEOSA 1L'!D7 -> 20.64 | M28: ='CASERA GASEOSA 1L'!D10 -> 21.48 | N28: =IFERROR(M28/L28-1,0) -> 0.040697674 | O28: 1 | P28: ENE 20,64 → FEB 21,48 (+4,1%) | Q28: SUBE
A29: ENVASADO / BEBIDA / OTROS | B29: DELIPAN | C29: PAN MOLDE BRIOCHE | D29: =IFERROR(INDEX('PAN MOLDE BRIOCHE'!$D$7:$D$12,MATCH("ENERO",'PAN MOLDE BRIOCHE'!$A$7:$A$12,0)),"") -> 84.7 | E29: =IFERROR(INDEX('PAN MOLDE BRIOCHE'!$D$7:$D$12,MATCH("FEBRERO",'PAN MOLDE BRIOCHE'!$A$7:$A$12,0)),"") -> 84.7 | G29: =IFERROR(INDEX('PAN MOLDE BRIOCHE'!$D$7:$D$12,MATCH("ABRIL",'PAN MOLDE BRIOCHE'!$A$7:$A$12,0)),"") -> 88.09 | H29: =IFERROR(INDEX('PAN MOLDE BRIOCHE'!$D$7:$D$12,MATCH("MAYO",'PAN MOLDE BRIOCHE'!$A$7:$A$12,0)),"") -> 88.09 | J29: =IFERROR(INDEX('PAN MOLDE BRIOCHE'!$D$7:$D$12,MATCH("JULIO",'PAN MOLDE BRIOCHE'!$A$7:$A$12,0)),"") -> 88.09 | K29: =IFERROR(INDEX('PAN MOLDE BRIOCHE'!$D$7:$D$12,MATCH("AGOSTO",'PAN MOLDE BRIOCHE'!$A$7:$A$12,0)),"") -> 88.09 | L29: ='PAN MOLDE BRIOCHE'!D7 -> 84.7 | M29: ='PAN MOLDE BRIOCHE'!D12 -> 88.09 | N29: =IFERROR(M29/L29-1,0) -> 0.040023613 | O29: 1 | P29: FEB 84,70 → ABR 88,09 (+4,0%) | Q29: SUBE
A30: ENVASADO / BEBIDA / OTROS | B30: MUNDELA | C30: PACO GARCIA CRIANZA 3/4 | D30: =IFERROR(INDEX('PACO GARCIA CRIANZA 3 4'!$D$7:$D$10,MATCH("ENERO",'PACO GARCIA CRIANZA 3 4'!$A$7:$A$10,0)),"") -> 5.1 | E30: =IFERROR(INDEX('PACO GARCIA CRIANZA 3 4'!$D$7:$D$10,MATCH("FEBRERO",'PACO GARCIA CRIANZA 3 4'!$A$7:$A$10,0)),"") -> 5.1 | H30: =IFERROR(INDEX('PACO GARCIA CRIANZA 3 4'!$D$7:$D$10,MATCH("MAYO",'PACO GARCIA CRIANZA 3 4'!$A$7:$A$10,0)),"") -> 5.3 | K30: =IFERROR(INDEX('PACO GARCIA CRIANZA 3 4'!$D$7:$D$10,MATCH("AGOSTO",'PACO GARCIA CRIANZA 3 4'!$A$7:$A$10,0)),"") -> 5.3 | L30: ='PACO GARCIA CRIANZA 3 4'!D7 -> 5.1 | M30: ='PACO GARCIA CRIANZA 3 4'!D10 -> 5.3 | N30: =IFERROR(M30/L30-1,0) -> 0.039215686 | O30: 1 | P30: FEB 5,10 → MAY 5,30 (+3,9%) | Q30: SUBE
A31: ENVASADO / BEBIDA / OTROS | B31: MUNDELA | C31: RAMON BILBAO BLANCO VERDEJO 3/4 | D31: =IFERROR(INDEX('RAMON BILBAO BLANCO VERDEJO'!$D$7:$D$11,MATCH("ENERO",'RAMON BILBAO BLANCO VERDEJO'!$A$7:$A$11,0)),"") -> 4.5 | E31: =IFERROR(INDEX('RAMON BILBAO BLANCO VERDEJO'!$D$7:$D$11,MATCH("FEBRERO",'RAMON BILBAO BLANCO VERDEJO'!$A$7:$A$11,0)),"") -> 4.5 | H31: =IFERROR(INDEX('RAMON BILBAO BLANCO VERDEJO'!$D$7:$D$11,MATCH("MAYO",'RAMON BILBAO BLANCO VERDEJO'!$A$7:$A$11,0)),"") -> 4.67 | J31: =IFERROR(INDEX('RAMON BILBAO BLANCO VERDEJO'!$D$7:$D$11,MATCH("JULIO",'RAMON BILBAO BLANCO VERDEJO'!$A$7:$A$11,0)),"") -> 4.67 | K31: =IFERROR(INDEX('RAMON BILBAO BLANCO VERDEJO'!$D$7:$D$11,MATCH("AGOSTO",'RAMON BILBAO BLANCO VERDEJO'!$A$7:$A$11,0)),"") -> 4.67 | L31: ='RAMON BILBAO BLANCO VERDEJO'!D7 -> 4.5 | M31: ='RAMON BILBAO BLANCO VERDEJO'!D11 -> 4.67 | N31: =IFERROR(M31/L31-1,0) -> 0.037777778 | O31: 1 | P31: FEB 4,50 → MAY 4,67 (+3,8%) | Q31: SUBE
A32: ENVASADO / BEBIDA / OTROS | B32: DITEMA (DIST. TENA) | C32: GODELLO VINAREDO | D32: =IFERROR(INDEX('GODELLO VINAREDO'!$D$7:$D$11,MATCH("ENERO",'GODELLO VINAREDO'!$A$7:$A$11,0)),"") -> 6.78 | E32: =IFERROR(INDEX('GODELLO VINAREDO'!$D$7:$D$11,MATCH("FEBRERO",'GODELLO VINAREDO'!$A$7:$A$11,0)),"") -> 6.78 | H32: =IFERROR(INDEX('GODELLO VINAREDO'!$D$7:$D$11,MATCH("MAYO",'GODELLO VINAREDO'!$A$7:$A$11,0)),"") -> 7.03 | J32: =IFERROR(INDEX('GODELLO VINAREDO'!$D$7:$D$11,MATCH("JULIO",'GODELLO VINAREDO'!$A$7:$A$11,0)),"") -> 7.03 | K32: =IFERROR(INDEX('GODELLO VINAREDO'!$D$7:$D$11,MATCH("AGOSTO",'GODELLO VINAREDO'!$A$7:$A$11,0)),"") -> 7.03 | L32: ='GODELLO VINAREDO'!D7 -> 6.78 | M32: ='GODELLO VINAREDO'!D11 -> 7.03 | N32: =IFERROR(M32/L32-1,0) -> 0.036873156 | O32: 1 | P32: FEB 6,78 → MAY 7,03 (+3,7%) | Q32: SUBE
A33: ENVASADO / BEBIDA / OTROS | B33: DITEMA (DIST. TENA) | C33: SENORIO FITERO ROBLE | D33: =IFERROR(INDEX('SENORIO FITERO ROBLE'!$D$7:$D$11,MATCH("ENERO",'SENORIO FITERO ROBLE'!$A$7:$A$11,0)),"") -> 2.72 | E33: =IFERROR(INDEX('SENORIO FITERO ROBLE'!$D$7:$D$11,MATCH("FEBRERO",'SENORIO FITERO ROBLE'!$A$7:$A$11,0)),"") -> 2.72 | H33: =IFERROR(INDEX('SENORIO FITERO ROBLE'!$D$7:$D$11,MATCH("MAYO",'SENORIO FITERO ROBLE'!$A$7:$A$11,0)),"") -> 2.82 | J33: =IFERROR(INDEX('SENORIO FITERO ROBLE'!$D$7:$D$11,MATCH("JULIO",'SENORIO FITERO ROBLE'!$A$7:$A$11,0)),"") -> 2.82 | K33: =IFERROR(INDEX('SENORIO FITERO ROBLE'!$D$7:$D$11,MATCH("AGOSTO",'SENORIO FITERO ROBLE'!$A$7:$A$11,0)),"") -> 2.82 | L33: ='SENORIO FITERO ROBLE'!D7 -> 2.72 | M33: ='SENORIO FITERO ROBLE'!D11 -> 2.82 | N33: =IFERROR(M33/L33-1,0) -> 0.036764706 | O33: 1 | P33: FEB 2,72 → MAY 2,82 (+3,7%) | Q33: SUBE
A34: ENVASADO / BEBIDA / OTROS | B34: MUNDELA | C34: CORIMBO | D34: =IFERROR(INDEX(CORIMBO!$D$7:$D$11,MATCH("ENERO",CORIMBO!$A$7:$A$11,0)),"") -> 13.42 | E34: =IFERROR(INDEX(CORIMBO!$D$7:$D$11,MATCH("FEBRERO",CORIMBO!$A$7:$A$11,0)),"") -> 13.42 | H34: =IFERROR(INDEX(CORIMBO!$D$7:$D$11,MATCH("MAYO",CORIMBO!$A$7:$A$11,0)),"") -> 13.91 | J34: =IFERROR(INDEX(CORIMBO!$D$7:$D$11,MATCH("JULIO",CORIMBO!$A$7:$A$11,0)),"") -> 13.91 | K34: =IFERROR(INDEX(CORIMBO!$D$7:$D$11,MATCH("AGOSTO",CORIMBO!$A$7:$A$11,0)),"") -> 13.91 | L34: =CORIMBO!D7 -> 13.42 | M34: =CORIMBO!D11 -> 13.91 | N34: =IFERROR(M34/L34-1,0) -> 0.036512668 | O34: 1 | P34: FEB 13,42 → MAY 13,91 (+3,7%) | Q34: SUBE
A35: ENVASADO / BEBIDA / OTROS | B35: VOLDIS | C35: SCHWEPPES TONICA VIDRIO 20CL | D35: =IFERROR(INDEX('SCHWEPPES TONICA VIDRIO 20CL'!$D$7:$D$10,MATCH("ENERO",'SCHWEPPES TONICA VIDRIO 20CL'!$A$7:$A$10,0)),"") -> 30.8 | E35: =IFERROR(INDEX('SCHWEPPES TONICA VIDRIO 20CL'!$D$7:$D$10,MATCH("FEBRERO",'SCHWEPPES TONICA VIDRIO 20CL'!$A$7:$A$10,0)),"") -> 31.92 | H35: =IFERROR(INDEX('SCHWEPPES TONICA VIDRIO 20CL'!$D$7:$D$10,MATCH("MAYO",'SCHWEPPES TONICA VIDRIO 20CL'!$A$7:$A$10,0)),"") -> 31.92 | J35: =IFERROR(INDEX('SCHWEPPES TONICA VIDRIO 20CL'!$D$7:$D$10,MATCH("JULIO",'SCHWEPPES TONICA VIDRIO 20CL'!$A$7:$A$10,0)),"") -> 31.92 | L35: ='SCHWEPPES TONICA VIDRIO 20CL'!D7 -> 30.8 | M35: ='SCHWEPPES TONICA VIDRIO 20CL'!D10 -> 31.92 | N35: =IFERROR(M35/L35-1,0) -> 0.036363636 | O35: 1 | P35: ENE 30,80 → FEB 31,92 (+3,6%) | Q35: SUBE
A36: ENVASADO / BEBIDA / OTROS | B36: MUNDELA | C36: RODA RESERVA 3/4 | D36: =IFERROR(INDEX('RODA RESERVA 3 4'!$D$7:$D$10,MATCH("ENERO",'RODA RESERVA 3 4'!$A$7:$A$10,0)),"") -> 20.63 | E36: =IFERROR(INDEX('RODA RESERVA 3 4'!$D$7:$D$10,MATCH("FEBRERO",'RODA RESERVA 3 4'!$A$7:$A$10,0)),"") -> 20.63 | H36: =IFERROR(INDEX('RODA RESERVA 3 4'!$D$7:$D$10,MATCH("MAYO",'RODA RESERVA 3 4'!$A$7:$A$10,0)),"") -> 21.38 | J36: =IFERROR(INDEX('RODA RESERVA 3 4'!$D$7:$D$10,MATCH("JULIO",'RODA RESERVA 3 4'!$A$7:$A$10,0)),"") -> 21.38 | L36: ='RODA RESERVA 3 4'!D7 -> 20.63 | M36: ='RODA RESERVA 3 4'!D10 -> 21.38 | N36: =IFERROR(M36/L36-1,0) -> 0.036354823 | O36: 1 | P36: FEB 20,63 → MAY 21,38 (+3,6%) | Q36: SUBE
A37: ENVASADO / BEBIDA / OTROS | B37: DITEMA (DIST. TENA) | C37: ALBARINO MAR FRADES | D37: =IFERROR(INDEX('ALBARINO MAR FRADES'!$D$7:$D$11,MATCH("ENERO",'ALBARINO MAR FRADES'!$A$7:$A$11,0)),"") -> 11.02 | E37: =IFERROR(INDEX('ALBARINO MAR FRADES'!$D$7:$D$11,MATCH("FEBRERO",'ALBARINO MAR FRADES'!$A$7:$A$11,0)),"") -> 11.02 | H37: =IFERROR(INDEX('ALBARINO MAR FRADES'!$D$7:$D$11,MATCH("MAYO",'ALBARINO MAR FRADES'!$A$7:$A$11,0)),"") -> 11.42 | J37: =IFERROR(INDEX('ALBARINO MAR FRADES'!$D$7:$D$11,MATCH("JULIO",'ALBARINO MAR FRADES'!$A$7:$A$11,0)),"") -> 11.42 | K37: =IFERROR(INDEX('ALBARINO MAR FRADES'!$D$7:$D$11,MATCH("AGOSTO",'ALBARINO MAR FRADES'!$A$7:$A$11,0)),"") -> 11.42 | L37: ='ALBARINO MAR FRADES'!D7 -> 11.02 | M37: ='ALBARINO MAR FRADES'!D11 -> 11.42 | N37: =IFERROR(M37/L37-1,0) -> 0.036297641 | O37: 1 | P37: FEB 11,02 → MAY 11,42 (+3,6%) | Q37: SUBE
A38: ENVASADO / BEBIDA / OTROS | B38: MUNDELA | C38: VINA MAYOR VERDEJO | D38: =IFERROR(INDEX('VINA MAYOR VERDEJO'!$D$7:$D$9,MATCH("ENERO",'VINA MAYOR VERDEJO'!$A$7:$A$9,0)),"") -> 5.88 | E38: =IFERROR(INDEX('VINA MAYOR VERDEJO'!$D$7:$D$9,MATCH("FEBRERO",'VINA MAYOR VERDEJO'!$A$7:$A$9,0)),"") -> 5.88 | H38: =IFERROR(INDEX('VINA MAYOR VERDEJO'!$D$7:$D$9,MATCH("MAYO",'VINA MAYOR VERDEJO'!$A$7:$A$9,0)),"") -> 6.08 | L38: ='VINA MAYOR VERDEJO'!D7 -> 5.88 | M38: ='VINA MAYOR VERDEJO'!D9 -> 6.08 | N38: =IFERROR(M38/L38-1,0) -> 0.034013605 | O38: 1 | P38: FEB 5,88 → MAY 6,08 (+3,4%) | Q38: SUBE
A39: ENVASADO / BEBIDA / OTROS | B39: VOLDIS | C39: SEVEN UP FREE VIDRIO 20CL | D39: =IFERROR(INDEX('SEVEN UP FREE VIDRIO 20CL'!$D$7:$D$9,MATCH("ENERO",'SEVEN UP FREE VIDRIO 20CL'!$A$7:$A$9,0)),"") -> 22.56 | E39: =IFERROR(INDEX('SEVEN UP FREE VIDRIO 20CL'!$D$7:$D$9,MATCH("FEBRERO",'SEVEN UP FREE VIDRIO 20CL'!$A$7:$A$9,0)),"") -> 23.28 | H39: =IFERROR(INDEX('SEVEN UP FREE VIDRIO 20CL'!$D$7:$D$9,MATCH("MAYO",'SEVEN UP FREE VIDRIO 20CL'!$A$7:$A$9,0)),"") -> 23.28 | L39: ='SEVEN UP FREE VIDRIO 20CL'!D7 -> 22.56 | M39: ='SEVEN UP FREE VIDRIO 20CL'!D9 -> 23.28 | N39: =IFERROR(M39/L39-1,0) -> 0.031914894 | O39: 1 | P39: ENE 22,56 → FEB 23,28 (+3,2%) | Q39: SUBE
A40: ENVASADO / BEBIDA / OTROS | B40: VOLDIS | C40: LIPTON ZERO LIMON VIDRIO 35CL | D40: =IFERROR(INDEX('LIPTON ZERO LIMON VIDRIO 35C'!$D$7:$D$10,MATCH("ENERO",'LIPTON ZERO LIMON VIDRIO 35C'!$A$7:$A$10,0)),"") -> 31.92 | E40: =IFERROR(INDEX('LIPTON ZERO LIMON VIDRIO 35C'!$D$7:$D$10,MATCH("FEBRERO",'LIPTON ZERO LIMON VIDRIO 35C'!$A$7:$A$10,0)),"") -> 32.88 | H40: =IFERROR(INDEX('LIPTON ZERO LIMON VIDRIO 35C'!$D$7:$D$10,MATCH("MAYO",'LIPTON ZERO LIMON VIDRIO 35C'!$A$7:$A$10,0)),"") -> 32.88 | J40: =IFERROR(INDEX('LIPTON ZERO LIMON VIDRIO 35C'!$D$7:$D$10,MATCH("JULIO",'LIPTON ZERO LIMON VIDRIO 35C'!$A$7:$A$10,0)),"") -> 32.88 | L40: ='LIPTON ZERO LIMON VIDRIO 35C'!D7 -> 31.92 | M40: ='LIPTON ZERO LIMON VIDRIO 35C'!D10 -> 32.88 | N40: =IFERROR(M40/L40-1,0) -> 0.030075188 | O40: 1 | P40: ENE 31,92 → FEB 32,88 (+3,0%) | Q40: SUBE
A41: ENVASADO / BEBIDA / OTROS | B41: MUNDELA | C41: R B EDI LIM EARLY HARVEST ROSADO | D41: =IFERROR(INDEX('R B EDI LIM EARLY HARVEST RO'!$D$7:$D$10,MATCH("ENERO",'R B EDI LIM EARLY HARVEST RO'!$A$7:$A$10,0)),"") -> 7.69 | E41: =IFERROR(INDEX('R B EDI LIM EARLY HARVEST RO'!$D$7:$D$10,MATCH("FEBRERO",'R B EDI LIM EARLY HARVEST RO'!$A$7:$A$10,0)),"") -> 7.69 | H41: =IFERROR(INDEX('R B EDI LIM EARLY HARVEST RO'!$D$7:$D$10,MATCH("MAYO",'R B EDI LIM EARLY HARVEST RO'!$A$7:$A$10,0)),"") -> 7.88 | J41: =IFERROR(INDEX('R B EDI LIM EARLY HARVEST RO'!$D$7:$D$10,MATCH("JULIO",'R B EDI LIM EARLY HARVEST RO'!$A$7:$A$10,0)),"") -> 7.88 | L41: ='R B EDI LIM EARLY HARVEST RO'!D7 -> 7.69 | M41: ='R B EDI LIM EARLY HARVEST RO'!D10 -> 7.88 | N41: =IFERROR(M41/L41-1,0) -> 0.024707412 | O41: 1 | P41: FEB 7,69 → MAY 7,88 (+2,5%) | Q41: SUBE
A42: ENVASADO / BEBIDA / OTROS | B42: DITEMA (DIST. TENA) | C42: POMMERY ROYAL BRUT 3/4 | D42: =IFERROR(INDEX('POMMERY ROYAL BRUT 3 4'!$D$7:$D$9,MATCH("ENERO",'POMMERY ROYAL BRUT 3 4'!$A$7:$A$9,0)),"") -> 35.49 | E42: =IFERROR(INDEX('POMMERY ROYAL BRUT 3 4'!$D$7:$D$9,MATCH("FEBRERO",'POMMERY ROYAL BRUT 3 4'!$A$7:$A$9,0)),"") -> 35.49 | H42: =IFERROR(INDEX('POMMERY ROYAL BRUT 3 4'!$D$7:$D$9,MATCH("MAYO",'POMMERY ROYAL BRUT 3 4'!$A$7:$A$9,0)),"") -> 36.35 | L42: ='POMMERY ROYAL BRUT 3 4'!D7 -> 35.49 | M42: ='POMMERY ROYAL BRUT 3 4'!D9 -> 36.35 | N42: =IFERROR(M42/L42-1,0) -> 0.024232178 | O42: 1 | P42: FEB 35,49 → MAY 36,35 (+2,4%) | Q42: SUBE
A43: ENVASADO / BEBIDA / OTROS | B43: DITEMA (DIST. TENA) | C43: GODELLO MAR FRADES | E43: =IFERROR(INDEX('GODELLO MAR FRADES'!$D$7:$D$8,MATCH("FEBRERO",'GODELLO MAR FRADES'!$A$7:$A$8,0)),"") -> 17.63 | H43: =IFERROR(INDEX('GODELLO MAR FRADES'!$D$7:$D$8,MATCH("MAYO",'GODELLO MAR FRADES'!$A$7:$A$8,0)),"") -> 18.03 | L43: ='GODELLO MAR FRADES'!D7 -> 17.63 | M43: ='GODELLO MAR FRADES'!D8 -> 18.03 | N43: =IFERROR(M43/L43-1,0) -> 0.022688599 | O43: 1 | P43: FEB 17,63 → MAY 18,03 (+2,3%) | Q43: SUBE
A44: ENVASADO / BEBIDA / OTROS | B44: VOLDIS | C44: SCHWEPPES LIMON LOW CAL VIDRIO 20CL | D44: =IFERROR(INDEX('SCHWEPPES LIMON LOW CAL VIDR'!$D$7:$D$10,MATCH("ENERO",'SCHWEPPES LIMON LOW CAL VIDR'!$A$7:$A$10,0)),"") -> 25.48 | E44: =IFERROR(INDEX('SCHWEPPES LIMON LOW CAL VIDR'!$D$7:$D$10,MATCH("FEBRERO",'SCHWEPPES LIMON LOW CAL VIDR'!$A$7:$A$10,0)),"") -> 26.04 | H44: =IFERROR(INDEX('SCHWEPPES LIMON LOW CAL VIDR'!$D$7:$D$10,MATCH("MAYO",'SCHWEPPES LIMON LOW CAL VIDR'!$A$7:$A$10,0)),"") -> 26.04 | J44: =IFERROR(INDEX('SCHWEPPES LIMON LOW CAL VIDR'!$D$7:$D$10,MATCH("JULIO",'SCHWEPPES LIMON LOW CAL VIDR'!$A$7:$A$10,0)),"") -> 26.04 | L44: ='SCHWEPPES LIMON LOW CAL VIDR'!D7 -> 25.48 | M44: ='SCHWEPPES LIMON LOW CAL VIDR'!D10 -> 26.04 | N44: =IFERROR(M44/L44-1,0) -> 0.021978022 | O44: 1 | P44: ENE 25,48 → FEB 26,04 (+2,2%) | Q44: SUBE
A45: ENVASADO / BEBIDA / OTROS | B45: VOLDIS | C45: SCHWEPPES NARANJA LOW CAL VIDRIO 20CL | D45: =IFERROR(INDEX('SCHWEPPES NARANJA LOW CAL VI'!$D$7:$D$10,MATCH("ENERO",'SCHWEPPES NARANJA LOW CAL VI'!$A$7:$A$10,0)),"") -> 25.48 | E45: =IFERROR(INDEX('SCHWEPPES NARANJA LOW CAL VI'!$D$7:$D$10,MATCH("FEBRERO",'SCHWEPPES NARANJA LOW CAL VI'!$A$7:$A$10,0)),"") -> 26.04 | H45: =IFERROR(INDEX('SCHWEPPES NARANJA LOW CAL VI'!$D$7:$D$10,MATCH("MAYO",'SCHWEPPES NARANJA LOW CAL VI'!$A$7:$A$10,0)),"") -> 26.04 | J45: =IFERROR(INDEX('SCHWEPPES NARANJA LOW CAL VI'!$D$7:$D$10,MATCH("JULIO",'SCHWEPPES NARANJA LOW CAL VI'!$A$7:$A$10,0)),"") -> 26.04 | L45: ='SCHWEPPES NARANJA LOW CAL VI'!D7 -> 25.48 | M45: ='SCHWEPPES NARANJA LOW CAL VI'!D10 -> 26.04 | N45: =IFERROR(M45/L45-1,0) -> 0.021978022 | O45: 1 | P45: ENE 25,48 → FEB 26,04 (+2,2%) | Q45: SUBE
A46: ENVASADO / BEBIDA / OTROS | B46: MAGOASE | C46: CUAD A O SUAVE GUADALIMAR 5L | D46: =IFERROR(INDEX('CUAD A O SUAVE GUADALIMAR 5L'!$D$7:$D$12,MATCH("ENERO",'CUAD A O SUAVE GUADALIMAR 5L'!$A$7:$A$12,0)),"") -> 23.95 | E46: =IFERROR(INDEX('CUAD A O SUAVE GUADALIMAR 5L'!$D$7:$D$12,MATCH("FEBRERO",'CUAD A O SUAVE GUADALIMAR 5L'!$A$7:$A$12,0)),"") -> 24.95 | G46: =IFERROR(INDEX('CUAD A O SUAVE GUADALIMAR 5L'!$D$7:$D$12,MATCH("ABRIL",'CUAD A O SUAVE GUADALIMAR 5L'!$A$7:$A$12,0)),"") -> 24.95 | H46: =IFERROR(INDEX('CUAD A O SUAVE GUADALIMAR 5L'!$D$7:$D$12,MATCH("MAYO",'CUAD A O SUAVE GUADALIMAR 5L'!$A$7:$A$12,0)),"") -> 23.95 | J46: =IFERROR(INDEX('CUAD A O SUAVE GUADALIMAR 5L'!$D$7:$D$12,MATCH("JULIO",'CUAD A O SUAVE GUADALIMAR 5L'!$A$7:$A$12,0)),"") -> 23.95 | K46: =IFERROR(INDEX('CUAD A O SUAVE GUADALIMAR 5L'!$D$7:$D$12,MATCH("AGOSTO",'CUAD A O SUAVE GUADALIMAR 5L'!$A$7:$A$12,0)),"") -> 24.45 | L46: ='CUAD A O SUAVE GUADALIMAR 5L'!D7 -> 23.95 | M46: ='CUAD A O SUAVE GUADALIMAR 5L'!D12 -> 24.45 | N46: =IFERROR(M46/L46-1,0) -> 0.020876827 | O46: 2 | P46: ENE 23,95 → FEB 24,95 (+4,2%) · ABR 24,95 → MAY 23,95 (-4,0%) · JUL 23,95 → AGO 24,45 (+2,1%) | Q46: SUBE
A47: ENVASADO / BEBIDA / OTROS | B47: MUNDELA | C47: VINAGRE JEREZ RESERVA AL MOSCATEL | D47: =IFERROR(INDEX('VINAGRE JEREZ RESERVA AL MOS'!$D$7:$D$11,MATCH("ENERO",'VINAGRE JEREZ RESERVA AL MOS'!$A$7:$A$11,0)),"") -> 5.33 | E47: =IFERROR(INDEX('VINAGRE JEREZ RESERVA AL MOS'!$D$7:$D$11,MATCH("FEBRERO",'VINAGRE JEREZ RESERVA AL MOS'!$A$7:$A$11,0)),"") -> 5.33 | H47: =IFERROR(INDEX('VINAGRE JEREZ RESERVA AL MOS'!$D$7:$D$11,MATCH("MAYO",'VINAGRE JEREZ RESERVA AL MOS'!$A$7:$A$11,0)),"") -> 5.44 | J47: =IFERROR(INDEX('VINAGRE JEREZ RESERVA AL MOS'!$D$7:$D$11,MATCH("JULIO",'VINAGRE JEREZ RESERVA AL MOS'!$A$7:$A$11,0)),"") -> 5.44 | K47: =IFERROR(INDEX('VINAGRE JEREZ RESERVA AL MOS'!$D$7:$D$11,MATCH("AGOSTO",'VINAGRE JEREZ RESERVA AL MOS'!$A$7:$A$11,0)),"") -> 5.44 | L47: ='VINAGRE JEREZ RESERVA AL MOS'!D7 -> 5.33 | M47: ='VINAGRE JEREZ RESERVA AL MOS'!D11 -> 5.44 | N47: =IFERROR(M47/L47-1,0) -> 0.020637899 | O47: 1 | P47: FEB 5,33 → MAY 5,44 (+2,1%) | Q47: SUBE
A48: ENVASADO / BEBIDA / OTROS | B48: FCO JAVIER LABRADOR | C48: FLOR ALCACHOFA CONFITADA EN AOVE | D48: =IFERROR(INDEX('FLOR ALCACHOFA CONFITADA EN'!$D$7:$D$10,MATCH("ENERO",'FLOR ALCACHOFA CONFITADA EN'!$A$7:$A$10,0)),"") -> 22.45 | E48: =IFERROR(INDEX('FLOR ALCACHOFA CONFITADA EN'!$D$7:$D$10,MATCH("FEBRERO",'FLOR ALCACHOFA CONFITADA EN'!$A$7:$A$10,0)),"") -> 22.45 | G48: =IFERROR(INDEX('FLOR ALCACHOFA CONFITADA EN'!$D$7:$D$10,MATCH("ABRIL",'FLOR ALCACHOFA CONFITADA EN'!$A$7:$A$10,0)),"") -> 22.9 | H48: =IFERROR(INDEX('FLOR ALCACHOFA CONFITADA EN'!$D$7:$D$10,MATCH("MAYO",'FLOR ALCACHOFA CONFITADA EN'!$A$7:$A$10,0)),"") -> 22.9 | L48: ='FLOR ALCACHOFA CONFITADA EN'!D7 -> 22.45 | M48: ='FLOR ALCACHOFA CONFITADA EN'!D10 -> 22.9 | N48: =IFERROR(M48/L48-1,0) -> 0.020044543 | O48: 1 | P48: FEB 22,45 → ABR 22,90 (+2,0%) | Q48: SUBE
A49: ENVASADO / BEBIDA / OTROS | B49: MUNDELA | C49: BARBADILLO VI MOSCATO FRIZZANTE | E49: =IFERROR(INDEX('BARBADILLO VI MOSCATO FRIZZA'!$D$7:$D$10,MATCH("FEBRERO",'BARBADILLO VI MOSCATO FRIZZA'!$A$7:$A$10,0)),"") -> 5.52 | H49: =IFERROR(INDEX('BARBADILLO VI MOSCATO FRIZZA'!$D$7:$D$10,MATCH("MAYO",'BARBADILLO VI MOSCATO FRIZZA'!$A$7:$A$10,0)),"") -> 5.63 | J49: =IFERROR(INDEX('BARBADILLO VI MOSCATO FRIZZA'!$D$7:$D$10,MATCH("JULIO",'BARBADILLO VI MOSCATO FRIZZA'!$A$7:$A$10,0)),"") -> 5.63 | K49: =IFERROR(INDEX('BARBADILLO VI MOSCATO FRIZZA'!$D$7:$D$10,MATCH("AGOSTO",'BARBADILLO VI MOSCATO FRIZZA'!$A$7:$A$10,0)),"") -> 5.63 | L49: ='BARBADILLO VI MOSCATO FRIZZA'!D7 -> 5.52 | M49: ='BARBADILLO VI MOSCATO FRIZZA'!D10 -> 5.63 | N49: =IFERROR(M49/L49-1,0) -> 0.019927536 | O49: 1 | P49: FEB 5,52 → MAY 5,63 (+2,0%) | Q49: SUBE
A50: ENVASADO / BEBIDA / OTROS | B50: SUBMARINER | C50: MAESTRO DOBEL DIAMANTE REPOSADO 0,70 | D50: =IFERROR(INDEX('MAESTRO DOBEL DIAMANTE REPOS'!$D$7:$D$11,MATCH("ENERO",'MAESTRO DOBEL DIAMANTE REPOS'!$A$7:$A$11,0)),"") -> 54.14 | E50: =IFERROR(INDEX('MAESTRO DOBEL DIAMANTE REPOS'!$D$7:$D$11,MATCH("FEBRERO",'MAESTRO DOBEL DIAMANTE REPOS'!$A$7:$A$11,0)),"") -> 54.14 | H50: =IFERROR(INDEX('MAESTRO DOBEL DIAMANTE REPOS'!$D$7:$D$11,MATCH("MAYO",'MAESTRO DOBEL DIAMANTE REPOS'!$A$7:$A$11,0)),"") -> 55.17 | J50: =IFERROR(INDEX('MAESTRO DOBEL DIAMANTE REPOS'!$D$7:$D$11,MATCH("JULIO",'MAESTRO DOBEL DIAMANTE REPOS'!$A$7:$A$11,0)),"") -> 55.17 | K50: =IFERROR(INDEX('MAESTRO DOBEL DIAMANTE REPOS'!$D$7:$D$11,MATCH("AGOSTO",'MAESTRO DOBEL DIAMANTE REPOS'!$A$7:$A$11,0)),"") -> 55.17 | L50: ='MAESTRO DOBEL DIAMANTE REPOS'!D7 -> 54.14 | M50: ='MAESTRO DOBEL DIAMANTE REPOS'!D11 -> 55.17 | N50: =IFERROR(M50/L50-1,0) -> 0.019024751 | O50: 1 | P50: FEB 54,14 → MAY 55,17 (+1,9%) | Q50: SUBE
A51: ENVASADO / BEBIDA / OTROS | B51: EIF DISTRIBUCIONES | C51: IZAGUIRRE BOX 20L | D51: =IFERROR(INDEX('IZAGUIRRE BOX 20L'!$D$7:$D$10,MATCH("ENERO",'IZAGUIRRE BOX 20L'!$A$7:$A$10,0)),"") -> 118.165 | E51: =IFERROR(INDEX('IZAGUIRRE BOX 20L'!$D$7:$D$10,MATCH("FEBRERO",'IZAGUIRRE BOX 20L'!$A$7:$A$10,0)),"") -> 116.18 | J51: =IFERROR(INDEX('IZAGUIRRE BOX 20L'!$D$7:$D$10,MATCH("JULIO",'IZAGUIRRE BOX 20L'!$A$7:$A$10,0)),"") -> 120.15 | K51: =IFERROR(INDEX('IZAGUIRRE BOX 20L'!$D$7:$D$10,MATCH("AGOSTO",'IZAGUIRRE BOX 20L'!$A$7:$A$10,0)),"") -> 120.15 | L51: ='IZAGUIRRE BOX 20L'!D7 -> 118.165 | M51: ='IZAGUIRRE BOX 20L'!D10 -> 120.15 | N51: =IFERROR(M51/L51-1,0) -> 0.016798544 | O51: 1 | P51: ENE 118,17 → FEB 116,18 (-1,7%) · FEB 116,18 → JUL 120,15 (+3,4%) | Q51: SUBE
A52: ENVASADO / BEBIDA / OTROS | B52: SUBMARINER | C52: MACALLAN 12 | E52: =IFERROR(INDEX('MACALLAN 12'!$D$7:$D$9,MATCH("FEBRERO",'MACALLAN 12'!$A$7:$A$9,0)),"") -> 55.2 | H52: =IFERROR(INDEX('MACALLAN 12'!$D$7:$D$9,MATCH("MAYO",'MACALLAN 12'!$A$7:$A$9,0)),"") -> 56.01 | J52: =IFERROR(INDEX('MACALLAN 12'!$D$7:$D$9,MATCH("JULIO",'MACALLAN 12'!$A$7:$A$9,0)),"") -> 56.01 | L52: ='MACALLAN 12'!D7 -> 55.2 | M52: ='MACALLAN 12'!D9 -> 56.01 | N52: =IFERROR(M52/L52-1,0) -> 0.014673913 | O52: 1 | P52: FEB 55,20 → MAY 56,01 (+1,5%) | Q52: SUBE
A53: ENVASADO / BEBIDA / OTROS | B53: SUBMARINER | C53: ABSOLUT 0,70 | D53: =IFERROR(INDEX('ABSOLUT 0,70'!$D$7:$D$11,MATCH("ENERO",'ABSOLUT 0,70'!$A$7:$A$11,0)),"") -> 11.68 | E53: =IFERROR(INDEX('ABSOLUT 0,70'!$D$7:$D$11,MATCH("FEBRERO",'ABSOLUT 0,70'!$A$7:$A$11,0)),"") -> 11.68 | H53: =IFERROR(INDEX('ABSOLUT 0,70'!$D$7:$D$11,MATCH("MAYO",'ABSOLUT 0,70'!$A$7:$A$11,0)),"") -> 11.85 | J53: =IFERROR(INDEX('ABSOLUT 0,70'!$D$7:$D$11,MATCH("JULIO",'ABSOLUT 0,70'!$A$7:$A$11,0)),"") -> 11.85 | K53: =IFERROR(INDEX('ABSOLUT 0,70'!$D$7:$D$11,MATCH("AGOSTO",'ABSOLUT 0,70'!$A$7:$A$11,0)),"") -> 11.85 | L53: ='ABSOLUT 0,70'!D7 -> 11.68 | M53: ='ABSOLUT 0,70'!D11 -> 11.85 | N53: =IFERROR(M53/L53-1,0) -> 0.014554795 | O53: 1 | P53: FEB 11,68 → MAY 11,85 (+1,5%) | Q53: SUBE
A54: ENVASADO / BEBIDA / OTROS | B54: EIF DISTRIBUCIONES | C54: BARCELO ANEJO | D54: =IFERROR(INDEX('BARCELO ANEJO'!$D$7:$D$10,MATCH("ENERO",'BARCELO ANEJO'!$A$7:$A$10,0)),"") -> 12.56 | E54: =IFERROR(INDEX('BARCELO ANEJO'!$D$7:$D$10,MATCH("FEBRERO",'BARCELO ANEJO'!$A$7:$A$10,0)),"") -> 12.56 | J54: =IFERROR(INDEX('BARCELO ANEJO'!$D$7:$D$10,MATCH("JULIO",'BARCELO ANEJO'!$A$7:$A$10,0)),"") -> 12.72 | K54: =IFERROR(INDEX('BARCELO ANEJO'!$D$7:$D$10,MATCH("AGOSTO",'BARCELO ANEJO'!$A$7:$A$10,0)),"") -> 12.72 | L54: ='BARCELO ANEJO'!D7 -> 12.56 | M54: ='BARCELO ANEJO'!D10 -> 12.72 | N54: =IFERROR(M54/L54-1,0) -> 0.012738854 | O54: 1 | P54: FEB 12,56 → JUL 12,72 (+1,3%) | Q54: SUBE
A55: ENVASADO / BEBIDA / OTROS | B55: MAGOASE | C55: A GIRASOL ALTO OLEICO | D55: =IFERROR(INDEX('A GIRASOL ALTO OLEICO'!$D$7:$D$12,MATCH("ENERO",'A GIRASOL ALTO OLEICO'!$A$7:$A$12,0)),"") -> 44.95 | E55: =IFERROR(INDEX('A GIRASOL ALTO OLEICO'!$D$7:$D$12,MATCH("FEBRERO",'A GIRASOL ALTO OLEICO'!$A$7:$A$12,0)),"") -> 44.95 | G55: =IFERROR(INDEX('A GIRASOL ALTO OLEICO'!$D$7:$D$12,MATCH("ABRIL",'A GIRASOL ALTO OLEICO'!$A$7:$A$12,0)),"") -> 44.95 | H55: =IFERROR(INDEX('A GIRASOL ALTO OLEICO'!$D$7:$D$12,MATCH("MAYO",'A GIRASOL ALTO OLEICO'!$A$7:$A$12,0)),"") -> 44.95 | J55: =IFERROR(INDEX('A GIRASOL ALTO OLEICO'!$D$7:$D$12,MATCH("JULIO",'A GIRASOL ALTO OLEICO'!$A$7:$A$12,0)),"") -> 44.95 | K55: =IFERROR(INDEX('A GIRASOL ALTO OLEICO'!$D$7:$D$12,MATCH("AGOSTO",'A GIRASOL ALTO OLEICO'!$A$7:$A$12,0)),"") -> 45.45 | L55: ='A GIRASOL ALTO OLEICO'!D7 -> 44.95 | M55: ='A GIRASOL ALTO OLEICO'!D12 -> 45.45 | N55: =IFERROR(M55/L55-1,0) -> 0.011123471 | O55: 1 | P55: JUL 44,95 → AGO 45,45 (+1,1%) | Q55: SUBE
A56: ENVASADO / BEBIDA / OTROS | B56: SUBMARINER | C56: HAVANA 7 ANOS | D56: =IFERROR(INDEX('HAVANA 7 ANOS'!$D$7:$D$10,MATCH("ENERO",'HAVANA 7 ANOS'!$A$7:$A$10,0)),"") -> 18.65 | E56: =IFERROR(INDEX('HAVANA 7 ANOS'!$D$7:$D$10,MATCH("FEBRERO",'HAVANA 7 ANOS'!$A$7:$A$10,0)),"") -> 18.65 | H56: =IFERROR(INDEX('HAVANA 7 ANOS'!$D$7:$D$10,MATCH("MAYO",'HAVANA 7 ANOS'!$A$7:$A$10,0)),"") -> 18.65 | J56: =IFERROR(INDEX('HAVANA 7 ANOS'!$D$7:$D$10,MATCH("JULIO",'HAVANA 7 ANOS'!$A$7:$A$10,0)),"") -> 18.81 | L56: ='HAVANA 7 ANOS'!D7 -> 18.65 | M56: ='HAVANA 7 ANOS'!D10 -> 18.81 | N56: =IFERROR(M56/L56-1,0) -> 0.0085790885 | O56: 1 | P56: MAY 18,65 → JUL 18,81 (+0,9%) | Q56: SUBE
A57: ENVASADO / BEBIDA / OTROS | B57: SUBMARINER | C57: BEEFEATER 0,70 | D57: =IFERROR(INDEX('BEEFEATER 0,70'!$D$7:$D$10,MATCH("ENERO",'BEEFEATER 0,70'!$A$7:$A$10,0)),"") -> 12.2 | E57: =IFERROR(INDEX('BEEFEATER 0,70'!$D$7:$D$10,MATCH("FEBRERO",'BEEFEATER 0,70'!$A$7:$A$10,0)),"") -> 12.2 | H57: =IFERROR(INDEX('BEEFEATER 0,70'!$D$7:$D$10,MATCH("MAYO",'BEEFEATER 0,70'!$A$7:$A$10,0)),"") -> 12.3 | J57: =IFERROR(INDEX('BEEFEATER 0,70'!$D$7:$D$10,MATCH("JULIO",'BEEFEATER 0,70'!$A$7:$A$10,0)),"") -> 12.3 | L57: ='BEEFEATER 0,70'!D7 -> 12.2 | M57: ='BEEFEATER 0,70'!D10 -> 12.3 | N57: =IFERROR(M57/L57-1,0) -> 0.0081967213 | O57: 1 | P57: FEB 12,20 → MAY 12,30 (+0,8%) | Q57: SUBE
A58: ENVASADO / BEBIDA / OTROS | B58: DITEMA (DIST. TENA) | C58: TRUS CRIANZA 3/4 | D58: =IFERROR(INDEX('TRUS CRIANZA 3 4'!$D$7:$D$9,MATCH("ENERO",'TRUS CRIANZA 3 4'!$A$7:$A$9,0)),"") -> 9.71 | E58: =IFERROR(INDEX('TRUS CRIANZA 3 4'!$D$7:$D$9,MATCH("FEBRERO",'TRUS CRIANZA 3 4'!$A$7:$A$9,0)),"") -> 9.71 | H58: =IFERROR(INDEX('TRUS CRIANZA 3 4'!$D$7:$D$9,MATCH("MAYO",'TRUS CRIANZA 3 4'!$A$7:$A$9,0)),"") -> 9.78 | L58: ='TRUS CRIANZA 3 4'!D7 -> 9.71 | M58: ='TRUS CRIANZA 3 4'!D9 -> 9.78 | N58: =IFERROR(M58/L58-1,0) -> 0.0072090628 | O58: 1 | P58: FEB 9,71 → MAY 9,78 (+0,7%) | Q58: SUBE
A59: ENVASADO / BEBIDA / OTROS | B59: SUBMARINER | C59: BRUGAL 0,70 | D59: =IFERROR(INDEX('BRUGAL 0,70'!$D$7:$D$10,MATCH("ENERO",'BRUGAL 0,70'!$A$7:$A$10,0)),"") -> 11.6 | E59: =IFERROR(INDEX('BRUGAL 0,70'!$D$7:$D$10,MATCH("FEBRERO",'BRUGAL 0,70'!$A$7:$A$10,0)),"") -> 11.6 | H59: =IFERROR(INDEX('BRUGAL 0,70'!$D$7:$D$10,MATCH("MAYO",'BRUGAL 0,70'!$A$7:$A$10,0)),"") -> 11.66 | J59: =IFERROR(INDEX('BRUGAL 0,70'!$D$7:$D$10,MATCH("JULIO",'BRUGAL 0,70'!$A$7:$A$10,0)),"") -> 11.66 | L59: ='BRUGAL 0,70'!D7 -> 11.6 | M59: ='BRUGAL 0,70'!D10 -> 11.66 | N59: =IFERROR(M59/L59-1,0) -> 0.0051724138 | O59: 1 | P59: FEB 11,60 → MAY 11,66 (+0,5%) | Q59: SUBE
A60: ENVASADO / BEBIDA / OTROS | B60: SUBMARINER | C60: LARIOS ESPECIAL 12 | D60: =IFERROR(INDEX('LARIOS ESPECIAL 12'!$D$7:$D$8,MATCH("ENERO",'LARIOS ESPECIAL 12'!$A$7:$A$8,0)),"") -> 12.06 | J60: =IFERROR(INDEX('LARIOS ESPECIAL 12'!$D$7:$D$8,MATCH("JULIO",'LARIOS ESPECIAL 12'!$A$7:$A$8,0)),"") -> 12.12 | L60: ='LARIOS ESPECIAL 12'!D7 -> 12.06 | M60: ='LARIOS ESPECIAL 12'!D8 -> 12.12 | N60: =IFERROR(M60/L60-1,0) -> 0.0049751244 | O60: 1 | P60: ENE 12,06 → JUL 12,12 (+0,5%) | Q60: SUBE
A61: ENVASADO / BEBIDA / OTROS | B61: SUBMARINER | C61: LARIOS 1L | D61: =IFERROR(INDEX('LARIOS 1L'!$D$7:$D$9,MATCH("ENERO",'LARIOS 1L'!$A$7:$A$9,0)),"") -> 10.27 | J61: =IFERROR(INDEX('LARIOS 1L'!$D$7:$D$9,MATCH("JULIO",'LARIOS 1L'!$A$7:$A$9,0)),"") -> 10.32 | K61: =IFERROR(INDEX('LARIOS 1L'!$D$7:$D$9,MATCH("AGOSTO",'LARIOS 1L'!$A$7:$A$9,0)),"") -> 10.32 | L61: ='LARIOS 1L'!D7 -> 10.27 | M61: ='LARIOS 1L'!D9 -> 10.32 | N61: =IFERROR(M61/L61-1,0) -> 0.0048685492 | O61: 1 | P61: ENE 10,27 → JUL 10,32 (+0,5%) | Q61: SUBE
A62: ENVASADO / BEBIDA / OTROS | B62: SUBMARINER | C62: SEAGRAMS 0,70 | D62: =IFERROR(INDEX('SEAGRAMS 0,70'!$D$7:$D$10,MATCH("ENERO",'SEAGRAMS 0,70'!$A$7:$A$10,0)),"") -> 13.32 | E62: =IFERROR(INDEX('SEAGRAMS 0,70'!$D$7:$D$10,MATCH("FEBRERO",'SEAGRAMS 0,70'!$A$7:$A$10,0)),"") -> 13.32 | H62: =IFERROR(INDEX('SEAGRAMS 0,70'!$D$7:$D$10,MATCH("MAYO",'SEAGRAMS 0,70'!$A$7:$A$10,0)),"") -> 13.38 | J62: =IFERROR(INDEX('SEAGRAMS 0,70'!$D$7:$D$10,MATCH("JULIO",'SEAGRAMS 0,70'!$A$7:$A$10,0)),"") -> 13.38 | L62: ='SEAGRAMS 0,70'!D7 -> 13.32 | M62: ='SEAGRAMS 0,70'!D10 -> 13.38 | N62: =IFERROR(M62/L62-1,0) -> 0.0045045045 | O62: 1 | P62: FEB 13,32 → MAY 13,38 (+0,5%) | Q62: SUBE
A63: ENVASADO / BEBIDA / OTROS | B63: SUBMARINER | C63: DYC 8 ANOS 0,70 | D63: =IFERROR(INDEX('DYC 8 ANOS 0,70'!$D$7:$D$8,MATCH("ENERO",'DYC 8 ANOS 0,70'!$A$7:$A$8,0)),"") -> 10.64 | H63: =IFERROR(INDEX('DYC 8 ANOS 0,70'!$D$7:$D$8,MATCH("MAYO",'DYC 8 ANOS 0,70'!$A$7:$A$8,0)),"") -> 10.67 | L63: ='DYC 8 ANOS 0,70'!D7 -> 10.64 | M63: ='DYC 8 ANOS 0,70'!D8 -> 10.67 | N63: =IFERROR(M63/L63-1,0) -> 0.0028195489 | O63: 1 | P63: ENE 10,64 → MAY 10,67 (+0,3%) | Q63: SUBE
A64: CARNE | B64: AGROFOOD | C64: ENTRECOT T MORUCHA | D64: =IFERROR(INDEX('ENTRECOT T MORUCHA'!$D$7:$D$12,MATCH("ENERO",'ENTRECOT T MORUCHA'!$A$7:$A$12,0)),"") -> 27.5 | E64: =IFERROR(INDEX('ENTRECOT T MORUCHA'!$D$7:$D$12,MATCH("FEBRERO",'ENTRECOT T MORUCHA'!$A$7:$A$12,0)),"") -> 27.5 | G64: =IFERROR(INDEX('ENTRECOT T MORUCHA'!$D$7:$D$12,MATCH("ABRIL",'ENTRECOT T MORUCHA'!$A$7:$A$12,0)),"") -> 27.5 | H64: =IFERROR(INDEX('ENTRECOT T MORUCHA'!$D$7:$D$12,MATCH("MAYO",'ENTRECOT T MORUCHA'!$A$7:$A$12,0)),"") -> 27.5 | J64: =IFERROR(INDEX('ENTRECOT T MORUCHA'!$D$7:$D$12,MATCH("JULIO",'ENTRECOT T MORUCHA'!$A$7:$A$12,0)),"") -> 27.5 | K64: =IFERROR(INDEX('ENTRECOT T MORUCHA'!$D$7:$D$12,MATCH("AGOSTO",'ENTRECOT T MORUCHA'!$A$7:$A$12,0)),"") -> 27.57 | L64: ='ENTRECOT T MORUCHA'!D7 -> 27.5 | M64: ='ENTRECOT T MORUCHA'!D12 -> 27.57 | N64: =IFERROR(M64/L64-1,0) -> 0.0025454545 | O64: 1 | P64: JUL 27,50 → AGO 27,57 (+0,3%) | Q64: SUBE
A65: CARNE | B65: AGROFOOD | C65: MEDALLON P SOLOMILLO VACUNO | D65: =IFERROR(INDEX('MEDALLON P SOLOMILLO VACUNO'!$D$7:$D$12,MATCH("ENERO",'MEDALLON P SOLOMILLO VACUNO'!$A$7:$A$12,0)),"") -> 36.9 | E65: =IFERROR(INDEX('MEDALLON P SOLOMILLO VACUNO'!$D$7:$D$12,MATCH("FEBRERO",'MEDALLON P SOLOMILLO VACUNO'!$A$7:$A$12,0)),"") -> 36.9 | G65: =IFERROR(INDEX('MEDALLON P SOLOMILLO VACUNO'!$D$7:$D$12,MATCH("ABRIL",'MEDALLON P SOLOMILLO VACUNO'!$A$7:$A$12,0)),"") -> 36.9 | H65: =IFERROR(INDEX('MEDALLON P SOLOMILLO VACUNO'!$D$7:$D$12,MATCH("MAYO",'MEDALLON P SOLOMILLO VACUNO'!$A$7:$A$12,0)),"") -> 36.9 | J65: =IFERROR(INDEX('MEDALLON P SOLOMILLO VACUNO'!$D$7:$D$12,MATCH("JULIO",'MEDALLON P SOLOMILLO VACUNO'!$A$7:$A$12,0)),"") -> 36.9 | K65: =IFERROR(INDEX('MEDALLON P SOLOMILLO VACUNO'!$D$7:$D$12,MATCH("AGOSTO",'MEDALLON P SOLOMILLO VACUNO'!$A$7:$A$12,0)),"") -> 36.97 | L65: ='MEDALLON P SOLOMILLO VACUNO'!D7 -> 36.9 | M65: ='MEDALLON P SOLOMILLO VACUNO'!D12 -> 36.97 | N65: =IFERROR(M65/L65-1,0) -> 0.001897019 | O65: 1 | P65: JUL 36,90 → AGO 36,97 (+0,2%) | Q65: SUBE
A66: ENVASADO / BEBIDA / OTROS | B66: DITEMA (DIST. TENA) | C66: CRUZ ALBA ROBLE 3/4 | D66: =IFERROR(INDEX('CRUZ ALBA ROBLE 3 4'!$D$7:$D$9,MATCH("ENERO",'CRUZ ALBA ROBLE 3 4'!$A$7:$A$9,0)),"") -> 7.47 | E66: =IFERROR(INDEX('CRUZ ALBA ROBLE 3 4'!$D$7:$D$9,MATCH("FEBRERO",'CRUZ ALBA ROBLE 3 4'!$A$7:$A$9,0)),"") -> 7.47 | H66: =IFERROR(INDEX('CRUZ ALBA ROBLE 3 4'!$D$7:$D$9,MATCH("MAYO",'CRUZ ALBA ROBLE 3 4'!$A$7:$A$9,0)),"") -> 7.48 | L66: ='CRUZ ALBA ROBLE 3 4'!D7 -> 7.47 | M66: ='CRUZ ALBA ROBLE 3 4'!D9 -> 7.48 | N66: =IFERROR(M66/L66-1,0) -> 0.0013386881 | O66: 1 | P66: FEB 7,47 → MAY 7,48 (+0,1%) | Q66: SUBE
A67: ENVASADO / BEBIDA / OTROS | B67: EIF DISTRIBUCIONES | C67: HENDRICKS | D67: =IFERROR(INDEX(HENDRICKS!$D$7:$D$8,MATCH("ENERO",HENDRICKS!$A$7:$A$8,0)),"") -> 24.43 | E67: =IFERROR(INDEX(HENDRICKS!$D$7:$D$8,MATCH("FEBRERO",HENDRICKS!$A$7:$A$8,0)),"") -> 24.46 | L67: =HENDRICKS!D7 -> 24.43 | M67: =HENDRICKS!D8 -> 24.46 | N67: =IFERROR(M67/L67-1,0) -> 0.0012279984 | O67: 1 | P67: ENE 24,43 → FEB 24,46 (+0,1%) | Q67: SUBE
A68: ENVASADO / BEBIDA / OTROS | B68: MANUEL AMBRES E HIJOS | C68: RACION CECINA PREMIUM 100GR | E68: =IFERROR(INDEX('RACION CECINA PREMIUM 100GR'!$D$7:$D$11,MATCH("FEBRERO",'RACION CECINA PREMIUM 100GR'!$A$7:$A$11,0)),"") -> 7.35 | G68: =IFERROR(INDEX('RACION CECINA PREMIUM 100GR'!$D$7:$D$11,MATCH("ABRIL",'RACION CECINA PREMIUM 100GR'!$A$7:$A$11,0)),"") -> 6.9 | H68: =IFERROR(INDEX('RACION CECINA PREMIUM 100GR'!$D$7:$D$11,MATCH("MAYO",'RACION CECINA PREMIUM 100GR'!$A$7:$A$11,0)),"") -> 7.35 | J68: =IFERROR(INDEX('RACION CECINA PREMIUM 100GR'!$D$7:$D$11,MATCH("JULIO",'RACION CECINA PREMIUM 100GR'!$A$7:$A$11,0)),"") -> 7.35 | K68: =IFERROR(INDEX('RACION CECINA PREMIUM 100GR'!$D$7:$D$11,MATCH("AGOSTO",'RACION CECINA PREMIUM 100GR'!$A$7:$A$11,0)),"") -> 7.35 | L68: ='RACION CECINA PREMIUM 100GR'!D7 -> 7.35 | M68: ='RACION CECINA PREMIUM 100GR'!D11 -> 7.35 | N68: =IFERROR(M68/L68-1,0) -> 0 | O68: 1 | P68: FEB 7,35 → ABR 6,90 (-6,1%) · ABR 6,90 → MAY 7,35 (+6,5%) | Q68: SUBIDA INTERMEDIA
A69: CARNE | B69: CARNICAS MEAT | C69: SOLOMILLO VACA | H69: =IFERROR(INDEX('SOLOMILLO VACA'!$D$7:$D$9,MATCH("MAYO",'SOLOMILLO VACA'!$A$7:$A$9,0)),"") -> 35 | J69: =IFERROR(INDEX('SOLOMILLO VACA'!$D$7:$D$9,MATCH("JULIO",'SOLOMILLO VACA'!$A$7:$A$9,0)),"") -> 34.775 | K69: =IFERROR(INDEX('SOLOMILLO VACA'!$D$7:$D$9,MATCH("AGOSTO",'SOLOMILLO VACA'!$A$7:$A$9,0)),"") -> 35 | L69: ='SOLOMILLO VACA'!D7 -> 35 | M69: ='SOLOMILLO VACA'!D9 -> 35 | N69: =IFERROR(M69/L69-1,0) -> 0 | O69: 1 | P69: MAY 35,00 → JUL 34,77 (-0,6%) · JUL 34,77 → AGO 35,00 (+0,6%) | Q69: SUBIDA INTERMEDIA
A70: ENVASADO / BEBIDA / OTROS | B70: MANUEL AMBRES E HIJOS | C70: RACION CECINA PREMIUM 100GR WAGYU | E70: =IFERROR(INDEX('RACION CECINA PREMIUM 100 2'!$D$7:$D$9,MATCH("FEBRERO",'RACION CECINA PREMIUM 100 2'!$A$7:$A$9,0)),"") -> 16 | G70: =IFERROR(INDEX('RACION CECINA PREMIUM 100 2'!$D$7:$D$9,MATCH("ABRIL",'RACION CECINA PREMIUM 100 2'!$A$7:$A$9,0)),"") -> 7.35 | H70: =IFERROR(INDEX('RACION CECINA PREMIUM 100 2'!$D$7:$D$9,MATCH("MAYO",'RACION CECINA PREMIUM 100 2'!$A$7:$A$9,0)),"") -> 16 | L70: ='RACION CECINA PREMIUM 100 2'!D7 -> 16 | M70: ='RACION CECINA PREMIUM 100 2'!D9 -> 16 | N70: =IFERROR(M70/L70-1,0) -> 0 | O70: 1 | P70: FEB 16,00 → ABR 7,35 (-54,1%) · ABR 7,35 → MAY 16,00 (+117,7%) | Q70: SUBIDA INTERMEDIA
A71: FRUTA / VERDURA | B71: FRUTERIA D'ALISTE | C71: LIMON | D71: =IFERROR(INDEX(LIMON!$D$7:$D$11,MATCH("ENERO",LIMON!$A$7:$A$11,0)),"") -> 2.1 | E71: =IFERROR(INDEX(LIMON!$D$7:$D$11,MATCH("FEBRERO",LIMON!$A$7:$A$11,0)),"") -> 2.15 | G71: =IFERROR(INDEX(LIMON!$D$7:$D$11,MATCH("ABRIL",LIMON!$A$7:$A$11,0)),"") -> 2.8333333 | H71: =IFERROR(INDEX(LIMON!$D$7:$D$11,MATCH("MAYO",LIMON!$A$7:$A$11,0)),"") -> 3.3 | J71: =IFERROR(INDEX(LIMON!$D$7:$D$11,MATCH("JULIO",LIMON!$A$7:$A$11,0)),"") -> 3.6 | L71: =LIMON!D7 -> 2.1 | M71: =LIMON!D11 -> 3.6 | N71: =IFERROR(M71/L71-1,0) -> 0.71428571 | O71: 2 | P71: FEB 2,15 → ABR 2,83 (+31,8%) · ABR 2,83 → MAY 3,30 (+16,5%) | Q71: SUBE (fresco)
A72: MARISCO / PESCADO FRESCO | B72: AGMASFOOD | C72: BOQUERON GORDO | D72: =IFERROR(INDEX('BOQUERON GORDO'!$D$7:$D$11,MATCH("ENERO",'BOQUERON GORDO'!$A$7:$A$11,0)),"") -> 8.8 | E72: =IFERROR(INDEX('BOQUERON GORDO'!$D$7:$D$11,MATCH("FEBRERO",'BOQUERON GORDO'!$A$7:$A$11,0)),"") -> 10.3 | G72: =IFERROR(INDEX('BOQUERON GORDO'!$D$7:$D$11,MATCH("ABRIL",'BOQUERON GORDO'!$A$7:$A$11,0)),"") -> 9.7 | J72: =IFERROR(INDEX('BOQUERON GORDO'!$D$7:$D$11,MATCH("JULIO",'BOQUERON GORDO'!$A$7:$A$11,0)),"") -> 11.95 | K72: =IFERROR(INDEX('BOQUERON GORDO'!$D$7:$D$11,MATCH("AGOSTO",'BOQUERON GORDO'!$A$7:$A$11,0)),"") -> 10.875 | L72: ='BOQUERON GORDO'!D7 -> 8.8 | M72: ='BOQUERON GORDO'!D11 -> 10.875 | N72: =IFERROR(M72/L72-1,0) -> 0.23579545 | O72: 2 | P72: ENE 8,80 → FEB 10,30 (+17,0%) · ABR 9,70 → JUL 11,95 (+23,2%) | Q72: SUBE (fresco)
A73: MARISCO / PESCADO FRESCO | B73: JOSE MANUEL ROMERO PLAZA | C73: PARROCHAS | H73: =IFERROR(INDEX(PARROCHAS!$D$7:$D$8,MATCH("MAYO",PARROCHAS!$A$7:$A$8,0)),"") -> 5.9966667 | J73: =IFERROR(INDEX(PARROCHAS!$D$7:$D$8,MATCH("JULIO",PARROCHAS!$A$7:$A$8,0)),"") -> 7.4 | L73: =PARROCHAS!D7 -> 5.9966667 | M73: =PARROCHAS!D8 -> 7.4 | N73: =IFERROR(M73/L73-1,0) -> 0.2340189 | O73: 1 | P73: MAY 6,00 → JUL 7,40 (+23,4%) | Q73: SUBE (fresco)
A74: MARISCO / PESCADO FRESCO | B74: JOSE MANUEL ROMERO PLAZA | C74: BOQUERON GORDO | D74: =IFERROR(INDEX('BOQUERON GORDO 2'!$D$7:$D$11,MATCH("ENERO",'BOQUERON GORDO 2'!$A$7:$A$11,0)),"") -> 9.09 | E74: =IFERROR(INDEX('BOQUERON GORDO 2'!$D$7:$D$11,MATCH("FEBRERO",'BOQUERON GORDO 2'!$A$7:$A$11,0)),"") -> 8.18 | G74: =IFERROR(INDEX('BOQUERON GORDO 2'!$D$7:$D$11,MATCH("ABRIL",'BOQUERON GORDO 2'!$A$7:$A$11,0)),"") -> 8.6366667 | H74: =IFERROR(INDEX('BOQUERON GORDO 2'!$D$7:$D$11,MATCH("MAYO",'BOQUERON GORDO 2'!$A$7:$A$11,0)),"") -> 8.9775 | J74: =IFERROR(INDEX('BOQUERON GORDO 2'!$D$7:$D$11,MATCH("JULIO",'BOQUERON GORDO 2'!$A$7:$A$11,0)),"") -> 10.625 | L74: ='BOQUERON GORDO 2'!D7 -> 9.09 | M74: ='BOQUERON GORDO 2'!D11 -> 10.625 | N74: =IFERROR(M74/L74-1,0) -> 0.16886689 | O74: 1 | P74: ENE 9,09 → FEB 8,18 (-10,0%) · MAY 8,98 → JUL 10,62 (+18,4%) | Q74: SUBE (fresco)
A75: MARISCO / PESCADO FRESCO | B75: PESCARUM | C75: QUISQUILLA | G75: =IFERROR(INDEX(QUISQUILLA!$D$7:$D$9,MATCH("ABRIL",QUISQUILLA!$A$7:$A$9,0)),"") -> 51 | H75: =IFERROR(INDEX(QUISQUILLA!$D$7:$D$9,MATCH("MAYO",QUISQUILLA!$A$7:$A$9,0)),"") -> 58 | J75: =IFERROR(INDEX(QUISQUILLA!$D$7:$D$9,MATCH("JULIO",QUISQUILLA!$A$7:$A$9,0)),"") -> 58.5 | L75: =QUISQUILLA!D7 -> 51 | M75: =QUISQUILLA!D9 -> 58.5 | N75: =IFERROR(M75/L75-1,0) -> 0.14705882 | O75: 1 | P75: ABR 51,00 → MAY 58,00 (+13,7%) | Q75: SUBE (fresco)
A76: MARISCO / PESCADO FRESCO | B76: PESCARUM | C76: LANGOSTINOS | D76: =IFERROR(INDEX(LANGOSTINOS!$D$7:$D$11,MATCH("ENERO",LANGOSTINOS!$A$7:$A$11,0)),"") -> 31.666667 | E76: =IFERROR(INDEX(LANGOSTINOS!$D$7:$D$11,MATCH("FEBRERO",LANGOSTINOS!$A$7:$A$11,0)),"") -> 34 | G76: =IFERROR(INDEX(LANGOSTINOS!$D$7:$D$11,MATCH("ABRIL",LANGOSTINOS!$A$7:$A$11,0)),"") -> 34 | H76: =IFERROR(INDEX(LANGOSTINOS!$D$7:$D$11,MATCH("MAYO",LANGOSTINOS!$A$7:$A$11,0)),"") -> 35 | J76: =IFERROR(INDEX(LANGOSTINOS!$D$7:$D$11,MATCH("JULIO",LANGOSTINOS!$A$7:$A$11,0)),"") -> 35 | L76: =LANGOSTINOS!D7 -> 31.666667 | M76: =LANGOSTINOS!D11 -> 35 | N76: =IFERROR(M76/L76-1,0) -> 0.10526316 | O76: 0 | P76: Sin cambios mes a mes superiores al umbral (subida gradual) | Q76: SUBE (fresco)
A77: MARISCO / PESCADO FRESCO | B77: PESCARUM | C77: CIGALAS | E77: =IFERROR(INDEX(CIGALAS!$D$7:$D$10,MATCH("FEBRERO",CIGALAS!$A$7:$A$10,0)),"") -> 68 | G77: =IFERROR(INDEX(CIGALAS!$D$7:$D$10,MATCH("ABRIL",CIGALAS!$A$7:$A$10,0)),"") -> 59 | H77: =IFERROR(INDEX(CIGALAS!$D$7:$D$10,MATCH("MAYO",CIGALAS!$A$7:$A$10,0)),"") -> 70 | J77: =IFERROR(INDEX(CIGALAS!$D$7:$D$10,MATCH("JULIO",CIGALAS!$A$7:$A$10,0)),"") -> 75 | L77: =CIGALAS!D7 -> 68 | M77: =CIGALAS!D10 -> 75 | N77: =IFERROR(M77/L77-1,0) -> 0.10294118 | O77: 1 | P77: FEB 68,00 → ABR 59,00 (-13,2%) · ABR 59,00 → MAY 70,00 (+18,6%) | Q77: SUBE (fresco)
A78: MARISCO / PESCADO FRESCO | B78: PESCARUM | C78: ALISTADOS | E78: =IFERROR(INDEX(ALISTADOS!$D$7:$D$10,MATCH("FEBRERO",ALISTADOS!$A$7:$A$10,0)),"") -> 82.5 | G78: =IFERROR(INDEX(ALISTADOS!$D$7:$D$10,MATCH("ABRIL",ALISTADOS!$A$7:$A$10,0)),"") -> 82.5 | J78: =IFERROR(INDEX(ALISTADOS!$D$7:$D$10,MATCH("JULIO",ALISTADOS!$A$7:$A$10,0)),"") -> 78 | K78: =IFERROR(INDEX(ALISTADOS!$D$7:$D$10,MATCH("AGOSTO",ALISTADOS!$A$7:$A$10,0)),"") -> 88 | L78: =ALISTADOS!D7 -> 82.5 | M78: =ALISTADOS!D10 -> 88 | N78: =IFERROR(M78/L78-1,0) -> 0.066666667 | O78: 1 | P78: JUL 78,00 → AGO 88,00 (+12,8%) | Q78: SUBIDA INTERMEDIA (fresco)
A79: MARISCO / PESCADO FRESCO | B79: PESCARUM | C79: CARABINEROS | D79: =IFERROR(INDEX(CARABINEROS!$D$7:$D$12,MATCH("ENERO",CARABINEROS!$A$7:$A$12,0)),"") -> 93.5 | E79: =IFERROR(INDEX(CARABINEROS!$D$7:$D$12,MATCH("FEBRERO",CARABINEROS!$A$7:$A$12,0)),"") -> 94.333333 | G79: =IFERROR(INDEX(CARABINEROS!$D$7:$D$12,MATCH("ABRIL",CARABINEROS!$A$7:$A$12,0)),"") -> 96.333333 | H79: =IFERROR(INDEX(CARABINEROS!$D$7:$D$12,MATCH("MAYO",CARABINEROS!$A$7:$A$12,0)),"") -> 108 | J79: =IFERROR(INDEX(CARABINEROS!$D$7:$D$12,MATCH("JULIO",CARABINEROS!$A$7:$A$12,0)),"") -> 98 | K79: =IFERROR(INDEX(CARABINEROS!$D$7:$D$12,MATCH("AGOSTO",CARABINEROS!$A$7:$A$12,0)),"") -> 98 | L79: =CARABINEROS!D7 -> 93.5 | M79: =CARABINEROS!D12 -> 98 | N79: =IFERROR(M79/L79-1,0) -> 0.048128342 | O79: 1 | P79: ABR 96,33 → MAY 108,00 (+12,1%) | Q79: SUBIDA INTERMEDIA (fresco)
A80: FRUTA / VERDURA | B80: FRUTERIA D'ALISTE | C80: TOMATE IBERICO | D80: =IFERROR(INDEX('TOMATE IBERICO'!$D$7:$D$11,MATCH("ENERO",'TOMATE IBERICO'!$A$7:$A$11,0)),"") -> 5.8 | E80: =IFERROR(INDEX('TOMATE IBERICO'!$D$7:$D$11,MATCH("FEBRERO",'TOMATE IBERICO'!$A$7:$A$11,0)),"") -> 5.8 | G80: =IFERROR(INDEX('TOMATE IBERICO'!$D$7:$D$11,MATCH("ABRIL",'TOMATE IBERICO'!$A$7:$A$11,0)),"") -> 7.45 | H80: =IFERROR(INDEX('TOMATE IBERICO'!$D$7:$D$11,MATCH("MAYO",'TOMATE IBERICO'!$A$7:$A$11,0)),"") -> 8.5 | J80: =IFERROR(INDEX('TOMATE IBERICO'!$D$7:$D$11,MATCH("JULIO",'TOMATE IBERICO'!$A$7:$A$11,0)),"") -> 5.8 | L80: ='TOMATE IBERICO'!D7 -> 5.8 | M80: ='TOMATE IBERICO'!D11 -> 5.8 | N80: =IFERROR(M80/L80-1,0) -> 0 | O80: 2 | P80: FEB 5,80 → ABR 7,45 (+28,4%) · ABR 7,45 → MAY 8,50 (+14,1%) · MAY 8,50 → JUL 5,80 (-31,8%) | Q80: SUBIDA INTERMEDIA (fresco)
A81: MARISCO / PESCADO FRESCO | B81: PESCARUM | C81: CALAMARES | D81: =IFERROR(INDEX(CALAMARES!$D$7:$D$12,MATCH("ENERO",CALAMARES!$A$7:$A$12,0)),"") -> 24 | E81: =IFERROR(INDEX(CALAMARES!$D$7:$D$12,MATCH("FEBRERO",CALAMARES!$A$7:$A$12,0)),"") -> 21.5 | G81: =IFERROR(INDEX(CALAMARES!$D$7:$D$12,MATCH("ABRIL",CALAMARES!$A$7:$A$12,0)),"") -> 24 | H81: =IFERROR(INDEX(CALAMARES!$D$7:$D$12,MATCH("MAYO",CALAMARES!$A$7:$A$12,0)),"") -> 21.5 | J81: =IFERROR(INDEX(CALAMARES!$D$7:$D$12,MATCH("JULIO",CALAMARES!$A$7:$A$12,0)),"") -> 21.5 | K81: =IFERROR(INDEX(CALAMARES!$D$7:$D$12,MATCH("AGOSTO",CALAMARES!$A$7:$A$12,0)),"") -> 21.5 | L81: =CALAMARES!D7 -> 24 | M81: =CALAMARES!D12 -> 21.5 | N81: =IFERROR(M81/L81-1,0) -> -0.10416667 | O81: 1 | P81: ENE 24,00 → FEB 21,50 (-10,4%) · FEB 21,50 → ABR 24,00 (+11,6%) · ABR 24,00 → MAY 21,50 (-10,4%) | Q81: SUBIÓ Y BAJÓ (fresco)
A82: MARISCO / PESCADO FRESCO | B82: PESCARUM | C82: NAVAJAS | D82: =IFERROR(INDEX(NAVAJAS!$D$7:$D$12,MATCH("ENERO",NAVAJAS!$A$7:$A$12,0)),"") -> 28.625 | E82: =IFERROR(INDEX(NAVAJAS!$D$7:$D$12,MATCH("FEBRERO",NAVAJAS!$A$7:$A$12,0)),"") -> 35.1 | G82: =IFERROR(INDEX(NAVAJAS!$D$7:$D$12,MATCH("ABRIL",NAVAJAS!$A$7:$A$12,0)),"") -> 28 | H82: =IFERROR(INDEX(NAVAJAS!$D$7:$D$12,MATCH("MAYO",NAVAJAS!$A$7:$A$12,0)),"") -> 27.4 | J82: =IFERROR(INDEX(NAVAJAS!$D$7:$D$12,MATCH("JULIO",NAVAJAS!$A$7:$A$12,0)),"") -> 25.75 | K82: =IFERROR(INDEX(NAVAJAS!$D$7:$D$12,MATCH("AGOSTO",NAVAJAS!$A$7:$A$12,0)),"") -> 25 | L82: =NAVAJAS!D7 -> 28.625 | M82: =NAVAJAS!D12 -> 25 | N82: =IFERROR(M82/L82-1,0) -> -0.12663755 | O82: 1 | P82: ENE 28,62 → FEB 35,10 (+22,6%) · FEB 35,10 → ABR 28,00 (-20,2%) | Q82: SUBIÓ Y BAJÓ (fresco)
A83: MARISCO / PESCADO FRESCO | B83: MARTIN CANEDA | C83: BERBERECHO | D83: =IFERROR(INDEX(BERBERECHO!$D$7:$D$12,MATCH("ENERO",BERBERECHO!$A$7:$A$12,0)),"") -> 61.5 | E83: =IFERROR(INDEX(BERBERECHO!$D$7:$D$12,MATCH("FEBRERO",BERBERECHO!$A$7:$A$12,0)),"") -> 22.666667 | G83: =IFERROR(INDEX(BERBERECHO!$D$7:$D$12,MATCH("ABRIL",BERBERECHO!$A$7:$A$12,0)),"") -> 48.333333 | H83: =IFERROR(INDEX(BERBERECHO!$D$7:$D$12,MATCH("MAYO",BERBERECHO!$A$7:$A$12,0)),"") -> 95 | J83: =IFERROR(INDEX(BERBERECHO!$D$7:$D$12,MATCH("JULIO",BERBERECHO!$A$7:$A$12,0)),"") -> 24.5 | K83: =IFERROR(INDEX(BERBERECHO!$D$7:$D$12,MATCH("AGOSTO",BERBERECHO!$A$7:$A$12,0)),"") -> 23 | L83: =BERBERECHO!D7 -> 61.5 | M83: =BERBERECHO!D12 -> 23 | N83: =IFERROR(M83/L83-1,0) -> -0.62601626 | O83: 2 | P83: ENE 61,50 → FEB 22,67 (-63,1%) · FEB 22,67 → ABR 48,33 (+113,2%) · ABR 48,33 → MAY 95,00 (+96,6%) · MAY 95,00 → JUL 24,50 (-74,2%) | Q83: SUBIÓ Y BAJÓ (fresco)

Sheet TODOS LOS PRODUCTOS
A1: TODOS LOS PRODUCTOS COMPRADOS EN 2 O MÁS MESES · PRECIO MEDIO UNITARIO POR MES
A3: CATEGORÍA | B3: PROVEEDOR | C3: PRODUCTO | D3: ENERO | E3: FEBRERO | F3: MARZO | G3: ABRIL | H3: MAYO | I3: JULIO | J3: AGOSTO | K3: PRIMER PRECIO | L3: ÚLTIMO PRECIO | M3: VARIACIÓN % | N3: ESTADO
A4: CARNE | B4: AGROFOOD | C4: CAJAS CERDO IBERICO | D4: 1 | G4: 1 | H4: 1 | K4: 1 | L4: 1 | M4: =IFERROR(L4/K4-1,0) -> 0 | N4: ESTABLE
A5: CARNE | B5: AGROFOOD | C5: DESMIGADA COLA TORO EN SU JUGO A BA | G5: 28.5 | H5: 28.5 | K5: 28.5 | L5: 28.5 | M5: =IFERROR(L5/K5-1,0) -> 0 | N5: ESTABLE
A6: CARNE | B6: AGROFOOD | C6: ENTRECOT T MORUCHA | D6: 27.5 | E6: 27.5 | G6: 27.5 | H6: 27.5 | I6: 27.5 | J6: 27.57 | K6: 27.5 | L6: 27.57 | M6: =IFERROR(L6/K6-1,0) -> 0.0025454545 | N6: SUBE
A7: CARNE | B7: AGROFOOD | C7: MEDALLON P SOLOMILLO VACUNO | D7: 36.9 | E7: 36.9 | G7: 36.9 | H7: 36.9 | I7: 36.9 | J7: 36.97 | K7: 36.9 | L7: 36.97 | M7: =IFERROR(L7/K7-1,0) -> 0.001897019 | N7: SUBE
A8: CARNE | B8: CARNICAS MEAT | C8: CHULETA CORDERO | H8: 25 | I8: 25 | J8: 25 | K8: 25 | L8: 25 | M8: =IFERROR(L8/K8-1,0) -> 0 | N8: ESTABLE
A9: CARNE | B9: CARNICAS MEAT | C9: SOLOMILLO VACA | H9: 35 | I9: 34.775 | J9: 35 | K9: 35 | L9: 35 | M9: =IFERROR(L9/K9-1,0) -> 0 | N9: SUBIDA INTERMEDIA
A10: CARNE | B10: CARNICAS MEAT | C10: TERNERA MIXTA | H10: 11.81 | I10: 10.9 | K10: 11.81 | L10: 10.9 | M10: =IFERROR(L10/K10-1,0) -> -0.077053345 | N10: BAJA
A11: CARNE | B11: CARNICAS OPC / CRNAS SERVAN | C11: CHORIZO ASTURIANO | E11: 9 | G11: 9 | I11: 9 | K11: 9 | L11: 9 | M11: =IFERROR(L11/K11-1,0) -> 0 | N11: ESTABLE
A12: CARNE | B12: CARNICAS OPC / CRNAS SERVAN | C12: FALDA TERNERA | D12: 11.5 | E12: 11.5 | G12: 11.5 | J12: 11.5 | K12: 11.5 | L12: 11.5 | M12: =IFERROR(L12/K12-1,0) -> 0 | N12: ESTABLE
A13: CARNE | B13: CARNICAS OPC / CRNAS SERVAN | C13: GALLINAS | G13: 3.75 | I13: 3.75 | K13: 3.75 | L13: 3.75 | M13: =IFERROR(L13/K13-1,0) -> 0 | N13: ESTABLE
A14: CARNE | B14: CARNICAS OPC / CRNAS SERVAN | C14: HUESO FRESCO | D14: 2 | E14: 2 | G14: 2 | J14: 2 | K14: 2 | L14: 2 | M14: =IFERROR(L14/K14-1,0) -> 0 | N14: ESTABLE
A15: CARNE | B15: CARNICAS OPC / CRNAS SERVAN | C15: HUESOS JAMON | E15: 4.5 | G15: 4.5 | K15: 4.5 | L15: 4.5 | M15: =IFERROR(L15/K15-1,0) -> 0 | N15: ESTABLE
A16: CARNE | B16: CARNICAS OPC / CRNAS SERVAN | C16: HUEVOS CORRAL | D16: 52.5 | E16: 52.5 | G16: 52.5 | H16: 52.5 | I16: 52.5 | J16: 52.5 | K16: 52.5 | L16: 52.5 | M16: =IFERROR(L16/K16-1,0) -> 0 | N16: ESTABLE
A17: CARNE | B17: CARNICAS OPC / CRNAS SERVAN | C17: MANOS CERDO | D17: 4.5 | E17: 4.5 | G17: 4.5 | I17: 4.5 | K17: 4.5 | L17: 4.5 | M17: =IFERROR(L17/K17-1,0) -> 0 | N17: ESTABLE
A18: CARNE | B18: CARNICAS OPC / CRNAS SERVAN | C18: MEDIA HUERVO | I18: 45 | J18: 45 | K18: 45 | L18: 45 | M18: =IFERROR(L18/K18-1,0) -> 0 | N18: ESTABLE
A19: CARNE | B19: CARNICAS OPC / CRNAS SERVAN | C19: MEDIA HUEVO | D19: 45 | E19: 45 | G19: 45 | H19: 45 | I19: 45 | K19: 45 | L19: 45 | M19: =IFERROR(L19/K19-1,0) -> 0 | N19: ESTABLE
A20: CARNE | B20: CARNICAS OPC / CRNAS SERVAN | C20: MORCILLA ASTURIANA | E20: 8 | G20: 8 | J20: 9 | K20: 8 | L20: 9 | M20: =IFERROR(L20/K20-1,0) -> 0.125 | N20: SUBE
A21: CARNE | B21: CARNICAS OPC / CRNAS SERVAN | C21: MORCILLO TERNERA | D21: 12.5 | E21: 12.5 | G21: 12.5 | I21: 12.5 | K21: 12.5 | L21: 12.5 | M21: =IFERROR(L21/K21-1,0) -> 0 | N21: ESTABLE
A22: CARNE | B22: CARNICAS OPC / CRNAS SERVAN | C22: MORRO TERNERA | D22: 8.5 | E22: 8.5 | G22: 8.5 | I22: 8.5 | J22: 8.5 | K22: 8.5 | L22: 8.5 | M22: =IFERROR(L22/K22-1,0) -> 0 | N22: ESTABLE
A23: CARNE | B23: CARNICAS OPC / CRNAS SERVAN | C23: OREJA CERDO | D23: 6 | E23: 6 | G23: 6 | H23: 6 | I23: 6 | J23: 6 | K23: 6 | L23: 6 | M23: =IFERROR(L23/K23-1,0) -> 0 | N23: ESTABLE
A24: CARNE | B24: CARNICAS OPC / CRNAS SERVAN | C24: PANCETA ADOBADA | D24: 8.8 | E24: 8.8 | G24: 8.8 | H24: 8.8 | I24: 8.8 | J24: 8.8 | K24: 8.8 | L24: 8.8 | M24: =IFERROR(L24/K24-1,0) -> 0 | N24: ESTABLE
A25: CARNE | B25: CARNICAS OPC / CRNAS SERVAN | C25: PANCETA FRESCA | E25: 7 | G25: 7 | K25: 7 | L25: 7 | M25: =IFERROR(L25/K25-1,0) -> 0 | N25: ESTABLE
A26: CARNE | B26: CARNICAS OPC / CRNAS SERVAN | C26: PATA TERNERA 2 | D26: 8.5 | E26: 8.5 | G26: 8.5 | I26: 8.5 | J26: 8.5 | K26: 8.5 | L26: 8.5 | M26: =IFERROR(L26/K26-1,0) -> 0 | N26: ESTABLE
A27: CARNE | B27: CARNICAS OPC / CRNAS SERVAN | C27: PECHUGA POLLO | E27: 6.5 | G27: 6.5 | K27: 6.5 | L27: 6.5 | M27: =IFERROR(L27/K27-1,0) -> 0 | N27: ESTABLE
A28: CARNE | B28: CARNICAS OPC / CRNAS SERVAN | C28: PICADA MIXTA | E28: 7.5 | G28: 7.5 | K28: 7.5 | L28: 7.5 | M28: =IFERROR(L28/K28-1,0) -> 0 | N28: ESTABLE
A29: CARNE | B29: CARNICAS OPC / CRNAS SERVAN | C29: POLLO ENTERO | E29: 3.5 | G29: 3.5 | I29: 3.5 | K29: 3.5 | L29: 3.5 | M29: =IFERROR(L29/K29-1,0) -> 0 | N29: ESTABLE
A30: CARNE | B30: CARNICAS OPC / CRNAS SERVAN | C30: POLLO TROCEADO | D30: 3.5 | E30: 3.5 | G30: 3.5 | H30: 3.5 | I30: 3.5 | K30: 3.5 | L30: 3.5 | M30: =IFERROR(L30/K30-1,0) -> 0 | N30: ESTABLE
A31: CARNE | B31: CARNICAS OPC / CRNAS SERVAN | C31: TOCINO IBERICO | E31: 5 | G31: 5 | K31: 5 | L31: 5 | M31: =IFERROR(L31/K31-1,0) -> 0 | N31: ESTABLE
A32: CARNE | B32: PEÑALASTALLAS | C32: MOLLEJAS CERDO | D32: 27.9 | E32: 27.9 | G32: 27.9 | H32: 27.9 | K32: 27.9 | L32: 27.9 | M32: =IFERROR(L32/K32-1,0) -> 0 | N32: ESTABLE
A33: CARNE | B33: PEÑALASTALLAS | C33: MOLLEJAS CORDERO | E33: 27.9 | G33: 27.9 | H33: 27.9 | I33: 27.9 | J33: 27.9 | K33: 27.9 | L33: 27.9 | M33: =IFERROR(L33/K33-1,0) -> 0 | N33: ESTABLE
A34: CARNE | B34: PEÑALASTALLAS | C34: PINCHO MORUNO POLLO | D34: 8.95 | E34: 8.9 | G34: 8.9 | H34: 8.9 | I34: 8.9 | J34: 8.9 | K34: 8.95 | L34: 8.9 | M34: =IFERROR(L34/K34-1,0) -> -0.0055865922 | N34: BAJA
A35: CARNE | B35: PEÑALASTALLAS | C35: PINCHOS MORUNOS | D35: 8.9 | E35: 8.9 | G35: 8.9 | H35: 8.9 | I35: 8.9 | J35: 8.9 | K35: 8.9 | L35: 8.9 | M35: =IFERROR(L35/K35-1,0) -> 0 | N35: ESTABLE
A36: CARNE | B36: ROMERO ALVAREZ | C36: PRESA 100 IBERICA | G36: 25.2 | I36: 25.2 | J36: 25.2 | K36: 25.2 | L36: 25.2 | M36: =IFERROR(L36/K36-1,0) -> 0 | N36: ESTABLE
A37: CARNE | B37: VENERO CLARO (CHAPTER ONE) | C37: LOMO VACA VENERO CLARO C/H | D37: 26 | E37: 26 | G37: 26 | H37: 26 | I37: 26 | J37: 26 | K37: 26 | L37: 26 | M37: =IFERROR(L37/K37-1,0) -> 0 | N37: ESTABLE
A38: ENVASADO / BEBIDA / OTROS | B38: ANTONIO DE MIGUEL | C38: PATO CEBADO FOIE RESTAURACION | D38: 28.03 | E38: 28.03 | G38: 28.03 | H38: 28.03 | I38: 28.03 | K38: 28.03 | L38: 28.03 | M38: =IFERROR(L38/K38-1,0) -> 0 | N38: ESTABLE
A39: ENVASADO / BEBIDA / OTROS | B39: CALIDOSCOPI | C39: OREMUS 3 | D39: 27.4 | H39: 29.25 | K39: 27.4 | L39: 29.25 | M39: =IFERROR(L39/K39-1,0) -> 0.067518248 | N39: SUBE
A40: ENVASADO / BEBIDA / OTROS | B40: CALIDOSCOPI | C40: PAGO CARRAOVEJAS 2023 | D40: 28.25 | E40: 28.25 | H40: 28.25 | I40: 28.25 | K40: 28.25 | L40: 28.25 | M40: =IFERROR(L40/K40-1,0) -> 0 | N40: ESTABLE
A41: ENVASADO / BEBIDA / OTROS | B41: CALIDOSCOPI | C41: ROMANICO 2023 | E41: 7.85 | H41: 7.85 | K41: 7.85 | L41: 7.85 | M41: =IFERROR(L41/K41-1,0) -> 0 | N41: ESTABLE
A42: ENVASADO / BEBIDA / OTROS | B42: COCA-COLA | C42: COCACOLA PET2L C6 | E42: 2.527 | I42: 2.504 | K42: 2.527 | L42: 2.504 | M42: =IFERROR(L42/K42-1,0) -> -0.0091017016 | N42: BAJA
A43: ENVASADO / BEBIDA / OTROS | B43: COCA-COLA | C43: COCACOLA VR237 C24 | E43: 0.845 | I43: 0.845 | J43: 0.8449 | K43: 0.845 | L43: 0.8449 | M43: =IFERROR(L43/K43-1,0) -> -0.0001183432 | N43: ESTABLE
A44: ENVASADO / BEBIDA / OTROS | B44: COCA-COLA | C44: COCACOLA ZER VR237 C24 | E44: 0.845 | I44: 0.845 | K44: 0.845 | L44: 0.845 | M44: =IFERROR(L44/K44-1,0) -> 0 | N44: ESTABLE
A45: ENVASADO / BEBIDA / OTROS | B45: COCA-COLA | C45: COCACOLA ZER ZER VR237 C24 | E45: 0.845 | I45: 0.845 | K45: 0.845 | L45: 0.845 | M45: =IFERROR(L45/K45-1,0) -> 0 | N45: ESTABLE
A46: ENVASADO / BEBIDA / OTROS | B46: COCA-COLA | C46: MINUTE MAID TOM VNR20 C24 | E46: 0.728 | I46: 0.728 | K46: 0.728 | L46: 0.728 | M46: =IFERROR(L46/K46-1,0) -> 0 | N46: ESTABLE
A47: ENVASADO / BEBIDA / OTROS | B47: CONSERVAS Y SALAZONES JIMENEZ | C47: ANCHOAS CANTABRICO COSTERA | D47: 16.9 | E47: 16.9 | G47: 16.9 | H47: 16.9 | I47: 16.9 | J47: 16.9 | K47: 16.9 | L47: 16.9 | M47: =IFERROR(L47/K47-1,0) -> 0 | N47: ESTABLE
A48: ENVASADO / BEBIDA / OTROS | B48: CONSERVAS Y SALAZONES JIMENEZ | C48: ANCHOAS CANTABRICO GRAN RESERVA | D48: 27.46 | E48: 27.46 | G48: 28.66 | H48: 28.66 | I48: 28.66 | J48: 28.66 | K48: 27.46 | L48: 28.66 | M48: =IFERROR(L48/K48-1,0) -> 0.043699927 | N48: SUBE
A49: ENVASADO / BEBIDA / OTROS | B49: CONSERVAS Y SALAZONES JIMENEZ | C49: ANCHOAS CANTABRICO RO 550 ETIQUETA ROJA | E49: 18.96 | G49: 18.96 | H49: 20.6 | I49: 20.6 | K49: 18.96 | L49: 20.6 | M49: =IFERROR(L49/K49-1,0) -> 0.08649789 | N49: SUBE
A50: ENVASADO / BEBIDA / OTROS | B50: CONSERVAS Y SALAZONES JIMENEZ | C50: MEJILLONES ESCABECHE RIAS GALLEGAS 44 125 6/8 VENGARCO | D50: 5.86 | E50: 5.86 | G50: 5.86 | H50: 5.86 | K50: 5.86 | L50: 5.86 | M50: =IFERROR(L50/K50-1,0) -> 0 | N50: ESTABLE
A51: ENVASADO / BEBIDA / OTROS | B51: CONSERVAS Y SALAZONES JIMENEZ | C51: MOJAMA EXTRA SUPERIOR CHANCA | D51: 34.6 | H51: 36.4 | I51: 36.4 | J51: 36.4 | K51: 34.6 | L51: 36.4 | M51: =IFERROR(L51/K51-1,0) -> 0.052023121 | N51: SUBE
A52: ENVASADO / BEBIDA / OTROS | B52: CONSERVAS Y SALAZONES JIMENEZ | C52: VENTRESCA BONITO EXTRA | D52: 5.56 | E52: 5.56 | G52: 5.56 | H52: 5.56 | I52: 5.86 | J52: 5.86 | K52: 5.56 | L52: 5.86 | M52: =IFERROR(L52/K52-1,0) -> 0.053956835 | N52: SUBE
A53: ENVASADO / BEBIDA / OTROS | B53: DELIPAN | C53: DELIFLAUTA 17 PERRITO 90 UD | D53: 17.73 | E53: 17.73 | G53: 17.73 | H53: 17.73 | K53: 17.73 | L53: 17.73 | M53: =IFERROR(L53/K53-1,0) -> 0 | N53: ESTABLE
A54: ENVASADO / BEBIDA / OTROS | B54: DELIPAN | C54: DELIFLAUTA 17 PERRITO 90 UDS | I54: 17.73 | J54: 17.73 | K54: 17.73 | L54: 17.73 | M54: =IFERROR(L54/K54-1,0) -> 0 | N54: ESTABLE
A55: ENVASADO / BEBIDA / OTROS | B55: DELIPAN | C55: PAN MOLDE BRIOCHE | D55: 84.7 | E55: 84.7 | G55: 88.09 | H55: 88.09 | I55: 88.09 | J55: 88.09 | K55: 84.7 | L55: 88.09 | M55: =IFERROR(L55/K55-1,0) -> 0.040023613 | N55: SUBE
A56: ENVASADO / BEBIDA / OTROS | B56: DELIPAN | C56: PICOS ARTESANOS 500 GR | D56: 10.97 | E56: 10.97 | G56: 11.48 | H56: 11.48 | K56: 10.97 | L56: 11.48 | M56: =IFERROR(L56/K56-1,0) -> 0.046490428 | N56: SUBE
A57: ENVASADO / BEBIDA / OTROS | B57: DELIPAN | C57: PICOS ARTESANOS 500GR | I57: 11.48 | J57: 11.48 | K57: 11.48 | L57: 11.48 | M57: =IFERROR(L57/K57-1,0) -> 0 | N57: ESTABLE
A58: ENVASADO / BEBIDA / OTROS | B58: DELIPAN | C58: PICOS GOURMET BOLSA 500GR | G58: 25 | H58: 25 | K58: 25 | L58: 25 | M58: =IFERROR(L58/K58-1,0) -> 0 | N58: ESTABLE
A59: ENVASADO / BEBIDA / OTROS | B59: DELIPAN | C59: PICOS SIN GLUTEN 20GR | G59: 11.29 | H59: 11.29 | I59: 11.29 | K59: 11.29 | L59: 11.29 | M59: =IFERROR(L59/K59-1,0) -> 0 | N59: ESTABLE
A60: ENVASADO / BEBIDA / OTROS | B60: DISOLTRIGO | C60: 24 PERLE NOIRE N2 | G60: 42 | H60: 42 | I60: 41.5 | J60: 41.5 | K60: 42 | L60: 41.5 | M60: =IFERROR(L60/K60-1,0) -> -0.011904762 | N60: BAJA
A61: ENVASADO / BEBIDA / OTROS | B61: DISOLTRIGO | C61: BOQUERON CASERO EN ACEITE | G61: 18.5 | H61: 18.5 | I61: 18.5 | K61: 18.5 | L61: 18.5 | M61: =IFERROR(L61/K61-1,0) -> 0 | N61: ESTABLE
A62: ENVASADO / BEBIDA / OTROS | B62: DISOLTRIGO | C62: BOQUERON EN VINAGRE PANDERETA | I62: 19 | J62: 19 | K62: 19 | L62: 19 | M62: =IFERROR(L62/K62-1,0) -> 0 | N62: ESTABLE
A63: ENVASADO / BEBIDA / OTROS | B63: DITEMA (DIST. TENA) | C63: ALBARINO MAR FRADES | D63: 11.02 | E63: 11.02 | H63: 11.42 | I63: 11.42 | J63: 11.42 | K63: 11.02 | L63: 11.42 | M63: =IFERROR(L63/K63-1,0) -> 0.036297641 | N63: SUBE
A64: ENVASADO / BEBIDA / OTROS | B64: DITEMA (DIST. TENA) | C64: CAVA BRUT NATURE GRAN CLAUSTRO | H64: 15.12 | I64: 15.12 | K64: 15.12 | L64: 15.12 | M64: =IFERROR(L64/K64-1,0) -> 0 | N64: ESTABLE
A65: ENVASADO / BEBIDA / OTROS | B65: DITEMA (DIST. TENA) | C65: CEPAS VELLAS GODEVAL | E65: 14.12 | H65: 14.12 | K65: 14.12 | L65: 14.12 | M65: =IFERROR(L65/K65-1,0) -> 0 | N65: ESTABLE
A66: ENVASADO / BEBIDA / OTROS | B66: DITEMA (DIST. TENA) | C66: CHARDONAY LIAS ECOLOGICO F ELEZ | H66: 9.02 | I66: 9.02 | J66: 9.02 | K66: 9.02 | L66: 9.02 | M66: =IFERROR(L66/K66-1,0) -> 0 | N66: ESTABLE
A67: ENVASADO / BEBIDA / OTROS | B67: DITEMA (DIST. TENA) | C67: CRUZ ALBA ROBLE 3/4 | D67: 7.47 | E67: 7.47 | H67: 7.48 | K67: 7.47 | L67: 7.48 | M67: =IFERROR(L67/K67-1,0) -> 0.0013386881 | N67: SUBE
A68: ENVASADO / BEBIDA / OTROS | B68: DITEMA (DIST. TENA) | C68: GINEBRA MARTIN MILLER 3/4 | D68: 15.1 | H68: 16.1 | I68: 16.1 | K68: 15.1 | L68: 16.1 | M68: =IFERROR(L68/K68-1,0) -> 0.066225166 | N68: SUBE
A69: ENVASADO / BEBIDA / OTROS | B69: DITEMA (DIST. TENA) | C69: GODELLO MAR FRADES | E69: 17.63 | H69: 18.03 | K69: 17.63 | L69: 18.03 | M69: =IFERROR(L69/K69-1,0) -> 0.022688599 | N69: SUBE
A70: ENVASADO / BEBIDA / OTROS | B70: DITEMA (DIST. TENA) | C70: GODELLO VINAREDO | D70: 6.78 | E70: 6.78 | H70: 7.03 | I70: 7.03 | J70: 7.03 | K70: 6.78 | L70: 7.03 | M70: =IFERROR(L70/K70-1,0) -> 0.036873156 | N70: SUBE
A71: ENVASADO / BEBIDA / OTROS | B71: DITEMA (DIST. TENA) | C71: LAS MORADAS SENDA | E71: 6.63 | H71: 6.63 | K71: 6.63 | L71: 6.63 | M71: =IFERROR(L71/K71-1,0) -> 0 | N71: ESTABLE
A72: ENVASADO / BEBIDA / OTROS | B72: DITEMA (DIST. TENA) | C72: PEPE YLLERA 3/4 | D72: 7.15 | E72: 7.46 | H72: 7.46 | K72: 7.15 | L72: 7.46 | M72: =IFERROR(L72/K72-1,0) -> 0.043356643 | N72: SUBE
A73: ENVASADO / BEBIDA / OTROS | B73: DITEMA (DIST. TENA) | C73: POMMERY ROYAL BRUT 3/4 | D73: 35.49 | E73: 35.49 | H73: 36.35 | K73: 35.49 | L73: 36.35 | M73: =IFERROR(L73/K73-1,0) -> 0.024232178 | N73: SUBE
A74: ENVASADO / BEBIDA / OTROS | B74: DITEMA (DIST. TENA) | C74: SENORIO FITERO ROBLE | D74: 2.72 | E74: 2.72 | H74: 2.82 | I74: 2.82 | J74: 2.82 | K74: 2.72 | L74: 2.82 | M74: =IFERROR(L74/K74-1,0) -> 0.036764706 | N74: SUBE
A75: ENVASADO / BEBIDA / OTROS | B75: DITEMA (DIST. TENA) | C75: TRUS CRIANZA 3/4 | D75: 9.71 | E75: 9.71 | H75: 9.78 | K75: 9.71 | L75: 9.78 | M75: =IFERROR(L75/K75-1,0) -> 0.0072090628 | N75: SUBE
A76: ENVASADO / BEBIDA / OTROS | B76: DON BOCARTE (CONS. SELECCIÓN) | C76: DON BOCARTE MEDIO PULPO 360 400 GR | I76: 27 | J76: 27 | K76: 27 | L76: 27 | M76: =IFERROR(L76/K76-1,0) -> 0 | N76: ESTABLE
A77: ENVASADO / BEBIDA / OTROS | B77: EIF DISTRIBUCIONES | C77: BARCELO ANEJO | D77: 12.56 | E77: 12.56 | I77: 12.72 | J77: 12.72 | K77: 12.56 | L77: 12.72 | M77: =IFERROR(L77/K77-1,0) -> 0.012738854 | N77: SUBE
A78: ENVASADO / BEBIDA / OTROS | B78: EIF DISTRIBUCIONES | C78: CINZANO PRO SPRITZ | D78: 4.86 | E78: 4.86 | K78: 4.86 | L78: 4.86 | M78: =IFERROR(L78/K78-1,0) -> 0 | N78: ESTABLE
A79: ENVASADO / BEBIDA / OTROS | B79: EIF DISTRIBUCIONES | C79: COCA COLA ZERO NAC | D79: 20.78 | J79: 21.78 | K79: 20.78 | L79: 21.78 | M79: =IFERROR(L79/K79-1,0) -> 0.048123195 | N79: SUBE
A80: ENVASADO / BEBIDA / OTROS | B80: EIF DISTRIBUCIONES | C80: HENDRICKS | D80: 24.43 | E80: 24.46 | K80: 24.43 | L80: 24.46 | M80: =IFERROR(L80/K80-1,0) -> 0.0012279984 | N80: SUBE
A81: ENVASADO / BEBIDA / OTROS | B81: EIF DISTRIBUCIONES | C81: IZAGUIRRE BOX 20L | D81: 118.165 | E81: 116.18 | I81: 120.15 | J81: 120.15 | K81: 118.165 | L81: 120.15 | M81: =IFERROR(L81/K81-1,0) -> 0.016798544 | N81: SUBE
A82: ENVASADO / BEBIDA / OTROS | B82: EIF DISTRIBUCIONES | C82: RED BULL | D82: 20.88 | E82: 20.88 | I82: 20.88 | K82: 20.88 | L82: 20.88 | M82: =IFERROR(L82/K82-1,0) -> 0 | N82: ESTABLE
A83: ENVASADO / BEBIDA / OTROS | B83: EIF DISTRIBUCIONES | C83: RED BULL SIN AZUCAR | D83: 20.88 | E83: 20.88 | I83: 20.88 | K83: 20.88 | L83: 20.88 | M83: =IFERROR(L83/K83-1,0) -> 0 | N83: ESTABLE
A84: ENVASADO / BEBIDA / OTROS | B84: EIF DISTRIBUCIONES | C84: SCHWEPPES TONICA 28 UDS | D84: 23.84 | J84: 24.84 | K84: 23.84 | L84: 24.84 | M84: =IFERROR(L84/K84-1,0) -> 0.041946309 | N84: SUBE
A85: ENVASADO / BEBIDA / OTROS | B85: EIF DISTRIBUCIONES | C85: SOLAN CABRAS CON GAS | D85: 25.44 | I85: 26.8 | J85: 26.8 | K85: 25.44 | L85: 26.8 | M85: =IFERROR(L85/K85-1,0) -> 0.053459119 | N85: SUBE
A86: ENVASADO / BEBIDA / OTROS | B86: EL ESCRIBANO | C86: LOMO BELLOTA 100 SM | E86: 48.6 | G86: 48.6 | H86: 48.6 | I86: 49.8 | J86: 51 | K86: 48.6 | L86: 51 | M86: =IFERROR(L86/K86-1,0) -> 0.049382716 | N86: SUBE
A87: ENVASADO / BEBIDA / OTROS | B87: EL ESCRIBANO | C87: PAPADA IBERICA SOBRE | D87: 2.3 | G87: 2.3 | I87: 2.3 | K87: 2.3 | L87: 2.3 | M87: =IFERROR(L87/K87-1,0) -> 0 | N87: ESTABLE
A88: ENVASADO / BEBIDA / OTROS | B88: EL ESCRIBANO | C88: SALCHICHON BELLOTA SM | E88: 22 | G88: 22 | H88: 22 | K88: 22 | L88: 22 | M88: =IFERROR(L88/K88-1,0) -> 0 | N88: ESTABLE
A89: ENVASADO / BEBIDA / OTROS | B89: EL ESCRIBANO | C89: SALCHICHON IBERICO | I89: 22 | J89: 22 | K89: 22 | L89: 22 | M89: =IFERROR(L89/K89-1,0) -> 0 | N89: ESTABLE
A90: ENVASADO / BEBIDA / OTROS | B90: ENRIQUE CAMPS | C90: TARTA CHOCOLATE | D90: 37 | E90: 37 | G90: 37 | I90: 37 | J90: 37 | K90: 37 | L90: 37 | M90: =IFERROR(L90/K90-1,0) -> 0 | N90: ESTABLE
A91: ENVASADO / BEBIDA / OTROS | B91: ENRIQUE CAMPS | C91: TARTA QUESO | D91: 35 | E91: 35 | G91: 35 | I91: 35 | J91: 35 | K91: 35 | L91: 35 | M91: =IFERROR(L91/K91-1,0) -> 0 | N91: ESTABLE
A92: ENVASADO / BEBIDA / OTROS | B92: FCO JAVIER LABRADOR | C92: FLOR ALCACHOFA CONFITADA | I92: 22.9 | J92: 22.9 | K92: 22.9 | L92: 22.9 | M92: =IFERROR(L92/K92-1,0) -> 0 | N92: ESTABLE
A93: ENVASADO / BEBIDA / OTROS | B93: FCO JAVIER LABRADOR | C93: FLOR ALCACHOFA CONFITADA EN AOVE | D93: 22.45 | E93: 22.45 | G93: 22.9 | H93: 22.9 | K93: 22.45 | L93: 22.9 | M93: =IFERROR(L93/K93-1,0) -> 0.020044543 | N93: SUBE
A94: ENVASADO / BEBIDA / OTROS | B94: MAGOASE | C94: A GIRASOL ALTO OLEICO | D94: 44.95 | E94: 44.95 | G94: 44.95 | H94: 44.95 | I94: 44.95 | J94: 45.45 | K94: 44.95 | L94: 45.45 | M94: =IFERROR(L94/K94-1,0) -> 0.011123471 | N94: SUBE
A95: ENVASADO / BEBIDA / OTROS | B95: MAGOASE | C95: CUAD A O SUAVE GUADALIMAR 5L | D95: 23.95 | E95: 24.95 | G95: 24.95 | H95: 23.95 | I95: 23.95 | J95: 24.45 | K95: 23.95 | L95: 24.45 | M95: =IFERROR(L95/K95-1,0) -> 0.020876827 | N95: SUBE
A96: ENVASADO / BEBIDA / OTROS | B96: MAGOASE | C96: CUADR A O V E GUADALIMAR 5L | D96: 28.95 | E96: 27.95 | G96: 27.95 | H96: 26.95 | K96: 28.95 | L96: 26.95 | M96: =IFERROR(L96/K96-1,0) -> -0.069084629 | N96: BAJA
A97: ENVASADO / BEBIDA / OTROS | B97: MAGOASE | C97: LATA A O V E AU LINGOTE TEMPRANO | D97: 7.95 | E97: 7.95 | G97: 7.95 | H97: 7.95 | I97: 7.95 | J97: 7.95 | K97: 7.95 | L97: 7.95 | M97: =IFERROR(L97/K97-1,0) -> 0 | N97: ESTABLE
A98: ENVASADO / BEBIDA / OTROS | B98: MANUEL AMBRES E HIJOS | C98: RACION CECINA PREMIUM 100GR | E98: 7.35 | G98: 6.9 | H98: 7.35 | I98: 7.35 | J98: 7.35 | K98: 7.35 | L98: 7.35 | M98: =IFERROR(L98/K98-1,0) -> 0 | N98: SUBIDA INTERMEDIA
A99: ENVASADO / BEBIDA / OTROS | B99: MANUEL AMBRES E HIJOS | C99: RACION CECINA PREMIUM 100GR WAGYU | E99: 16 | G99: 7.35 | H99: 16 | K99: 16 | L99: 16 | M99: =IFERROR(L99/K99-1,0) -> 0 | N99: SUBIDA INTERMEDIA
A100: ENVASADO / BEBIDA / OTROS | B100: MANUEL AMBRES E HIJOS | C100: RACION J BELLOTA 100 100GR | D100: 13.9 | E100: 13.9 | G100: 13.9 | H100: 13.9 | I100: 13.9 | J100: 13.9 | K100: 13.9 | L100: 13.9 | M100: =IFERROR(L100/K100-1,0) -> 0 | N100: ESTABLE
A101: ENVASADO / BEBIDA / OTROS | B101: MUNDELA | C101: BARBADILLO VI MOSCATO FRIZZANTE | E101: 5.52 | H101: 5.63 | I101: 5.63 | J101: 5.63 | K101: 5.52 | L101: 5.63 | M101: =IFERROR(L101/K101-1,0) -> 0.019927536 | N101: SUBE
...

Sheet NOTAS
A1: NOTAS Y CRITERIOS
A3: Fuentes: ALBARANES ENERO/FEBRERO/ABRIL/MAYO 2026 (raíz 2026, de Adri), ALBARANES JULIO 2026 v3 y ALBARANES AGOSTO 2026 v1 (3t).
A5: Marzo: no hay Excel de marzo; solo aparecen 2 precios sueltos de Vins des Dieux. Junio: el archivo "ALBARANES JUNIO 2026" es una copia de mayo sin datos propios de junio, por eso no se usa.
A7: Precio comparado: precio unitario del albarán (P/U), sin IVA y antes de descuento. Si en un mes hay varios precios se usa la media, y en la hoja del producto se ven mínimo, medio y máximo.
A9: Coca-Cola: en julio el precio está por botella y en agosto por caja; los de agosto se han pasado a precio por botella (caja ÷ 24, PET 2L ÷ 6) para poder compararlos.
A11: Agrofood: desde julio/agosto el precio lleva sumado el "MER" (0,07 €/kg); se compara tal cual porque es lo que se paga.
A13: Se agrupan nombres del mismo producto escritos de forma distinta (p. ej. "ANCHOAS CANTABRICO COSTERA" y "... CESMAR PREMIUM 65/70"). No se mezclan variedades (zero/light, limón/naranja...).
A15: No se incluyen tasas de residuos, envases, portes, servicios logísticos, abonos ni regalos.
A17: Criterio SUBIDA: envasados, bebidas y carne → cualquier subida del precio medio entre el primer y el último mes con compras. Frescos (marisco, pescado, fruta y verdura) → solo si la media del último mes supera en más de un 10 % a la del primero; si varía más de un 15 % pero sin tendencia se marca FLUCTÚA.
A19: Cada mes, al cerrar el Excel de albaranes, se actualizará este comparativo con el nuevo mes.

Sheet MORCILLA ASTURIANA
A1: MORCILLA ASTURIANA | I1: ← Volver al resumen
A2: Proveedor: CARNICAS OPC / CRNAS SERVAN · Categoría: CARNE
A3: Nombres en albaranes: MORCILLA ASTURIANA
A4: Producto envasado / tarifa: cualquier subida de precio unitario entre el primer y el último mes con compras se considera SUBIDA.
A6: MES | B6: Nº PRECIOS | C6: PRECIO MÍN. | D6: PRECIO MEDIO | E6: PRECIO MÁX. | F6: VAR. vs MES ANTERIOR | G6: VAR. vs PRIMER MES
A7: FEBRERO | B7: =COUNTIF($A$14:$A$16,A7) -> 1 | C7: =_xlfn.MINIFS($B$14:$B$16,$A$14:$A$16,A7) -> 8 | D7: =AVERAGEIF($A$14:$A$16,A7,$B$14:$B$16) -> 8 | E7: =_xlfn.MAXIFS($B$14:$B$16,$A$14:$A$16,A7) -> 8
A8: ABRIL | B8: =COUNTIF($A$14:$A$16,A8) -> 1 | C8: =_xlfn.MINIFS($B$14:$B$16,$A$14:$A$16,A8) -> 8 | D8: =AVERAGEIF($A$14:$A$16,A8,$B$14:$B$16) -> 8 | E8: =_xlfn.MAXIFS($B$14:$B$16,$A$14:$A$16,A8) -> 8 | F8: =D8/D7-1 -> 0 | G8: =D8/$D$7-1 -> 0
A9: AGOSTO | B9: =COUNTIF($A$14:$A$16,A9) -> 1 | C9: =_xlfn.MINIFS($B$14:$B$16,$A$14:$A$16,A9) -> 9 | D9: =AVERAGEIF($A$14:$A$16,A9,$B$14:$B$16) -> 9 | E9: =_xlfn.MAXIFS($B$14:$B$16,$A$14:$A$16,A9) -> 9 | F9: =D9/D8-1 -> 0.125 | G9: =D9/$D$7-1 -> 0.125
F10: SUBIDA TOTAL | G10: =D9/D7-1 -> 0.125
A12: DETALLE DE PRECIOS (una línea por precio distinto anotado en el Excel del mes)
A13: MES | B13: PRECIO | C13: CANTIDAD | D13: PRODUCTO (tal cual en el Excel) | E13: ARCHIVO ORIGEN
A14: FEBRERO | B14: 8 | C14: 3 | D14: MORCILLA ASTURIANA | E14: ALBARANES MAYO 2026
A15: ABRIL | B15: 8 | D15: MORCILLA ASTURIANA | E15: ALBARANES MAYO 2026
A16: AGOSTO | B16: 9 | C16: 8.6 | D16: MORCILLA ASTURIANA | E16: ALBARANES AGOSTO 2026 v1

Sheet CANTALAPIEDRA CHIVIRITERO 20
A1: CANTALAPIEDRA CHIVIRITERO 2023 | I1: ← Volver al resumen
A2: Proveedor: VINS DES DIEUX · Categoría: ENVASADO / BEBIDA / OTROS
A3: Nombres en albaranes: CANTALAPIEDRA CHIVIRITERO 2023 | CANTALAPIEDRA CHIVIRITERO 2024
A4: Producto envasado / tarifa: cualquier subida de precio unitario entre el primer y el último mes con compras se considera SUBIDA.
A6: MES | B6: Nº PRECIOS | C6: PRECIO MÍN. | D6: PRECIO MEDIO | E6: PRECIO MÁX. | F6: VAR. vs MES ANTERIOR | G6: VAR. vs PRIMER MES
A7: FEBRERO | B7: =COUNTIF($A$16:$A$20,A7) -> 1 | C7: =_xlfn.MINIFS($B$16:$B$20,$A$16:$A$20,A7) -> 15.5 | D7: =AVERAGEIF($A$16:$A$20,A7,$B$16:$B$20) -> 15.5 | E7: =_xlfn.MAXIFS($B$16:$B$20,$A$16:$A$20,A7) -> 15.5
A8: MARZO | B8: =COUNTIF($A$16:$A$20,A8) -> 1 | C8: =_xlfn.MINIFS($B$16:$B$20,$A$16:$A$20,A8) -> 15.5 | D8: =AVERAGEIF($A$16:$A$20,A8,$B$16:$B$20) -> 15.5 | E8: =_xlfn.MAXIFS($B$16:$B$20,$A$16:$A$20,A8) -> 15.5 | F8: =D8/D7-1 -> 0 | G8: =D8/$D$7-1 -> 0
A9: ABRIL | B9: =COUNTIF($A$16:$A$20,A9) -> 1 | C9: =_xlfn.MINIFS($B$16:$B$20,$A$16:$A$20,A9) -> 15.5 | D9: =AVERAGEIF($A$16:$A$20,A9,$B$16:$B$20) -> 15.5 | E9: =_xlfn.MAXIFS($B$16:$B$20,$A$16:$A$20,A9) -> 15.5 | F9: =D9/D8-1 -> 0 | G9: =D9/$D$7-1 -> 0
A10: MAYO | B10: =COUNTIF($A$16:$A$20,A10) -> 1 | C10: =_xlfn.MINIFS($B$16:$B$20,$A$16:$A$20,A10) -> 16.9 | D10: =AVERAGEIF($A$16:$A$20,A10,$B$16:$B$20) -> 16.9 | E10: =_xlfn.MAXIFS($B$16:$B$20,$A$16:$A$20,A10) -> 16.9 | F10: =D10/D9-1 -> 0.090322581 | G10: =D10/$D$7-1 -> 0.090322581
A11: JULIO | B11: =COUNTIF($A$16:$A$20,A11) -> 1 | C11: =_xlfn.MINIFS($B$16:$B$20,$A$16:$A$20,A11) -> 16.9 | D11: =AVERAGEIF($A$16:$A$20,A11,$B$16:$B$20) -> 16.9 | E11: =_xlfn.MAXIFS($B$16:$B$20,$A$16:$A$20,A11) -> 16.9 | F11: =D11/D10-1 -> 0 | G11: =D11/$D$7-1 -> 0.090322581
F12: SUBIDA TOTAL | G12: =D11/D7-1 -> 0.090322581
A14: DETALLE DE PRECIOS (una línea por precio distinto anotado en el Excel del mes)
A15: MES | B15: PRECIO | C15: CANTIDAD | D15: PRODUCTO (tal cual en el Excel) | E15: ARCHIVO ORIGEN
A16: FEBRERO | B16: 15.5 | C16: 6 | D16: CANTALAPIEDRA CHIVIRITERO 2023 | E16: ALBARANES MAYO 2026
A17: MARZO | B17: 15.5 | D17: CANTALAPIEDRA CHIVIRITERO 2023 | E17: ALBARANES MAYO 2026
A18: ABRIL | B18: 15.5 | D18: CANTALAPIEDRA CHIVIRITERO 2023 | E18: ALBARANES MAYO 2026
A19: MAYO | B19: 16.9 | C19: 12 | D19: CANTALAPIEDRA CHIVIRITERO 2023 | E19: ALBARANES MAYO 2026
A20: JULIO | B20: 16.9 | C20: 12 | D20: CANTALAPIEDRA CHIVIRITERO 2024 | E20: ALBARANES JULIO 2026 v3

Sheet ANCHOAS CANTABRICO RO 550 ET
A1: ANCHOAS CANTABRICO RO 550 ETIQUETA ROJA | I1: ← Volver al resumen
A2: Proveedor: CONSERVAS Y SALAZONES JIMENEZ · Categoría: ENVASADO / BEBIDA / OTROS
A3: Nombres en albaranes: ANCHOAS CANTABRICO RO-550 ETIQUETA ROJA | ANCHOAS CANTABRICO RO-550 ETIQUETA ROJA REZUMAR
A4: Producto envasado / tarifa: cualquier subida de precio unitario entre el primer y el último mes con compras se considera SUBIDA.
A6: MES | B6: Nº PRECIOS | C6: PRECIO MÍN. | D6: PRECIO MEDIO | E6: PRECIO MÁX. | F6: VAR. vs MES ANTERIOR | G6: VAR. vs PRIMER MES
A7: FEBRERO | B7: =COUNTIF($A$15:$A$18,A7) -> 1 | C7: =_xlfn.MINIFS($B$15:$B$18,$A$15:$A$18,A7) -> 18.96 | D7: =AVERAGEIF($A$15:$A$18,A7,$B$15:$B$18) -> 18.96 | E7: =_xlfn.MAXIFS($B$15:$B$18,$A$15:$A$18,A7) -> 18.96
A8: ABRIL | B8: =COUNTIF($A$15:$A$18,A8) -> 1 | C8: =_xlfn.MINIFS($B$15:$B$18,$A$15:$A$18,A8) -> 18.96 | D8: =AVERAGEIF($A$15:$A$18,A8,$B$15:$B$18) -> 18.96 | E8: =_xlfn.MAXIFS($B$15:$B$18,$A$15:$A$18,A8) -> 18.96 | F8: =D8/D7-1 -> 0 | G8: =D8/$D$7-1 -> 0
A9: MAYO | B9: =COUNTIF($A$15:$A$18,A9) -> 1 | C9: =_xlfn.MINIFS($B$15:$B$18,$A$15:$A$18,A9) -> 20.6 | D9: =AVERAGEIF($A$15:$A$18,A9,$B$15:$B$18) -> 20.6 | E9: =_xlfn.MAXIFS($B$15:$B$18,$A$15:$A$18,A9) -> 20.6 | F9: =D9/D8-1 -> 0.08649789 | G9: =D9/$D$7-1 -> 0.08649789
A10: JULIO | B10: =COUNTIF($A$15:$A$18,A10) -> 1 | C10: =_xlfn.MINIFS($B$15:$B$18,$A$15:$A$18,A10) -> 20.6 | D10: =AVERAGEIF($A$15:$A$18,A10,$B$15:$B$18) -> 20.6 | E10: =_xlfn.MAXIFS($B$15:$B$18,$A$15:$A$18,A10) -> 20.6 | F10: =D10/D9-1 -> 0 | G10: =D10/$D$7-1 -> 0.08649789
F11: SUBIDA TOTAL | G11: =D10/D7-1 -> 0.08649789
A13: DETALLE DE PRECIOS (una línea por precio distinto anotado en el Excel del mes)
A14: MES | B14: PRECIO | C14: CANTIDAD | D14: PRODUCTO (tal cual en el Excel) | E14: ARCHIVO ORIGEN
A15: FEBRERO | B15: 18.96 | C15: 12 | D15: ANCHOAS CANTABRICO RO-550 ETIQUETA ROJA REZUMAR | E15: ALBARANES MAYO 2026
A16: ABRIL | B16: 18.96 | D16: ANCHOAS CANTABRICO RO-550 ETIQUETA ROJA REZUMAR | E16: ALBARANES MAYO 2026
A17: MAYO | B17: 20.6 | C17: 12 | D17: ANCHOAS CANTABRICO RO-550 ETIQUETA ROJA REZUMAR | E17: ALBARANES MAYO 2026
A18: JULIO | B18: 20.6 | C18: 18 | D18: ANCHOAS CANTABRICO RO-550 ETIQUETA ROJA | E18: ALBARANES JULIO 2026 v3

Sheet ZACAPA X O
A1: ZACAPA X O | I1: ← Volver al resumen
A2: Proveedor: SUBMARINER · Categoría: ENVASADO / BEBIDA / OTROS
A3: Nombres en albaranes: ACAPA X.O. | ZACAPA X.O.
A4: Producto envasado / tarifa: cualquier subida de precio unitario entre el primer y el último mes con compras se considera SUBIDA.
A6: MES | B6: Nº PRECIOS | C6: PRECIO MÍN. | D6: PRECIO MEDIO | E6: PRECIO MÁX. | F6: VAR. vs MES ANTERIOR | G6: VAR. vs PRIMER MES
A7: ENERO | B7: =COUNTIF($A$13:$A$14,A7) -> 1 | C7: =_xlfn.MINIFS($B$13:$B$14,$A$13:$A$14,A7) -> 122.71 | D7: =AVERAGEIF($A$13:$A$14,A7,$B$13:$B$14) -> 122.71 | E7: =_xlfn.MAXIFS($B$13:$B$14,$A$13:$A$14,A7) -> 122.71
A8: MAYO | B8: =COUNTIF($A$13:$A$14,A8) -> 1 | C8: =_xlfn.MINIFS($B$13:$B$14,$A$13:$A$14,A8) -> 132.94 | D8: =AVERAGEIF($A$13:$A$14,A8,$B$13:$B$14) -> 132.94 | E8: =_xlfn.MAXIFS($B$13:$B$14,$A$13:$A$14,A8) -> 132.94 | F8: =D8/D7-1 -> 0.083367289 | G8: =D8/$D$7-1 -> 0.083367289
F9: SUBIDA TOTAL | G9: =D8/D7-1 -> 0.083367289
A11: DETALLE DE PRECIOS (una línea por precio distinto anotado en el Excel del mes)
A12: MES | B12: PRECIO | C12: CANTIDAD | D12: PRODUCTO (tal cual en el Excel) | E12: ARCHIVO ORIGEN
A13: ENERO | B13: 122.71 | C13: 1 | D13: ZACAPA X.O. | E13: ALBARANES MAYO 2026
A14: MAYO | B14: 132.94 | C14: 2 | D14: ACAPA X.O. | E14: ALBARANES MAYO 2026

Sheet OREMUS 3
A1: OREMUS 3 | I1: ← Volver al resumen
A2: Proveedor: CALIDOSCOPI · Categoría: ENVASADO / BEBIDA / OTROS
A3: Nombres en albaranes: OREMUS 3 | OREMUS 3 PUTTONYOS 2018 (50CL)
A4: Producto envasado / tarifa: cualquier subida de precio unitario entre el primer y el último mes con compras se considera SUBIDA.
A6: MES | B6: Nº PRECIOS | C6: PRECIO MÍN. | D6: PRECIO MEDIO | E6: PRECIO MÁX. | F6: VAR. vs MES ANTERIOR | G6: VAR. vs PRIMER MES
A7: ENERO | B7: =COUNTIF($A$13:$A$14,A7) -> 1 | C7: =_xlfn.MINIFS($B$13:$B$14,$A$13:$A$14,A7) -> 27.4 | D7: =AVERAGEIF($A$13:$A$14,A7,$B$13:$B$14) -> 27.4 | E7: =_xlfn.MAXIFS($B$13:$B$14,$A$13:$A$14,A7) -> 27.4
A8: MAYO | B8: =COUNTIF($A$13:$A$14,A8) -> 1 | C8: =_xlfn.MINIFS($B$13:$B$14,$A$13:$A$14,A8) -> 29.25 | D8: =AVERAGEIF($A$13:$A$14,A8,$B$13:$B$14) -> 29.25 | E8: =_xlfn.MAXIFS($B$13:$B$14,$A$13:$A$14,A8) -> 29.25 | F8: =D8/D7-1 -> 0.067518248 | G8: =D8/$D$7-1 -> 0.067518248
F9: SUBIDA TOTAL | G9: =D8/D7-1 -> 0.067518248
A11: DETALLE DE PRECIOS (una línea por precio distinto anotado en el Excel del mes)
A12: MES | B12: PRECIO | C12: CANTIDAD | D12: PRODUCTO (tal cual en el Excel) | E12: ARCHIVO ORIGEN
A13: ENERO | B13: 27.4 | C13: 6 | D13: OREMUS 3 PUTTONYOS 2018 (50CL) | E13: ALBARANES MAYO 2026
A14: MAYO | B14: 29.25 | C14: 6 | D14: OREMUS 3 | E14: ALBARANES MAYO 2026

Sheet GINEBRA MARTIN MILLER 3 4
A1: GINEBRA MARTIN MILLER 3/4 | I1: ← Volver al resumen
A2: Proveedor: DITEMA (DIST. TENA) · Categoría: ENVASADO / BEBIDA / OTROS
A3: Nombres en albaranes: GINEBRA MARTIN MILLER 3/4
A4: Producto envasado / tarifa: cualquier subida de precio unitario entre el primer y el último mes con compras se considera SUBIDA.
A6: MES | B6: Nº PRECIOS | C6: PRECIO MÍN. | D6: PRECIO MEDIO | E6: PRECIO MÁX. | F6: VAR. vs MES ANTERIOR | G6: VAR. vs PRIMER MES
A7: ENERO | B7: =COUNTIF($A$14:$A$16,A7) -> 1 | C7: =_xlfn.MINIFS($B$14:$B$16,$A$14:$A$16,A7) -> 15.1 | D7: =AVERAGEIF($A$14:$A$16,A7,$B$14:$B$16) -> 15.1 | E7: =_xlfn.MAXIFS($B$14:$B$16,$A$14:$A$16,A7) -> 15.1
A8: MAYO | B8: =COUNTIF($A$14:$A$16,A8) -> 1 | C8: =_xlfn.MINIFS($B$14:$B$16,$A$14:$A$16,A8) -> 16.1 | D8: =AVERAGEIF($A$14:$A$16,A8,$B$14:$B$16) -> 16.1 | E8: =_xlfn.MAXIFS($B$14:$B$16,$A$14:$A$16,A8) -> 16.1 | F8: =D8/D7-1 -> 0.066225166 | G8: =D8/$D$7-1 -> 0.066225166
A9: JULIO | B9: =COUNTIF($A$14:$A$16,A9) -> 1 | C9: =_xlfn.MINIFS($B$14:$B$16,$A$14:$A$16,A9) -> 16.1 | D9: =AVERAGEIF($A$14:$A$16,A9,$B$14:$B$16) -> 16.1 | E9: =_xlfn.MAXIFS($B$14:$B$16,$A$14:$A$16,A9) -> 16.1 | F9: =D9/D8-1 -> 0 | G9: =D9/$D$7-1 -> 0.066225166
F10: SUBIDA TOTAL | G10: =D9/D7-1 -> 0.066225166
A12: DETALLE DE PRECIOS (una línea por precio distinto anotado en el Excel del mes)
A13: MES | B13: PRECIO | C13: CANTIDAD | D13: PRODUCTO (tal cual en el Excel) | E13: ARCHIVO ORIGEN
A14: ENERO | B14: 15.1 | C14: 6 | D14: GINEBRA MARTIN MILLER 3/4 | E14: ALBARANES MAYO 2026
A15: MAYO | B15: 16.1 | C15: 6 | D15: GINEBRA MARTIN MILLER 3/4 | E15: ALBARANES MAYO 2026
A16: JULIO | B16: 16.1 | D16: GINEBRA MARTIN MILLER 3/4 | E16: ALBARANES JULIO 2026 v3

Sheet AQUARADE ZERO NARANJA VIDRIO
A1: AQUARADE ZERO NARANJA VIDRIO 35CL | I1: ← Volver al resumen
A2: Proveedor: VOLDIS · Categoría: ENVASADO / BEBIDA / OTROS
A3: Nombres en albaranes: AQUARADE ZERO NARANJA VIDRIO RET 35CL | AQUARADE ZERO NARANJA VIDRIO RET 35CL CAJA 24U
A4: Producto envasado / tarifa: cualquier subida de precio unitario entre el primer y el último mes con compras se considera SUBIDA.
A6: MES | B6: Nº PRECIOS | C6: PRECIO MÍN. | D6: PRECIO MEDIO | E6: PRECIO MÁX. | F6: VAR. vs MES ANTERIOR | G6: VAR. vs PRIMER MES
A7: ENERO | B7: =COUNTIF($A$15:$A$18,A7) -> 1 | C7: =_xlfn.MINIFS($B$15:$B$18,$A$15:$A$18,A7) -> 31.92 | D7: =AVERAGEIF($A$15:$A$18,A7,$B$15:$B$18) -> 31.92 | E7: =_xlfn.MAXIFS($B$15:$B$18,$A$15:$A$18,A7) -> 31.92
A8: FEBRERO | B8: =COUNTIF($A$15:$A$18,A8) -> 1 | C8: =_xlfn.MINIFS($B$15:$B$18,$A$15:$A$18,A8) -> 33.84 | D8: =AVERAGEIF($A$15:$A$18,A8,$B$15:$B$18) -> 33.84 | E8: =_xlfn.MAXIFS($B$15:$B$18,$A$15:$A$18,A8) -> 33.84 | F8: =D8/D7-1 -> 0.060150376 | G8: =D8/$D$7-1 -> 0.060150376
A9: MAYO | B9: =COUNTIF($A$15:$A$18,A9) -> 1 | C9: =_xlfn.MINIFS($B$15:$B$18,$A$15:$A$18,A9) -> 33.84 | D9: =AVERAGEIF($A$15:$A$18,A9,$B$15:$B$18) -> 33.84 | E9: =_xlfn.MAXIFS($B$15:$B$18,$A$15:$A$18,A9) -> 33.84 | F9: =D9/D8-1 -> 0 | G9: =D9/$D$7-1 -> 0.060150376
A10: JULIO | B10: =COUNTIF($A$15:$A$18,A10) -> 1 | C10: =_xlfn.MINIFS($B$15:$B$18,$A$15:$A$18,A10) -> 33.84 | D10: =AVERAGEIF($A$15:$A$18,A10,$B$15:$B$18) -> 33.84 | E10: =_xlfn.MAXIFS($B$15:$B$18,$A$15:$A$18,A10) -> 33.84 | F10: =D10/D9-1 -> 0 | G10: =D10/$D$7-1 -> 0.060150376
F11: SUBIDA TOTAL | G11: =D10/D7-1 -> 0.060150376
A13: DETALLE DE PRECIOS (una línea por precio distinto anotado en el Excel del mes)
A14: MES | B14: PRECIO | C14: CANTIDAD | D14: PRODUCTO (tal cual en el Excel) | E14: ARCHIVO ORIGEN
A15: ENERO | B15: 31.92 | C15: 4 | D15: AQUARADE ZERO NARANJA VIDRIO RET 35CL CAJA 24U | E15: ALBARANES MAYO 2026
A16: FEBRERO | B16: 33.84 | C16: 2 | D16: AQUARADE ZERO NARANJA VIDRIO RET 35CL CAJA 24U | E16: ALBARANES MAYO 2026
A17: MAYO | B17: 33.84 | C17: 3 | D17: AQUARADE ZERO NARANJA VIDRIO RET 35CL CAJA 24U | E17: ALBARANES MAYO 2026
A18: JULIO | B18: 33.84 | C18: 2 | D18: AQUARADE ZERO NARANJA VIDRIO RET 35CL | E18: ALBARANES JULIO 2026 v3

Sheet VENTRESCA BONITO EXTRA
A1: VENTRESCA BONITO EXTRA | I1: ← Volver al resumen
A2: Proveedor: CONSERVAS Y SALAZONES JIMENEZ · Categoría: ENVASADO / BEBIDA / OTROS
A3: Nombres en albaranes: VENTRESCA DE BONITO EXTRA | VENTRESCA DE BONITO EXTRA EN ACEITE OL-120 ARROYABE
A4: Producto envasado / tarifa: cualquier subida de precio unitario entre el primer y el último mes con compras se considera SUBIDA.
A6: MES | B6: Nº PRECIOS | C6: PRECIO MÍN. | D6: PRECIO MEDIO | E6: PRECIO MÁX. | F6: VAR. vs MES ANTERIOR | G6: VAR. vs PRIMER MES
A7: ENERO | B7: =COUNTIF($A$17:$A$22,A7) -> 1 | C7: =_xlfn.MINIFS($B$17:$B$22,$A$17:$A$22,A7) -> 5.56 | D7: =AVERAGEIF($A$17:$A$22,A7,$B$17:$B$22) -> 5.56 | E7: =_xlfn.MAXIFS($B$17:$B$22,$A$17:$A$22,A7) -> 5.56
A8: FEBRERO | B8: =COUNTIF($A$17:$A$22,A8) -> 1 | C8: =_xlfn.MINIFS($B$17:$B$22,$A$17:$A$22,A8) -> 5.56 | D8: =AVERAGEIF($A$17:$A$22,A8,$B$17:$B$22) -> 5.56 | E8: =_xlfn.MAXIFS($B$17:$B$22,$A$17:$A$22,A8) -> 5.56 | F8: =D8/D7-1 -> 0 | G8: =D8/$D$7-1 -> 0
A9: ABRIL | B9: =COUNTIF($A$17:$A$22,A9) -> 1 | C9: =_xlfn.MINIFS($B$17:$B$22,$A$17:$A$22,A9) -> 5.56 | D9: =AVERAGEIF($A$17:$A$22,A9,$B$17:$B$22) -> 5.56 | E9: =_xlfn.MAXIFS($B$17:$B$22,$A$17:$A$22,A9) -> 5.56 | F9: =D9/D8-1 -> 0 | G9: =D9/$D$7-1 -> 0
A10: MAYO | B10: =COUNTIF($A$17:$A$22,A10) -> 1 | C10: =_xlfn.MINIFS($B$17:$B$22,$A$17:$A$22,A10) -> 5.56 | D10: =AVERAGEIF($A$17:$A$22,A10,$B$17:$B$22) -> 5.56 | E10: =_xlfn.MAXIFS($B$17:$B$22,$A$17:$A$22,A10) -> 5.56 | F10: =D10/D9-1 -> 0 | G10: =D10/$D$7-1 -> 0
A11: JULIO | B11: =COUNTIF($A$17:$A$22,A11) -> 1 | C11: =_xlfn.MINIFS($B$17:$B$22,$A$17:$A$22,A11) -> 5.86 | D11: =AVERAGEIF($A$17:$A$22,A11,$B$17:$B$22) -> 5.86 | E11: =_xlfn.MAXIFS($B$17:$B$22,$A$17:$A$22,A11) -> 5.86 | F11: =D11/D10-1 -> 0.053956835 | G11: =D11/$D$7-1 -> 0.053956835
A12: AGOSTO | B12: =COUNTIF($A$17:$A$22,A12) -> 1 | C12: =_xlfn.MINIFS($B$17:$B$22,$A$17:$A$22,A12) -> 5.86 | D12: =AVERAGEIF($A$17:$A$22,A12,$B$17:$B$22) -> 5.86 | E12: =_xlfn.MAXIFS($B$17:$B$22,$A$17:$A$22,A12) -> 5.86 | F12: =D12/D11-1 -> 0 | G12: =D12/$D$7-1 -> 0.053956835
F13: SUBIDA TOTAL | G13: =D12/D7-1 -> 0.053956835
A15: DETALLE DE PRECIOS (una línea por precio distinto anotado en el Excel del mes)
A16: MES | B16: PRECIO | C16: CANTIDAD | D16: PRODUCTO (tal cual en el Excel) | E16: ARCHIVO ORIGEN
A17: ENERO | B17: 5.56 | C17: 24 | D17: VENTRESCA DE BONITO EXTRA EN ACEITE OL-120 ARROYABE | E17: ALBARANES MAYO 2026
A18: FEBRERO | B18: 5.56 | C18: 48 | D18: VENTRESCA DE BONITO EXTRA EN ACEITE OL-120 ARROYABE | E18: ALBARANES MAYO 2026
A19: ABRIL | B19: 5.56 | C19: 48 | D19: VENTRESCA DE BONITO EXTRA EN ACEITE OL-120 ARROYABE | E19: ALBARANES MAYO 2026
A20: MAYO | B20: 5.56 | C20: 24 | D20: VENTRESCA DE BONITO EXTRA EN ACEITE OL-120 ARROYABE | E20: ALBARANES MAYO 2026
A21: JULIO | B21: 5.86 | D21: VENTRESCA DE BONITO EXTRA | E21: ALBARANES JULIO 2026 v3
A22: AGOSTO | B22: 5.86 | C22: 24 | D22: VENTRESCA DE BONITO EXTRA | E22: ALBARANES AGOSTO 2026 v1

Sheet SOLAN CABRAS CON GAS
A1: SOLAN CABRAS CON GAS | I1: ← Volver al resumen
A2: Proveedor: EIF DISTRIBUCIONES · Categoría: ENVASADO / BEBIDA / OTROS
A3: Nombres en albaranes: SOLAN DE CABRAS CON GAS | SOLAN DE CABRAS CON GAS 0.33
A4: Producto envasado / tarifa: cualquier subida de precio unitario entre el primer y el último mes con compras se considera SUBIDA.
A6: MES | B6: Nº PRECIOS | C6: PRECIO MÍN. | D6: PRECIO MEDIO | E6: PRECIO MÁX. | F6: VAR. vs MES ANTERIOR | G6: VAR. vs PRIMER MES
A7: ENERO | B7: =COUNTIF($A$14:$A$17,A7) -> 2 | C7: =_xlfn.MINIFS($B$14:$B$17,$A$14:$A$17,A7) -> 25.44 | D7: =AVERAGEIF($A$14:$A$17,A7,$B$14:$B$17) -> 25.44 | E7: =_xlfn.MAXIFS($B$14:$B$17,$A$14:$A$17,A7) -> 25.44
A8: JULIO | B8: =COUNTIF($A$14:$A$17,A8) -> 1 | C8: =_xlfn.MINIFS($B$14:$B$17,$A$14:$A$17,A8) -> 26.8 | D8: =AVERAGEIF($A$14:$A$17,A8,$B$14:$B$17) -> 26.8 | E8: =_xlfn.MAXIFS($B$14:$B$17,$A$14:$A$17,A8) -> 26.8 | F8: =D8/D7-1 -> 0.053459119 | G8: =D8/$D$7-1 -> 0.053459119
A9: AGOSTO | B9: =COUNTIF($A$14:$A$17,A9) -> 1 | C9: =_xlfn.MINIFS($B$14:$B$17,$A$14:$A$17,A9) -> 26.8 | D9: =AVERAGEIF($A$14:$A$17,A9,$B$14:$B$17) -> 26.8 | E9: =_xlfn.MAXIFS($B$14:$B$17,$A$14:$A$17,A9) -> 26.8 | F9: =D9/D8-1 -> 0 | G9: =D9/$D$7-1 -> 0.053459119
F10: SUBIDA TOTAL | G10: =D9/D7-1 -> 0.053459119
A12: DETALLE DE PRECIOS (una línea por precio distinto anotado en el Excel del mes)
A13: MES | B13: PRECIO | C13: CANTIDAD | D13: PRODUCTO (tal cual en el Excel) | E13: ARCHIVO ORIGEN
A14: ENERO | B14: 25.44 | C14: 3 | D14: SOLAN DE CABRAS CON GAS 0.33 | E14: ALBARANES MAYO 2026
A15: ENERO | B15: 25.44 | D15: SOLAN DE CABRAS CON GAS 0.33 | E15: ALBARANES MAYO 2026
A16: JULIO | B16: 26.8 | C16: 5 | D16: SOLAN DE CABRAS CON GAS | E16: ALBARANES JULIO 2026 v3
A17: AGOSTO | B17: 26.8 | C17: 2 | D17: SOLAN DE CABRAS CON GAS | E17: ALBARANES AGOSTO 2026 v1

Sheet AGUA SOLAN CABRAS VIDRIO 50C
A1: AGUA SOLAN CABRAS VIDRIO 50CL | I1: ← Volver al resumen
A2: Proveedor: VOLDIS · Categoría: ENVASADO / BEBIDA / OTROS
A3: Nombres en albaranes: AGUA SOLAN DE CABRAS VIDRIO RET 50CL 20U | AGUA SOLAN DE CABRAS VIDRIO RET 50CL CAJA 20UDS
A4: Producto envasado / tarifa: cualquier subida de precio unitario entre el primer y el último mes con compras se considera SUBIDA.
A6: MES | B6: Nº PRECIOS | C6: PRECIO MÍN. | D6: PRECIO MEDIO | E6: PRECIO MÁX. | F6: VAR. vs MES ANTERIOR | G6: VAR. vs PRIMER MES
A7: ENERO | B7: =COUNTIF($A$15:$A$18,A7) -> 1 | C7: =_xlfn.MINIFS($B$15:$B$18,$A$15:$A$18,A7) -> 11.68 | D7: =AVERAGEIF($A$15:$A$18,A7,$B$15:$B$18) -> 11.68 | E7: =_xlfn.MAXIFS($B$15:$B$18,$A$15:$A$18,A7) -> 11.68
A8: FEBRERO | B8: =COUNTIF($A$15:$A$18,A8) -> 1 | C8: =_xlfn.MINIFS($B$15:$B$18,$A$15:$A$18,A8) -> 11.68 | D8: =AVERAGEIF($A$15:$A$18,A8,$B$15:$B$18) -> 11.68 | E8: =_xlfn.MAXIFS($B$15:$B$18,$A$15:$A$18,A8) -> 11.68 | F8: =D8/D7-1 -> 0 | G8: =D8/$D$7-1 -> 0
A9: MAYO | B9: =COUNTIF($A$15:$A$18,A9) -> 1 | C9: =_xlfn.MINIFS($B$15:$B$18,$A$15:$A$18,A9) -> 11.68 | D9: =AVERAGEIF($A$15:$A$18,A9,$B$15:$B$18) -> 11.68 | E9: =_xlfn.MAXIFS($B$15:$B$18,$A$15:$A$18,A9) -> 11.68 | F9: =D9/D8-1 -> 0 | G9: =D9/$D$7-1 -> 0
A10: JULIO | B10: =COUNTIF($A$15:$A$18,A10) -> 1 | C10: =_xlfn.MINIFS($B$15:$B$18,$A$15:$A$18,A10) -> 12.3 | D10: =AVERAGEIF($A$15:$A$18,A10,$B$15:$B$18) -> 12.3 | E10: =_xlfn.MAXIFS($B$15:$B$18,$A$15:$A$18,A10) -> 12.3 | F10: =D10/D9-1 -> 0.053082192 | G10: =D10/$D$7-1 -> 0.053082192
F11: SUBIDA TOTAL | G11: =D10/D7-1 -> 0.053082192
A13: DETALLE DE PRECIOS (una línea por precio distinto anotado en el Excel del mes)
A14: MES | B14: PRECIO | C14: CANTIDAD | D14: PRODUCTO (tal cual en el Excel) | E14: ARCHIVO ORIGEN
A15: ENERO | B15: 11.68 | C15: 44 | D15: AGUA SOLAN DE CABRAS VIDRIO RET 50CL CAJA 20UDS | E15: ALBARANES MAYO 2026
A16: FEBRERO | B16: 11.68 | C16: 40 | D16: AGUA SOLAN DE CABRAS VIDRIO RET 50CL CAJA 20UDS | E16: ALBARANES MAYO 2026
A17: MAYO | B17: 11.68 | C17: 49 | D17: AGUA SOLAN DE CABRAS VIDRIO RET 50CL CAJA 20UDS | E17: ALBARANES MAYO 2026
A18: JULIO | B18: 12.3 | C18: 49 | D18: AGUA SOLAN DE CABRAS VIDRIO RET 50CL 20U | E18: ALBARANES JULIO 2026 v3

Sheet AGUA CON GAS SOLAN CABRAS VI
A1: AGUA CON GAS SOLAN CABRAS VIDRIO 33CL | I1: ← Volver al resumen
A2: Proveedor: VOLDIS · Categoría: ENVASADO / BEBIDA / OTROS
A3: Nombres en albaranes: AGUA CON GAS SOLAN DE CABRAS VIDRIO NR 33CL | AGUA CON GAS SOLAN DE CABRAS VIDRIO RNR 33CL
A4: Producto envasado / tarifa: cualquier subida de precio unitario entre el primer y el último mes con compras se considera SUBIDA.
A6: MES | B6: Nº PRECIOS | C6: PRECIO MÍN. | D6: PRECIO MEDIO | E6: PRECIO MÁX. | F6: VAR. vs MES ANTERIOR | G6: VAR. vs PRIMER MES
A7: ENERO | B7: =COUNTIF($A$15:$A$18,A7) -> 1 | C7: =_xlfn.MINIFS($B$15:$B$18,$A$15:$A$18,A7) -> 25.464 | D7: =AVERAGEIF($A$15:$A$18,A7,$B$15:$B$18) -> 25.464 | E7: =_xlfn.MAXIFS($B$15:$B$18,$A$15:$A$18,A7) -> 25.464
A8: FEBRERO | B8: =COUNTIF($A$15:$A$18,A8) -> 1 | C8: =_xlfn.MINIFS($B$15:$B$18,$A$15:$A$18,A8) -> 25.464 | D8: =AVERAGEIF($A$15:$A$18,A8,$B$15:$B$18) -> 25.464 | E8: =_xlfn.MAXIFS($B$15:$B$18,$A$15:$A$18,A8) -> 25.464 | F8: =D8/D7-1 -> 0 | G8: =D8/$D$7-1 -> 0
A9: MAYO | B9: =COUNTIF($A$15:$A$18,A9) -> 1 | C9: =_xlfn.MINIFS($B$15:$B$18,$A$15:$A$18,A9) -> 25.464 | D9: =AVERAGEIF($A$15:$A$18,A9,$B$15:$B$18) -> 25.464 | E9: =_xlfn.MAXIFS($B$15:$B$18,$A$15:$A$18,A9) -> 25.464 | F9: =D9/D8-1 -> 0 | G9: =D9/$D$7-1 -> 0
A10: JULIO | B10: =COUNTIF($A$15:$A$18,A10) -> 1 | C10: =_xlfn.MINIFS($B$15:$B$18,$A$15:$A$18,A10) -> 26.81 | D10: =AVERAGEIF($A$15:$A$18,A10,$B$15:$B$18) -> 26.81 | E10: =_xlfn.MAXIFS($B$15:$B$18,$A$15:$A$18,A10) -> 26.81 | F10: =D10/D9-1 -> 0.052858938 | G10: =D10/$D$7-1 -> 0.052858938
F11: SUBIDA TOTAL | G11: =D10/D7-1 -> 0.052858938
A13: DETALLE DE PRECIOS (una línea por precio distinto anotado en el Excel del mes)
A14: MES | B14: PRECIO | C14: CANTIDAD | D14: PRODUCTO (tal cual en el Excel) | E14: ARCHIVO ORIGEN
A15: ENERO | B15: 25.464 | C15: 36 | D15: AGUA CON GAS SOLAN DE CABRAS VIDRIO NR 33CL | E15: ALBARANES MAYO 2026
A16: FEBRERO | B16: 25.464 | C16: 35 | D16: AGUA CON GAS SOLAN DE CABRAS VIDRIO NR 33CL | E16: ALBARANES MAYO 2026
A17: MAYO | B17: 25.464 | C17: 47 | D17: AGUA CON GAS SOLAN DE CABRAS VIDRIO NR 33CL | E17: ALBARANES MAYO 2026
A18: JULIO | B18: 26.81 | C18: 41 | D18: AGUA CON GAS SOLAN DE CABRAS VIDRIO RNR 33CL | E18: ALBARANES JULIO 2026 v3

Sheet MOJAMA EXTRA SUPERIOR CHANCA
A1: MOJAMA EXTRA SUPERIOR CHANCA | I1: ← Volver al resumen
A2: Proveedor: CONSERVAS Y SALAZONES JIMENEZ · Categoría: ENVASADO / BEBIDA / OTROS
A3: Nombres en albaranes: MOJAMA EXTRA SUPERIOR LA CHANCA
A4: Producto envasado / tarifa: cualquier subida de precio unitario entre el primer y el último mes con compras se considera SUBIDA.
A6: MES | B6: Nº PRECIOS | C6: PRECIO MÍN. | D6: PRECIO MEDIO | E6: PRECIO MÁX. | F6: VAR. vs MES ANTERIOR | G6: VAR. vs PRIMER MES
A7: ENERO | B7: =COUNTIF($A$15:$A$18,A7) -> 1 | C7: =_xlfn.MINIFS($B$15:$B$18,$A$15:$A$18,A7) -> 34.6 | D7: =AVERAGEIF($A$15:$A$18,A7,$B$15:$B$18) -> 34.6 | E7: =_xlfn.MAXIFS($B$15:$B$18,$A$15:$A$18,A7) -> 34.6
A8: MAYO | B8: =COUNTIF($A$15:$A$18,A8) -> 1 | C8: =_xlfn.MINIFS($B$15:$B$18,$A$15:$A$18,A8) -> 36.4 | D8: =AVERAGEIF($A$15:$A$18,A8,$B$15:$B$18) -> 36.4 | E8: =_xlfn.MAXIFS($B$15:$B$18,$A$15:$A$18,A8) -> 36.4 | F8: =D8/D7-1 -> 0.052023121 | G8: =D8/$D$7-1 -> 0.052023121
A9: JULIO | B9: =COUNTIF($A$15:$A$18,A9) -> 1 | C9: =_xlfn.MINIFS($B$15:$B$18,$A$15:$A$18,A9) -> 36.4 | D9: =AVERAGEIF($A$15:$A$18,A9,$B$15:$B$18) -> 36.4 | E9: =_xlfn.MAXIFS($B$15:$B$18,$A$15:$A$18,A9) -> 36.4 | F9: =D9/D8-1 -> 0 | G9: =D9/$D$7-1 -> 0.052023121
A10: AGOSTO | B10: =COUNTIF($A$15:$A$18,A10) -> 1 | C10: =_xlfn.MINIFS($B$15:$B$18,$A$15:$A$18,A10) -> 36.4 | D10: =AVERAGEIF($A$15:$A$18,A10,$B$15:$B$18) -> 36.4 | E10: =_xlfn.MAXIFS($B$15:$B$18,$A$15:$A$18,A10) -> 36.4 | F10: =D10/D9-1 -> 0 | G10: =D10/$D$7-1 -> 0.052023121
F11: SUBIDA TOTAL | G11: =D10/D7-1 -> 0.052023121
A13: DETALLE DE PRECIOS (una línea por precio distinto anotado en el Excel del mes)
A14: MES | B14: PRECIO | C14: CANTIDAD | D14: PRODUCTO (tal cual en el Excel) | E14: ARCHIVO ORIGEN
A15: ENERO | B15: 34.6 | C15: 2.25 | D15: MOJAMA EXTRA SUPERIOR LA CHANCA | E15: ALBARANES MAYO 2026
A16: MAYO | B16: 36.4 | C16: 0.708 | D16: MOJAMA EXTRA SUPERIOR LA CHANCA | E16: ALBARANES MAYO 2026
A17: JULIO | B17: 36.4 | C17: 2.71 | D17: MOJAMA EXTRA SUPERIOR LA CHANCA | E17: ALBARANES JULIO 2026 v3
A18: AGOSTO | B18: 36.4 | C18: 1.94 | D18: MOJAMA EXTRA SUPERIOR LA CHANCA | E18: ALBARANES AGOSTO 2026 v1

Sheet BITTER KAS VIDRIO 20CL
A1: BITTER KAS VIDRIO 20CL | I1: ← Volver al resumen
A2: Proveedor: VOLDIS · Categoría: ENVASADO / BEBIDA / OTROS
A3: Nombres en albaranes: BITTER KAS VIDRIO NR 20CL CAJA 24U
A4: Producto envasado / tarifa: cualquier subida de precio unitario entre el primer y el último mes con compras se considera SUBIDA.
A6: MES | B6: Nº PRECIOS | C6: PRECIO MÍN. | D6: PRECIO MEDIO | E6: PRECIO MÁX. | F6: VAR. vs MES ANTERIOR | G6: VAR. vs PRIMER MES
A7: ENERO | B7: =COUNTIF($A$13:$A$14,A7) -> 1 | C7: =_xlfn.MINIFS($B$13:$B$14,$A$13:$A$14,A7) -> 37.68 | D7: =AVERAGEIF($A$13:$A$14,A7,$B$13:$B$14) -> 37.68 | E7: =_xlfn.MAXIFS($B$13:$B$14,$A$13:$A$14,A7) -> 37.68
A8: MAYO | B8: =COUNTIF($A$13:$A$14,A8) -> 1 | C8: =_xlfn.MINIFS($B$13:$B$14,$A$13:$A$14,A8) -> 39.6 | D8: =AVERAGEIF($A$13:$A$14,A8,$B$13:$B$14) -> 39.6 | E8: =_xlfn.MAXIFS($B$13:$B$14,$A$13:$A$14,A8) -> 39.6 | F8: =D8/D7-1 -> 0.050955414 | G8: =D8/$D$7-1 -> 0.050955414
F9: SUBIDA TOTAL | G9: =D8/D7-1 -> 0.050955414
A11: DETALLE DE PRECIOS (una línea por precio distinto anotado en el Excel del mes)
A12: MES | B12: PRECIO | C12: CANTIDAD | D12: PRODUCTO (tal cual en el Excel) | E12: ARCHIVO ORIGEN
A13: ENERO | B13: 37.68 | C13: 1 | D13: BITTER KAS VIDRIO NR 20CL CAJA 24U | E13: ALBARANES MAYO 2026
A14: MAYO | B14: 39.6 | C14: 2 | D14: BITTER KAS VIDRIO NR 20CL CAJA 24U | E14: ALBARANES MAYO 2026

Sheet AQUARADE ZERO LIMON VIDRIO 3
A1: AQUARADE ZERO LIMON VIDRIO 35CL | I1: ← Volver al resumen
A2: Proveedor: VOLDIS · Categoría: ENVASADO / BEBIDA / OTROS
A3: Nombres en albaranes: AQUARADE ZERO LIMON VIDRIO RET 35CL | AQUARADE ZERO LIMON VIDRIO RET 35CL CAJA 24U
A4: Producto envasado / tarifa: cualquier subida de precio unitario entre el primer y el último mes con compras se considera SUBIDA.
A6: MES | B6: Nº PRECIOS | C6: PRECIO MÍN. | D6: PRECIO MEDIO | E6: PRECIO MÁX. | F6: VAR. vs MES ANTERIOR | G6: VAR. vs PRIMER MES
A7: ENERO | B7: =COUNTIF($A$15:$A$18,A7) -> 1 | C7: =_xlfn.MINIFS($B$15:$B$18,$A$15:$A$18,A7) -> 31.92 | D7: =AVERAGEIF($A$15:$A$18,A7,$B$15:$B$18) -> 31.92 | E7: =_xlfn.MAXIFS($B$15:$B$18,$A$15:$A$18,A7) -> 31.92
A8: FEBRERO | B8: =COUNTIF($A$15:$A$18,A8) -> 1 | C8: =_xlfn.MINIFS($B$15:$B$18,$A$15:$A$18,A8) -> 33.84 | D8: =AVERAGEIF($A$15:$A$18,A8,$B$15:$B$18) -> 33.84 | E8: =_xlfn.MAXIFS($B$15:$B$18,$A$15:$A$18,A8) -> 33.84 | F8: =D8/D7-1 -> 0.060150376 | G8: =D8/$D$7-1 -> 0.060150376
A9: MAYO | B9: =COUNTIF($A$15:$A$18,A9) -> 1 | C9: =_xlfn.MINIFS($B$15:$B$18,$A$15:$A$18,A9) -> 33.84 | D9: =AVERAGEIF($A$15:$A$18,A9,$B$15:$B$18) -> 33.84 | E9: =_xlfn.MAXIFS($B$15:$B$18,$A$15:$A$18,A9) -> 33.84 | F9: =D9/D8-1 -> 0 | G9: =D9/$D$7-1 -> 0.060150376
A10: JULIO | B10: =COUNTIF($A$15:$A$18,A10) -> 1 | C10: =_xlfn.MINIFS($B$15:$B$18,$A$15:$A$18,A10) -> 33.54 | D10: =AVERAGEIF($A$15:$A$18,A10,$B$15:$B$18) -> 33.54 | E10: =_xlfn.MAXIFS($B$15:$B$18,$A$15:$A$18,A10) -> 33.54 | F10: =D10/D9-1 -> -0.0088652482 | G10: =D10/$D$7-1 -> 0.05075188
F11: SUBIDA TOTAL | G11: =D10/D7-1 -> 0.05075188
A13: DETALLE DE PRECIOS (una línea por precio distinto anotado en el Excel del mes)
A14: MES | B14: PRECIO | C14: CANTIDAD | D14: PRODUCTO (tal cual en el Excel) | E14: ARCHIVO ORIGEN
A15: ENERO | B15: 31.92 | C15: 5 | D15: AQUARADE ZERO LIMON VIDRIO RET 35CL CAJA 24U | E15: ALBARANES MAYO 2026
A16: FEBRERO | B16: 33.84 | C16: 3 | D16: AQUARADE ZERO LIMON VIDRIO RET 35CL CAJA 24U | E16: ALBARANES MAYO 2026
A17: MAYO | B17: 33.84 | C17: 5 | D17: AQUARADE ZERO LIMON VIDRIO RET 35CL CAJA 24U | E17: ALBARANES MAYO 2026
A18: JULIO | B18: 33.54 | C18: 3 | D18: AQUARADE ZERO LIMON VIDRIO RET 35CL | E18: ALBARANES JULIO 2026 v3

Sheet LOMO BELLOTA 100 SM
A1: LOMO BELLOTA 100 SM | I1: ← Volver al resumen
A2: Proveedor: EL ESCRIBANO · Categoría: ENVASADO / BEBIDA / OTROS
A3: Nombres en albaranes: LOMO BELLOTA 100% | LOMO BELLOTA 100% SM
A4: Producto envasado / tarifa: cualquier subida de precio unitario entre el primer y el último mes con compras se considera SUBIDA.
A6: MES | B6: Nº PRECIOS | C6: PRECIO MÍN. | D6: PRECIO MEDIO | E6: PRECIO MÁX. | F6: VAR. vs MES ANTERIOR | G6: VAR. vs PRIMER MES
A7: FEBRERO | B7: =COUNTIF($A$16:$A$21,A7) -> 1 | C7: =_xlfn.MINIFS($B$16:$B$21,$A$16:$A$21,A7) -> 48.6 | D7: =AVERAGEIF($A$16:$A$21,A7,$B$16:$B$21) -> 48.6 | E7: =_xlfn.MAXIFS($B$16:$B$21,$A$16:$A$21,A7) -> 48.6
A8: ABRIL | B8: =COUNTIF($A$16:$A$21,A8) -> 1 | C8: =_xlfn.MINIFS($B$16:$B$21,$A$16:$A$21,A8) -> 48.6 | D8: =AVERAGEIF($A$16:$A$21,A8,$B$16:$B$21) -> 48.6 | E8: =_xlfn.MAXIFS($B$16:$B$21,$A$16:$A$21,A8) -> 48.6 | F8: =D8/D7-1 -> 0 | G8: =D8/$D$7-1 -> 0
A9: MAYO | B9: =COUNTIF($A$16:$A$21,A9) -> 1 | C9: =_xlfn.MINIFS($B$16:$B$21,$A$16:$A$21,A9) -> 48.6 | D9: =AVERAGEIF($A$16:$A$21,A9,$B$16:$B$21) -> 48.6 | E9: =_xlfn.MAXIFS($B$16:$B$21,$A$16:$A$21,A9) -> 48.6 | F9: =D9/D8-1 -> 0 | G9: =D9/$D$7-1 -> 0
A10: JULIO | B10: =COUNTIF($A$16:$A$21,A10) -> 2 | C10: =_xlfn.MINIFS($B$16:$B$21,$A$16:$A$21,A10) -> 48.6 | D10: =AVERAGEIF($A$16:$A$21,A10,$B$16:$B$21) -> 49.8 | E10: =_xlfn.MAXIFS($B$16:$B$21,$A$16:$A$21,A10) -> 51 | F10: =D10/D9-1 -> 0.024691358 | G10: =D10/$D$7-1 -> 0.024691358
A11: AGOSTO | B11: =COUNTIF($A$16:$A$21,A11) -> 1 | C11: =_xlfn.MINIFS($B$16:$B$21,$A$16:$A$21,A11) -> 51 | D11: =AVERAGEIF($A$16:$A$21,A11,$B$16:$B$21) -> 51 | E11: =_xlfn.MAXIFS($B$16:$B$21,$A$16:$A$21,A11) -> 51 | F11: =D11/D10-1 -> 0.024096386 | G11: =D11/$D$7-1 -> 0.049382716
F12: SUBIDA TOTAL | G12: =D11/D7-1 -> 0.049382716
A14: DETALLE DE PRECIOS (una línea por precio distinto anotado en el Excel del mes)
A15: MES | B15: PRECIO | C15: CANTIDAD | D15: PRODUCTO (tal cual en el Excel) | E15: ARCHIVO ORIGEN
A16: FEBRERO | B16: 48.6 | C16: 2 | D16: LOMO BELLOTA 100% SM | E16: ALBARANES MAYO 2026
A17: ABRIL | B17: 48.6 | C17: 3.1 | D17: LOMO BELLOTA 100% SM | E17: ALBARANES MAYO 2026
A18: MAYO | B18: 48.6 | C18: 2.2 | D18: LOMO BELLOTA 100% SM | E18: ALBARANES MAYO 2026
A19: JULIO | B19: 48.6 | D19: LOMO BELLOTA 100% | E19: ALBARANES JULIO 2026 v3
A20: JULIO | B20: 51 | C20: 1.1 | D20: LOMO BELLOTA 100% | E20: ALBARANES JULIO 2026 v3
A21: AGOSTO | B21: 51 | C21: 1.1 | D21: LOMO BELLOTA 100% | E21: ALBARANES AGOSTO 2026 v1

Sheet COCA COLA ZERO NAC
A1: COCA COLA ZERO NAC | I1: ← Volver al resumen
A2: Proveedor: EIF DISTRIBUCIONES · Categoría: ENVASADO / BEBIDA / OTROS
A3: Nombres en albaranes: COCA COLA ZERO NAC RET | COCA-COLA ZERO NAC RET
A4: Producto envasado / tarifa: cualquier subida de precio unitario entre el primer y el último mes con compras se considera SUBIDA.
A6: MES | B6: Nº PRECIOS | C6: PRECIO MÍN. | D6: PRECIO MEDIO | E6: PRECIO MÁX. | F6: VAR. vs MES ANTERIOR | G6: VAR. vs PRIMER MES
A7: ENERO | B7: =COUNTIF($A$13:$A$15,A7) -> 2 | C7: =_xlfn.MINIFS($B$13:$B$15,$A$13:$A$15,A7) -> 20.78 | D7: =AVERAGEIF($A$13:$A$15,A7,$B$13:$B$15) -> 20.78 | E7: =_xlfn.MAXIFS($B$13:$B$15,$A$13:$A$15,A7) -> 20.78
A8: AGOSTO | B8: =COUNTIF($A$13:$A$15,A8) -> 1 | C8: =_xlfn.MINIFS($B$13:$B$15,$A$13:$A$15,A8) -> 21.78 | D8: =AVERAGEIF($A$13:$A$15,A8,$B$13:$B$15) -> 21.78 | E8: =_xlfn.MAXIFS($B$13:$B$15,$A$13:$A$15,A8) -> 21.78 | F8: =D8/D7-1 -> 0.048123195 | G8: =D8/$D$7-1 -> 0.048123195
F9: SUBIDA TOTAL | G9: =D8/D7-1 -> 0.048123195
A11: DETALLE DE PRECIOS (una línea por precio distinto anotado en el Excel del mes)
A12: MES | B12: PRECIO | C12: CANTIDAD | D12: PRODUCTO (tal cual en el Excel) | E12: ARCHIVO ORIGEN
A13: ENERO | B13: 20.78 | C13: 6 | D13: COCA-COLA ZERO NAC RET | E13: ALBARANES MAYO 2026
A14: ENERO | B14: 20.78 | C14: 4 | D14: COCA-COLA ZERO NAC RET | E14: ALBARANES MAYO 2026
A15: AGOSTO | B15: 21.78 | C15: 4 | D15: COCA COLA ZERO NAC RET | E15: ALBARANES AGOSTO 2026 v1

Sheet MANZANILLA SOLEAR 3 8
A1: MANZANILLA SOLEAR 3/8 | I1: ← Volver al resumen
A2: Proveedor: MUNDELA · Categoría: ENVASADO / BEBIDA / OTROS
A3: Nombres en albaranes: MANZANILLA SOLEAR 3/8
A4: Producto envasado / tarifa: cualquier subida de precio unitario entre el primer y el último mes con compras se considera SUBIDA.
A6: MES | B6: Nº PRECIOS | C6: PRECIO MÍN. | D6: PRECIO MEDIO | E6: PRECIO MÁX. | F6: VAR. vs MES ANTERIOR | G6: VAR. vs PRIMER MES
A7: ENERO | B7: =COUNTIF($A$15:$A$18,A7) -> 1 | C7: =_xlfn.MINIFS($B$15:$B$18,$A$15:$A$18,A7) -> 4.22 | D7: =AVERAGEIF($A$15:$A$18,A7,$B$15:$B$18) -> 4.22 | E7: =_xlfn.MAXIFS($B$15:$B$18,$A$15:$A$18,A7) -> 4.22
A8: FEBRERO | B8: =COUNTIF($A$15:$A$18,A8) -> 1 | C8: =_xlfn.MINIFS($B$15:$B$18,$A$15:$A$18,A8) -> 4.42 | D8: =AVERAGEIF($A$15:$A$18,A8,$B$15:$B$18) -> 4.42 | E8: =_xlfn.MAXIFS($B$15:$B$18,$A$15:$A$18,A8) -> 4.42 | F8: =D8/D7-1 -> 0.047393365 | G8: =D8/$D$7-1 -> 0.047393365
A9: MAYO | B9: =COUNTIF($A$15:$A$18,A9) -> 1 | C9: =_xlfn.MINIFS($B$15:$B$18,$A$15:$A$18,A9) -> 4.42 | D9: =AVERAGEIF($A$15:$A$18,A9,$B$15:$B$18) -> 4.42 | E9: =_xlfn.MAXIFS($B$15:$B$18,$A$15:$A$18,A9) -> 4.42 | F9: =D9/D8-1 -> 0 | G9: =D9/$D$7-1 -> 0.047393365
A10: AGOSTO | B10: =COUNTIF($A$15:$A$18,A10) -> 1 | C10: =_xlfn.MINIFS($B$15:$B$18,$A$15:$A$18,A10) -> 4.42 | D10: =AVERAGEIF($A$15:$A$18,A10,$B$15:$B$18) -> 4.42 | E10: =_xlfn.MAXIFS($B$15:$B$18,$A$15:$A$18,A10) -> 4.42 | F10: =D10/D9-1 -> 0 | G10: =D10/$D$7-1 -> 0.047393365
F11: SUBIDA TOTAL | G11: =D10/D7-1 -> 0.047393365
A13: DETALLE DE PRECIOS (una línea por precio distinto anotado en el Excel del mes)
A14: MES | B14: PRECIO | C14: CANTIDAD | D14: PRODUCTO (tal cual en el Excel) | E14: ARCHIVO ORIGEN
A15: ENERO | B15: 4.22 | C15: 12 | D15: MANZANILLA SOLEAR 3/8 | E15: ALBARANES MAYO 2026
A16: FEBRERO | B16: 4.42 | C16: 24 | D16: MANZANILLA SOLEAR 3/8 | E16: ALBARANES MAYO 2026
A17: MAYO | B17: 4.42 | C17: 12 | D17: MANZANILLA SOLEAR 3/8 | E17: ALBARANES MAYO 2026
A18: AGOSTO | B18: 4.42 | D18: MANZANILLA SOLEAR 3/8 | E18: ALBARANES AGOSTO 2026 v1

Sheet PICOS ARTESANOS 500 GR
A1: PICOS ARTESANOS 500 GR | I1: ← Volver al resumen
A2: Proveedor: DELIPAN · Categoría: ENVASADO / BEBIDA / OTROS
A3: Nombres en albaranes: PICOS ARTESANOS 500 GR
A4: Producto envasado / tarifa: cualquier subida de precio unitario entre el primer y el último mes con compras se considera SUBIDA.
A6: MES | B6: Nº PRECIOS | C6: PRECIO MÍN. | D6: PRECIO MEDIO | E6: PRECIO MÁX. | F6: VAR. vs MES ANTERIOR | G6: VAR. vs PRIMER MES
A7: ENERO | B7: =COUNTIF($A$15:$A$18,A7) -> 1 | C7: =_xlfn.MINIFS($B$15:$B$18,$A$15:$A$18,A7) -> 10.97 | D7: =AVERAGEIF($A$15:$A$18,A7,$B$15:$B$18) -> 10.97 | E7: =_xlfn.MAXIFS($B$15:$B$18,$A$15:$A$18,A7) -> 10.97
A8: FEBRERO | B8: =COUNTIF($A$15:$A$18,A8) -> 1 | C8: =_xlfn.MINIFS($B$15:$B$18,$A$15:$A$18,A8) -> 10.97 | D8: =AVERAGEIF($A$15:$A$18,A8,$B$15:$B$18) -> 10.97 | E8: =_xlfn.MAXIFS($B$15:$B$18,$A$15:$A$18,A8) -> 10.97 | F8: =D8/D7-1 -> 0 | G8: =D8/$D$7-1 -> 0
A9: ABRIL | B9: =COUNTIF($A$15:$A$18,A9) -> 1 | C9: =_xlfn.MINIFS($B$15:$B$18,$A$15:$A$18,A9) -> 11.48 | D9: =AVERAGEIF($A$15:$A$18,A9,$B$15:$B$18) -> 11.48 | E9: =_xlfn.MAXIFS($B$15:$B$18,$A$15:$A$18,A9) -> 11.48 | F9: =D9/D8-1 -> 0.046490428 | G9: =D9/$D$7-1 -> 0.046490428
A10: MAYO | B10: =COUNTIF($A$15:$A$18,A10) -> 1 | C10: =_xlfn.MINIFS($B$15:$B$18,$A$15:$A$18,A10) -> 11.48 | D10: =AVERAGEIF($A$15:$A$18,A10,$B$15:$B$18) -> 11.48 | E10: =_xlfn.MAXIFS($B$15:$B$18,$A$15:$A$18,A10) -> 11.48 | F10: =D10/D9-1 -> 0 | G10: =D10/$D$7-1 -> 0.046490428
F11: SUBIDA TOTAL | G11: =D10/D7-1 -> 0.046490428
A13: DETALLE DE PRECIOS (una línea por precio distinto anotado en el Excel del mes)
A14: MES | B14: PRECIO | C14: CANTIDAD | D14: PRODUCTO (tal cual en el Excel) | E14: ARCHIVO ORIGEN
A15: ENERO | B15: 10.97 | C15: 14 | D15: PICOS ARTESANOS 500 GR | E15: ALBARANES MAYO 2026
A16: FEBRERO | B16: 10.97 | C16: 14 | D16: PICOS ARTESANOS 500 GR | E16: ALBARANES MAYO 2026
A17: ABRIL | B17: 11.48 | C17: 17 | D17: PICOS ARTESANOS 500 GR | E17: ALBARANES MAYO 2026
A18: MAYO | B18: 11.48 | C18: 16 | D18: PICOS ARTESANOS 500 GR | E18: ALBARANES MAYO 2026

Sheet ANCHOAS CANTABRICO GRAN RESE
A1: ANCHOAS CANTABRICO GRAN RESERVA | I1: ← Volver al resumen
A2: Proveedor: CONSERVAS Y SALAZONES JIMENEZ · Categoría: ENVASADO / BEBIDA / OTROS
A3: Nombres en albaranes: ANCHOAS DEL CANTABRICO GRAN RESERVA | ANCHOAS DEL CANTABRICO GRAN RESERVA HL-270 REZUMAR
A4: Producto envasado / tarifa: cualquier subida de precio unitario entre el primer y el último mes con compras se considera SUBIDA.
A6: MES | B6: Nº PRECIOS | C6: PRECIO MÍN. | D6: PRECIO MEDIO | E6: PRECIO MÁX. | F6: VAR. vs MES ANTERIOR | G6: VAR. vs PRIMER MES
A7: ENERO | B7: =COUNTIF($A$17:$A$22,A7) -> 1 | C7: =_xlfn.MINIFS($B$17:$B$22,$A$17:$A$22,A7) -> 27.46 | D7: =AVERAGEIF($A$17:$A$22,A7,$B$17:$B$22) -> 27.46 | E7: =_xlfn.MAXIFS($B$17:$B$22,$A$17:$A$22,A7) -> 27.46
A8: FEBRERO | B8: =COUNTIF($A$17:$A$22,A8) -> 1 | C8: =_xlfn.MINIFS($B$17:$B$22,$A$17:$A$22,A8) -> 27.46 | D8: =AVERAGEIF($A$17:$A$22,A8,$B$17:$B$22) -> 27.46 | E8: =_xlfn.MAXIFS($B$17:$B$22,$A$17:$A$22,A8) -> 27.46 | F8: =D8/D7-1 -> 0 | G8: =D8/$D$7-1 -> 0
A9: ABRIL | B9: =COUNTIF($A$17:$A$22,A9) -> 1 | C9: =_xlfn.MINIFS($B$17:$B$22,$A$17:$A$22,A9) -> 28.66 | D9: =AVERAGEIF($A$17:$A$22,A9,$B$17:$B$22) -> 28.66 | E9: =_xlfn.MAXIFS($B$17:$B$22,$A$17:$A$22,A9) -> 28.66 | F9: =D9/D8-1 -> 0.043699927 | G9: =D9/$D$7-1 -> 0.043699927
A10: MAYO | B10: =COUNTIF($A$17:$A$22,A10) -> 1 | C10: =_xlfn.MINIFS($B$17:$B$22,$A$17:$A$22,A10) -> 28.66 | D10: =AVERAGEIF($A$17:$A$22,A10,$B$17:$B$22) -> 28.66 | E10: =_xlfn.MAXIFS($B$17:$B$22,$A$17:$A$22,A10) -> 28.66 | F10: =D10/D9-1 -> 0 | G10: =D10/$D$7-1 -> 0.043699927
A11: JULIO | B11: =COUNTIF($A$17:$A$22,A11) -> 1 | C11: =_xlfn.MINIFS($B$17:$B$22,$A$17:$A$22,A11) -> 28.66 | D11: =AVERAGEIF($A$17:$A$22,A11,$B$17:$B$22) -> 28.66 | E11: =_xlfn.MAXIFS($B$17:$B$22,$A$17:$A$22,A11) -> 28.66 | F11: =D11/D10-1 -> 0 | G11: =D11/$D$7-1 -> 0.043699927
A12: AGOSTO | B12: =COUNTIF($A$17:$A$22,A12) -> 1 | C12: =_xlfn.MINIFS($B$17:$B$22,$A$17:$A$22,A12) -> 28.66 | D12: =AVERAGEIF($A$17:$A$22,A12,$B$17:$B$22) -> 28.66 | E12: =_xlfn.MAXIFS($B$17:$B$22,$A$17:$A$22,A12) -> 28.66 | F12: =D12/D11-1 -> 0 | G12: =D12/$D$7-1 -> 0.043699927
F13: SUBIDA TOTAL | G13: =D12/D7-1 -> 0.043699927
A15: DETALLE DE PRECIOS (una línea por precio distinto anotado en el Excel del mes)
A16: MES | B16: PRECIO | C16: CANTIDAD | D16: PRODUCTO (tal cual en el Excel) | E16: ARCHIVO ORIGEN
A17: ENERO | B17: 27.46 | C17: 80 | D17: ANCHOAS DEL CANTABRICO GRAN RESERVA HL-270 REZUMAR | E17: ALBARANES MAYO 2026
A18: FEBRERO | B18: 27.46 | C18: 48 | D18: ANCHOAS DEL CANTABRICO GRAN RESERVA HL-270 REZUMAR | E18: ALBARANES MAYO 2026
A19: ABRIL | B19: 28.66 | C19: 64 | D19: ANCHOAS DEL CANTABRICO GRAN RESERVA HL-270 REZUMAR | E19: ALBARANES MAYO 2026
A20: MAYO | B20: 28.66 | C20: 48 | D20: ANCHOAS DEL CANTABRICO GRAN RESERVA HL-270 REZUMAR | E20: ALBARANES MAYO 2026
A21: JULIO | B21: 28.66 | D21: ANCHOAS DEL CANTABRICO GRAN RESERVA | E21: ALBARANES JULIO 2026 v3
A22: AGOSTO | B22: 28.66 | C22: 16 | D22: ANCHOAS DEL CANTABRICO GRAN RESERVA | E22: ALBARANES AGOSTO 2026 v1

Sheet PEPE YLLERA 3 4
A1: PEPE YLLERA 3/4 | I1: ← Volver al resumen
A2: Proveedor: DITEMA (DIST. TENA) · Categoría: ENVASADO / BEBIDA / OTROS
A3: Nombres en albaranes: PEPE YLLERA 3/4
A4: Producto envasado / tarifa: cualquier subida de precio unitario entre el primer y el último mes con compras se considera SUBIDA.
A6: MES | B6: Nº PRECIOS | C6: PRECIO MÍN. | D6: PRECIO MEDIO | E6: PRECIO MÁX. | F6: VAR. vs MES ANTERIOR | G6: VAR. vs PRIMER MES
A7: ENERO | B7: =COUNTIF($A$14:$A$16,A7) -> 1 | C7: =_xlfn.MINIFS($B$14:$B$16,$A$14:$A$16,A7) -> 7.15 | D7: =AVERAGEIF($A$14:$A$16,A7,$B$14:$B$16) -> 7.15 | E7: =_xlfn.MAXIFS($B$14:$B$16,$A$14:$A$16,A7) -> 7.15
A8: FEBRERO | B8: =COUNTIF($A$14:$A$16,A8) -> 1 | C8: =_xlfn.MINIFS($B$14:$B$16,$A$14:$A$16,A8) -> 7.46 | D8: =AVERAGEIF($A$14:$A$16,A8,$B$14:$B$16) -> 7.46 | E8: =_xlfn.MAXIFS($B$14:$B$16,$A$14:$A$16,A8) -> 7.46 | F8: =D8/D7-1 -> 0.043356643 | G8: =D8/$D$7-1 -> 0.043356643
A9: MAYO | B9: =COUNTIF($A$14:$A$16,A9) -> 1 | C9: =_xlfn.MINIFS($B$14:$B$16,$A$14:$A$16,A9) -> 7.46 | D9: =AVERAGEIF($A$14:$A$16,A9,$B$14:$B$16) -> 7.46 | E9: =_xlfn.MAXIFS($B$14:$B$16,$A$14:$A$16,A9) -> 7.46 | F9: =D9/D8-1 -> 0 | G9: =D9/$D$7-1 -> 0.043356643
F10: SUBIDA TOTAL | G10: =D9/D7-1 -> 0.043356643
A12: DETALLE DE PRECIOS (una línea por precio distinto anotado en el Excel del mes)
A13: MES | B13: PRECIO | C13: CANTIDAD | D13: PRODUCTO (tal cual en el Excel) | E13: ARCHIVO ORIGEN
A14: ENERO | B14: 7.15 | C14: 36 | D14: PEPE YLLERA 3/4 | E14: ALBARANES MAYO 2026
A15: FEBRERO | B15: 7.46 | C15: 132 | D15: PEPE YLLERA 3/4 | E15: ALBARANES MAYO 2026
A16: MAYO | B16: 7.46 | C16: 0 | D16: PEPE YLLERA 3/4 | E16: ALBARANES MAYO 2026

Sheet SCHWEPPES TONICA 28 UDS
A1: SCHWEPPES TONICA 28 UDS | I1: ← Volver al resumen
A2: Proveedor: EIF DISTRIBUCIONES · Categoría: ENVASADO / BEBIDA / OTROS
A3: Nombres en albaranes: SCHWEPPES TONICA RET 28 UDS | SCHWEPPES TONICA RET. 28 UDS
A4: Producto envasado / tarifa: cualquier subida de precio unitario entre el primer y el último mes con compras se considera SUBIDA.
A6: MES | B6: Nº PRECIOS | C6: PRECIO MÍN. | D6: PRECIO MEDIO | E6: PRECIO MÁX. | F6: VAR. vs MES ANTERIOR | G6: VAR. vs PRIMER MES
A7: ENERO | B7: =COUNTIF($A$13:$A$15,A7) -> 2 | C7: =_xlfn.MINIFS($B$13:$B$15,$A$13:$A$15,A7) -> 23.84 | D7: =AVERAGEIF($A$13:$A$15,A7,$B$13:$B$15) -> 23.84 | E7: =_xlfn.MAXIFS($B$13:$B$15,$A$13:$A$15,A7) -> 23.84
A8: AGOSTO | B8: =COUNTIF($A$13:$A$15,A8) -> 1 | C8: =_xlfn.MINIFS($B$13:$B$15,$A$13:$A$15,A8) -> 24.84 | D8: =AVERAGEIF($A$13:$A$15,A8,$B$13:$B$15) -> 24.84 | E8: =_xlfn.MAXIFS($B$13:$B$15,$A$13:$A$15,A8) -> 24.84 | F8: =D8/D7-1 -> 0.041946309 | G8: =D8/$D$7-1 -> 0.041946309
F9: SUBIDA TOTAL | G9: =D8/D7-1 -> 0.041946309
A11: DETALLE DE PRECIOS (una línea por precio distinto anotado en el Excel del mes)
A12: MES | B12: PRECIO | C12: CANTIDAD | D12: PRODUCTO (tal cual en el Excel) | E12: ARCHIVO ORIGEN
A13: ENERO | B13: 23.84 | C13: 3 | D13: SCHWEPPES TONICA RET. 28 UDS | E13: ALBARANES MAYO 2026
A14: ENERO | B14: 23.84 | C14: 5 | D14: SCHWEPPES TONICA RET. 28 UDS | E14: ALBARANES MAYO 2026
A15: AGOSTO | B15: 24.84 | C15: 5 | D15: SCHWEPPES TONICA RET 28 UDS | E15: ALBARANES AGOSTO 2026 v1

Sheet CASERA LIMON 1L
A1: CASERA LIMON 1L | I1: ← Volver al resumen
A2: Proveedor: VOLDIS · Categoría: ENVASADO / BEBIDA / OTROS
A3: Nombres en albaranes: LA CASERA LIMON PET 1L CAJA 12U
A4: Producto envasado / tarifa: cualquier subida de precio unitario entre el primer y el último mes con compras se considera SUBIDA.
A6: MES | B6: Nº PRECIOS | C6: PRECIO MÍN. | D6: PRECIO MEDIO | E6: PRECIO MÁX. | F6: VAR. vs MES ANTERIOR | G6: VAR. vs PRIMER MES
A7: ENERO | B7: =COUNTIF($A$15:$A$18,A7) -> 1 | C7: =_xlfn.MINIFS($B$15:$B$18,$A$15:$A$18,A7) -> 23.64 | D7: =AVERAGEIF($A$15:$A$18,A7,$B$15:$B$18) -> 23.64 | E7: =_xlfn.MAXIFS($B$15:$B$18,$A$15:$A$18,A7) -> 23.64
A8: FEBRERO | B8: =COUNTIF($A$15:$A$18,A8) -> 1 | C8: =_xlfn.MINIFS($B$15:$B$18,$A$15:$A$18,A8) -> 24.61 | D8: =AVERAGEIF($A$15:$A$18,A8,$B$15:$B$18) -> 24.61 | E8: =_xlfn.MAXIFS($B$15:$B$18,$A$15:$A$18,A8) -> 24.61 | F8: =D8/D7-1 -> 0.041032149 | G8: =D8/$D$7-1 -> 0.041032149
A9: MAYO | B9: =COUNTIF($A$15:$A$18,A9) -> 1 | C9: =_xlfn.MINIFS($B$15:$B$18,$A$15:$A$18,A9) -> 24.61 | D9: =AVERAGEIF($A$15:$A$18,A9,$B$15:$B$18) -> 24.61 | E9: =_xlfn.MAXIFS($B$15:$B$18,$A$15:$A$18,A9) -> 24.61 | F9: =D9/D8-1 -> 0 | G9: =D9/$D$7-1 -> 0.041032149
A10: JULIO | B10: =COUNTIF($A$15:$A$18,A10) -> 1 | C10: =_xlfn.MINIFS($B$15:$B$18,$A$15:$A$18,A10) -> 24.61 | D10: =AVERAGEIF($A$15:$A$18,A10,$B$15:$B$18) -> 24.61 | E10: =_xlfn.MAXIFS($B$15:$B$18,$A$15:$A$18,A10) -> 24.61 | F10: =D10/D9-1 -> 0 | G10: =D10/$D$7-1 -> 0.041032149
F11: SUBIDA TOTAL | G11: =D10/D7-1 -> 0.041032149
A13: DETALLE DE PRECIOS (una línea por precio distinto anotado en el Excel del mes)
A14: MES | B14: PRECIO | C14: CANTIDAD | D14: PRODUCTO (tal cual en el Excel) | E14: ARCHIVO ORIGEN
A15: ENERO | B15: 23.64 | C15: 8 | D15: LA CASERA LIMON PET 1L CAJA 12U | E15: ALBARANES MAYO 2026
A16: FEBRERO | B16: 24.61 | C16: 7 | D16: LA CASERA LIMON PET 1L CAJA 12U | E16: ALBARANES MAYO 2026
A17: MAYO | B17: 24.61 | C17: 19 | D17: LA CASERA LIMON PET 1L CAJA 12U | E17: ALBARANES MAYO 2026
A18: JULIO | B18: 24.61 | C18: 17 | D18: LA CASERA LIMON PET 1L CAJA 12U | E18: ALBARANES JULIO 2026 v3

Sheet CASERA GASEOSA 1L
A1: CASERA GASEOSA 1L | I1: ← Volver al resumen
A2: Proveedor: VOLDIS · Categoría: ENVASADO / BEBIDA / OTROS
A3: Nombres en albaranes: LA CASERA GASEOSA PET 1L CAJA 12U
A4: Producto envasado / tarifa: cualquier subida de precio unitario entre el primer y el último mes con compras se considera SUBIDA.
A6: MES | B6: Nº PRECIOS | C6: PRECIO MÍN. | D6: PRECIO MEDIO | E6: PRECIO MÁX. | F6: VAR. vs MES ANTERIOR | G6: VAR. vs PRIMER MES
A7: ENERO | B7: =COUNTIF($A$15:$A$18,A7) -> 1 | C7: =_xlfn.MINIFS($B$15:$B$18,$A$15:$A$18,A7) -> 20.64 | D7: =AVERAGEIF($A$15:$A$18,A7,$B$15:$B$18) -> 20.64 | E7: =_xlfn.MAXIFS($B$15:$B$18,$A$15:$A$18,A7) -> 20.64
A8: FEBRERO | B8: =COUNTIF($A$15:$A$18,A8) -> 1 | C8: =_xlfn.MINIFS($B$15:$B$18,$A$15:$A$18,A8) -> 21.48 | D8: =AVERAGEIF($A$15:$A$18,A8,$B$15:$B$18) -> 21.48 | E8: =_xlfn.MAXIFS($B$15:$B$18,$A$15:$A$18,A8) -> 21.48 | F8: =D8/D7-1 -> 0.040697674 | G8: =D8/$D$7-1 -> 0.040697674
A9: MAYO | B9: =COUNTIF($A$15:$A$18,A9) -> 1 | C9: =_xlfn.MINIFS($B$15:$B$18,$A$15:$A$18,A9) -> 21.48 | D9: =AVERAGEIF($A$15:$A$18,A9,$B$15:$B$18) -> 21.48 | E9: =_xlfn.MAXIFS($B$15:$B$18,$A$15:$A$18,A9) -> 21.48 | F9: =D9/D8-1 -> 0 | G9: =D9/$D$7-1 -> 0.040697674
A10: JULIO | B10: =COUNTIF($A$15:$A$18,A10) -> 1 | C10: =_xlfn.MINIFS($B$15:$B$18,$A$15:$A$18,A10) -> 21.48 | D10: =AVERAGEIF($A$15:$A$18,A10,$B$15:$B$18) -> 21.48 | E10: =_xlfn.MAXIFS($B$15:$B$18,$A$15:$A$18,A10) -> 21.48 | F10: =D10/D9-1 -> 0 | G10: =D10/$D$7-1 -> 0.040697674
F11: SUBIDA TOTAL | G11: =D10/D7-1 -> 0.040697674
A13: DETALLE DE PRECIOS (una línea por precio distinto anotado en el Excel del mes)
A14: MES | B14: PRECIO | C14: CANTIDAD | D14: PRODUCTO (tal cual en el Excel) | E14: ARCHIVO ORIGEN
A15: ENERO | B15: 20.64 | C15: 3 | D15: LA CASERA GASEOSA PET 1L CAJA 12U | E15: ALBARANES MAYO 2026
A16: FEBRERO | B16: 21.48 | C16: 1 | D16: LA CASERA GASEOSA PET 1L CAJA 12U | E16: ALBARANES MAYO 2026
A17: MAYO | B17: 21.48 | C17: 6 | D17: LA CASERA GASEOSA PET 1L CAJA 12U | E17: ALBARANES MAYO 2026
A18: JULIO | B18: 21.48 | C18: 3 | D18: LA CASERA GASEOSA PET 1L CAJA 12U | E18: ALBARANES JULIO 2026 v3

Sheet PAN MOLDE BRIOCHE
A1: PAN MOLDE BRIOCHE | I1: ← Volver al resumen
A2: Proveedor: DELIPAN · Categoría: ENVASADO / BEBIDA / OTROS
A3: Nombres en albaranes: PAN MOLDE BRIOCHE (7 UD) | PAN MOLDE BRIOCHE (7UD)
A4: Producto envasado / tarifa: cualquier subida de precio unitario entre el primer y el último mes con compras se considera SUBIDA.
A6: MES | B6: Nº PRECIOS | C6: PRECIO MÍN. | D6: PRECIO MEDIO | E6: PRECIO MÁX. | F6: VAR. vs MES ANTERIOR | G6: VAR. vs PRIMER MES
A7: ENERO | B7: =COUNTIF($A$17:$A$22,A7) -> 1 | C7: =_xlfn.MINIFS($B$17:$B$22,$A$17:$A$22,A7) -> 84.7 | D7: =AVERAGEIF($A$17:$A$22,A7,$B$17:$B$22) -> 84.7 | E7: =_xlfn.MAXIFS($B$17:$B$22,$A$17:$A$22,A7) -> 84.7
A8: FEBRERO | B8: =COUNTIF($A$17:$A$22,A8) -> 1 | C8: =_xlfn.MINIFS($B$17:$B$22,$A$17:$A$22,A8) -> 84.7 | D8: =AVERAGEIF($A$17:$A$22,A8,$B$17:$B$22) -> 84.7 | E8: =_xlfn.MAXIFS($B$17:$B$22,$A$17:$A$22,A8) -> 84.7 | F8: =D8/D7-1 -> 0 | G8: =D8/$D$7-1 -> 0
A9: ABRIL | B9: =COUNTIF($A$17:$A$22,A9) -> 1 | C9: =_xlfn.MINIFS($B$17:$B$22,$A$17:$A$22,A9) -> 88.09 | D9: =AVERAGEIF($A$17:$A$22,A9,$B$17:$B$22) -> 88.09 | E9: =_xlfn.MAXIFS($B$17:$B$22,$A$17:$A$22,A9) -> 88.09 | F9: =D9/D8-1 -> 0.040023613 | G9: =D9/$D$7-1 -> 0.040023613
A10: MAYO | B10: =COUNTIF($A$17:$A$22,A10) -> 1 | C10: =_xlfn.MINIFS($B$17:$B$22,$A$17:$A$22,A10) -> 88.09 | D10: =AVERAGEIF($A$17:$A$22,A10,$B$17:$B$22) -> 88.09 | E10: =_xlfn.MAXIFS($B$17:$B$22,$A$17:$A$22,A10) -> 88.09 | F10: =D10/D9-1 -> 0 | G10: =D10/$D$7-1 -> 0.040023613
A11: JULIO | B11: =COUNTIF($A$17:$A$22,A11) -> 1 | C11: =_xlfn.MINIFS($B$17:$B$22,$A$17:$A$22,A11) -> 88.09 | D11: =AVERAGEIF($A$17:$A$22,A11,$B$17:$B$22) -> 88.09 | E11: =_xlfn.MAXIFS($B$17:$B$22,$A$17:$A$22,A11) -> 88.09 | F11: =D11/D10-1 -> 0 | G11: =D11/$D$7-1 -> 0.040023613
A12: AGOSTO | B12: =COUNTIF($A$17:$A$22,A12) -> 1 | C12: =_xlfn.MINIFS($B$17:$B$22,$A$17:$A$22,A12) -> 88.09 | D12: =AVERAGEIF($A$17:$A$22,A12,$B$17:$B$22) -> 88.09 | E12: =_xlfn.MAXIFS($B$17:$B$22,$A$17:$A$22,A12) -> 88.09 | F12: =D12/D11-1 -> 0 | G12: =D12/$D$7-1 -> 0.040023613
F13: SUBIDA TOTAL | G13: =D12/D7-1 -> 0.040023613
A15: DETALLE DE PRECIOS (una línea por precio distinto anotado en el Excel del mes)
A16: MES | B16: PRECIO | C16: CANTIDAD | D16: PRODUCTO (tal cual en el Excel) | E16: ARCHIVO ORIGEN
A17: ENERO | B17: 84.7 | C17: 4 | D17: PAN MOLDE BRIOCHE (7UD) | E17: ALBARANES MAYO 2026
A18: FEBRERO | B18: 84.7 | C18: 5 | D18: PAN MOLDE BRIOCHE (7UD) | E18: ALBARANES MAYO 2026
A19: ABRIL | B19: 88.09 | C19: 6 | D19: PAN MOLDE BRIOCHE (7UD) | E19: ALBARANES MAYO 2026
A20: MAYO | B20: 88.09 | C20: 4 | D20: PAN MOLDE BRIOCHE (7UD) | E20: ALBARANES MAYO 2026
A21: JULIO | B21: 88.09 | D21: PAN MOLDE BRIOCHE (7 UD) | E21: ALBARANES JULIO 2026 v3
A22: AGOSTO | B22: 88.09 | C22: 1 | D22: PAN MOLDE BRIOCHE (7 UD) | E22: ALBARANES AGOSTO 2026 v1

Sheet PACO GARCIA CRIANZA 3 4
A1: PACO GARCIA CRIANZA 3/4 | I1: ← Volver al resumen
A2: Proveedor: MUNDELA · Categoría: ENVASADO / BEBIDA / OTROS
A3: Nombres en albaranes: PACO GARCIA CRIANZA 3/4
A4: Producto envasado / tarifa: cualquier subida de precio unitario entre el primer y el último mes con compras se considera SUBIDA.
A6: MES | B6: Nº PRECIOS | C6: PRECIO MÍN. | D6: PRECIO MEDIO | E6: PRECIO MÁX. | F6: VAR. vs MES ANTERIOR | G6: VAR. vs PRIMER MES
A7: ENERO | B7: =COUNTIF($A$15:$A$18,A7) -> 1 | C7: =_xlfn.MINIFS($B$15:$B$18,$A$15:$A$18,A7) -> 5.1 | D7: =AVERAGEIF($A$15:$A$18,A7,$B$15:$B$18) -> 5.1 | E7: =_xlfn.MAXIFS($B$15:$B$18,$A$15:$A$18,A7) -> 5.1
A8: FEBRERO | B8: =COUNTIF($A$15:$A$18,A8) -> 1 | C8: =_xlfn.MINIFS($B$15:$B$18,$A$15:$A$18,A8) -> 5.1 | D8: =AVERAGEIF($A$15:$A$18,A8,$B$15:$B$18) -> 5.1 | E8: =_xlfn.MAXIFS($B$15:$B$18,$A$15:$A$18,A8) -> 5.1 | F8: =D8/D7-1 -> 0 | G8: =D8/$D$7-1 -> 0
A9: MAYO | B9: =COUNTIF($A$15:$A$18,A9) -> 1 | C9: =_xlfn.MINIFS($B$15:$B$18,$A$15:$A$18,A9) -> 5.3 | D9: =AVERAGEIF($A$15:$A$18,A9,$B$15:$B$18) -> 5.3 | E9: =_xlfn.MAXIFS($B$15:$B$18,$A$15:$A$18,A9) -> 5.3 | F9: =D9/D8-1 -> 0.039215686 | G9: =D9/$D$7-1 -> 0.039215686
A10: AGOSTO | B10: =COUNTIF($A$15:$A$18,A10) -> 1 | C10: =_xlfn.MINIFS($B$15:$B$18,$A$15:$A$18,A10) -> 5.3 | D10: =AVERAGEIF($A$15:$A$18,A10,$B$15:$B$18) -> 5.3 | E10: =_xlfn.MAXIFS($B$15:$B$18,$A$15:$A$18,A10) -> 5.3 | F10: =D10/D9-1 -> 0 | G10: =D10/$D$7-1 -> 0.039215686
F11: SUBIDA TOTAL | G11: =D10/D7-1 -> 0.039215686
A13: DETALLE DE PRECIOS (una línea por precio distinto anotado en el Excel del mes)
A14: MES | B14: PRECIO | C14: CANTIDAD | D14: PRODUCTO (tal cual en el Excel) | E14: ARCHIVO ORIGEN
A15: ENERO | B15: 5.1 | C15: 72 | D15: PACO GARCIA CRIANZA 3/4 | E15: ALBARANES MAYO 2026
A16: FEBRERO | B16: 5.1 | C16: 84 | D16: PACO GARCIA CRIANZA 3/4 | E16: ALBARANES MAYO 2026
A17: MAYO | B17: 5.3 | C17: 60 | D17: PACO GARCIA CRIANZA 3/4 | E17: ALBARANES MAYO 2026
A18: AGOSTO | B18: 5.3 | D18: PACO GARCIA CRIANZA 3/4 | E18: ALBARANES AGOSTO 2026 v1

Sheet RAMON BILBAO BLANCO VERDEJO
A1: RAMON BILBAO BLANCO VERDEJO 3/4 | I1: ← Volver al resumen
A2: Proveedor: MUNDELA · Categoría: ENVASADO / BEBIDA / OTROS
A3: Nombres en albaranes: RAMON BILBAO BLANCO VERDEJO 3/4 | RAMÓN BILBAO BLANCO VERDEJO 3/4
A4: Producto envasado / tarifa: cualquier subida de precio unitario entre el primer y el último mes con compras se considera SUBIDA.
A6: MES | B6: Nº PRECIOS | C6: PRECIO MÍN. | D6: PRECIO MEDIO | E6: PRECIO MÁX. | F6: VAR. vs MES ANTERIOR | G6: VAR. vs PRIMER MES
A7: ENERO | B7: =COUNTIF($A$16:$A$20,A7) -> 1 | C7: =_xlfn.MINIFS($B$16:$B$20,$A$16:$A$20,A7) -> 4.5 | D7: =AVERAGEIF($A$16:$A$20,A7,$B$16:$B$20) -> 4.5 | E7: =_xlfn.MAXIFS($B$16:$B$20,$A$16:$A$20,A7) -> 4.5
A8: FEBRERO | B8: =COUNTIF($A$16:$A$20,A8) -> 1 | C8: =_xlfn.MINIFS($B$16:$B$20,$A$16:$A$20,A8) -> 4.5 | D8: =AVERAGEIF($A$16:$A$20,A8,$B$16:$B$20) -> 4.5 | E8: =_xlfn.MAXIFS($B$16:$B$20,$A$16:$A$20,A8) -> 4.5 | F8: =D8/D7-1 -> 0 | G8: =D8/$D$7-1 -> 0
A9: MAYO | B9: =COUNTIF($A$16:$A$20,A9) -> 1 | C9: =_xlfn.MINIFS($B$16:$B$20,$A$16:$A$20,A9) -> 4.67 | D9: =AVERAGEIF($A$16:$A$20,A9,$B$16:$B$20) -> 4.67 | E9: =_xlfn.MAXIFS($B$16:$B$20,$A$16:$A$20,A9) -> 4.67 | F9: =D9/D8-1 -> 0.037777778 | G9: =D9/$D$7-1 -> 0.037777778
A10: JULIO | B10: =COUNTIF($A$16:$A$20,A10) -> 1 | C10: =_xlfn.MINIFS($B$16:$B$20,$A$16:$A$20,A10) -> 4.67 | D10: =AVERAGEIF($A$16:$A$20,A10,$B$16:$B$20) -> 4.67 | E10: =_xlfn.MAXIFS($B$16:$B$20,$A$16:$A$20,A10) -> 4.67 | F10: =D10/D9-1 -> 0 | G10: =D10/$D$7-1 -> 0.037777778
A11: AGOSTO | B11: =COUNTIF($A$16:$A$20,A11) -> 1 | C11: =_xlfn.MINIFS($B$16:$B$20,$A$16:$A$20,A11) -> 4.67 | D11: =AVERAGEIF($A$16:$A$20,A11,$B$16:$B$20) -> 4.67 | E11: =_xlfn.MAXIFS($B$16:$B$20,$A$16:$A$20,A11) -> 4.67 | F11: =D11/D10-1 -> 0 | G11: =D11/$D$7-1 -> 0.037777778
F12: SUBIDA TOTAL | G12: =D11/D7-1 -> 0.037777778
A14: DETALLE DE PRECIOS (una línea por precio distinto anotado en el Excel del mes)
A15: MES | B15: PRECIO | C15: CANTIDAD | D15: PRODUCTO (tal cual en el Excel) | E15: ARCHIVO ORIGEN
A16: ENERO | B16: 4.5 | C16: 84 | D16: RAMÓN BILBAO BLANCO VERDEJO 3/4 | E16: ALBARANES MAYO 2026
A17: FEBRERO | B17: 4.5 | C17: 12 | D17: RAMÓN BILBAO BLANCO VERDEJO 3/4 | E17: ALBARANES MAYO 2026
A18: MAYO | B18: 4.67 | C18: 96 | D18: RAMÓN BILBAO BLANCO VERDEJO 3/4 | E18: ALBARANES MAYO 2026
A19: JULIO | B19: 4.67 | D19: RAMON BILBAO BLANCO VERDEJO 3/4 | E19: ALBARANES JULIO 2026 v3
A20: AGOSTO | B20: 4.67 | D20: RAMON BILBAO BLANCO VERDEJO 3/4 | E20: ALBARANES AGOSTO 2026 v1

Sheet GODELLO VINAREDO
A1: GODELLO VINAREDO | I1: ← Volver al resumen
A2: Proveedor: DITEMA (DIST. TENA) · Categoría: ENVASADO / BEBIDA / OTROS
A3: Nombres en albaranes: GODELLO VIÑAREDO
A4: Producto envasado / tarifa: cualquier subida de precio unitario entre el primer y el último mes con compras se considera SUBIDA.
A6: MES | B6: Nº PRECIOS | C6: PRECIO MÍN. | D6: PRECIO MEDIO | E6: PRECIO MÁX. | F6: VAR. vs MES ANTERIOR | G6: VAR. vs PRIMER MES
A7: ENERO | B7: =COUNTIF($A$16:$A$20,A7) -> 1 | C7: =_xlfn.MINIFS($B$16:$B$20,$A$16:$A$20,A7) -> 6.78 | D7: =AVERAGEIF($A$16:$A$20,A7,$B$16:$B$20) -> 6.78 | E7: =_xlfn.MAXIFS($B$16:$B$20,$A$16:$A$20,A7) -> 6.78
A8: FEBRERO | B8: =COUNTIF($A$16:$A$20,A8) -> 1 | C8: =_xlfn.MINIFS($B$16:$B$20,$A$16:$A$20,A8) -> 6.78 | D8: =AVERAGEIF($A$16:$A$20,A8,$B$16:$B$20) -> 6.78 | E8: =_xlfn.MAXIFS($B$16:$B$20,$A$16:$A$20,A8) -> 6.78 | F8: =D8/D7-1 -> 0 | G8: =D8/$D$7-1 -> 0
A9: MAYO | B9: =COUNTIF($A$16:$A$20,A9) -> 1 | C9: =_xlfn.MINIFS($B$16:$B$20,$A$16:$A$20,A9) -> 7.03 | D9: =AVERAGEIF($A$16:$A$20,A9,$B$16:$B$20) -> 7.03 | E9: =_xlfn.MAXIFS($B$16:$B$20,$A$16:$A$20,A9) -> 7.03 | F9: =D9/D8-1 -> 0.036873156 | G9: =D9/$D$7-1 -> 0.036873156
A10: JULIO | B10: =COUNTIF($A$16:$A$20,A10) -> 1 | C10: =_xlfn.MINIFS($B$16:$B$20,$A$16:$A$20,A10) -> 7.03 | D10: =AVERAGEIF($A$16:$A$20,A10,$B$16:$B$20) -> 7.03 | E10: =_xlfn.MAXIFS($B$16:$B$20,$A$16:$A$20,A10) -> 7.03 | F10: =D10/D9-1 -> 0 | G10: =D10/$D$7-1 -> 0.036873156
A11: AGOSTO | B11: =COUNTIF($A$16:$A$20,A11) -> 1 | C11: =_xlfn.MINIFS($B$16:$B$20,$A$16:$A$20,A11) -> 7.03 | D11: =AVERAGEIF($A$16:$A$20,A11,$B$16:$B$20) -> 7.03 | E11: =_xlfn.MAXIFS($B$16:$B$20,$A$16:$A$20,A11) -> 7.03 | F11: =D11/D10-1 -> 0 | G11: =D11/$D$7-1 -> 0.036873156
F12: SUBIDA TOTAL | G12: =D11/D7-1 -> 0.036873156
A14: DETALLE DE PRECIOS (una línea por precio distinto anotado en el Excel del mes)
A15: MES | B15: PRECIO | C15: CANTIDAD | D15: PRODUCTO (tal cual en el Excel) | E15: ARCHIVO ORIGEN
A16: ENERO | B16: 6.78 | C16: 30 | D16: GODELLO VIÑAREDO | E16: ALBARANES MAYO 2026
A17: FEBRERO | B17: 6.78 | C17: 48 | D17: GODELLO VIÑAREDO | E17: ALBARANES MAYO 2026
A18: MAYO | B18: 7.03 | C18: 108 | D18: GODELLO VIÑAREDO | E18: ALBARANES MAYO 2026
A19: JULIO | B19: 7.03 | D19: GODELLO VIÑAREDO | E19: ALBARANES JULIO 2026 v3
A20: AGOSTO | B20: 7.03 | D20: GODELLO VIÑAREDO | E20: ALBARANES AGOSTO 2026 v1

Sheet SENORIO FITERO ROBLE
A1: SENORIO FITERO ROBLE | I1: ← Volver al resumen
A2: Proveedor: DITEMA (DIST. TENA) · Categoría: ENVASADO / BEBIDA / OTROS
A3: Nombres en albaranes: SEÑORIO DE FITERO ROBLE
A4: Producto envasado / tarifa: cualquier subida de precio unitario entre el primer y el último mes con compras se considera SUBIDA.
A6: MES | B6: Nº PRECIOS | C6: PRECIO MÍN. | D6: PRECIO MEDIO | E6: PRECIO MÁX. | F6: VAR. vs MES ANTERIOR | G6: VAR. vs PRIMER MES
A7: ENERO | B7: =COUNTIF($A$16:$A$20,A7) -> 1 | C7: =_xlfn.MINIFS($B$16:$B$20,$A$16:$A$20,A7) -> 2.72 | D7: =AVERAGEIF($A$16:$A$20,A7,$B$16:$B$20) -> 2.72 | E7: =_xlfn.MAXIFS($B$16:$B$20,$A$16:$A$20,A7) -> 2.72
A8: FEBRERO | B8: =COUNTIF($A$16:$A$20,A8) -> 1 | C8: =_xlfn.MINIFS($B$16:$B$20,$A$16:$A$20,A8) -> 2.72 | D8: =AVERAGEIF($A$16:$A$20,A8,$B$16:$B$20) -> 2.72 | E8: =_xlfn.MAXIFS($B$16:$B$20,$A$16:$A$20,A8) -> 2.72 | F8: =D8/D7-1 -> 0 | G8: =D8/$D$7-1 -> 0
A9: MAYO | B9: =COUNTIF($A$16:$A$20,A9) -> 1 | C9: =_xlfn.MINIFS($B$16:$B$20,$A$16:$A$20,A9) -> 2.82 | D9: =AVERAGEIF($A$16:$A$20,A9,$B$16:$B$20) -> 2.82 | E9: =_xlfn.MAXIFS($B$16:$B$20,$A$16:$A$20,A9) -> 2.82 | F9: =D9/D8-1 -> 0.036764706 | G9: =D9/$D$7-1 -> 0.036764706
A10: JULIO | B10: =COUNTIF($A$16:$A$20,A10) -> 1 | C10: =_xlfn.MINIFS($B$16:$B$20,$A$16:$A$20,A10) -> 2.82 | D10: =AVERAGEIF($A$16:$A$20,A10,$B$16:$B$20) -> 2.82 | E10: =_xlfn.MAXIFS($B$16:$B$20,$A$16:$A$20,A10) -> 2.82 | F10: =D10/D9-1 -> 0 | G10: =D10/$D$7-1 -> 0.036764706
A11: AGOSTO | B11: =COUNTIF($A$16:$A$20,A11) -> 1 | C11: =_xlfn.MINIFS($B$16:$B$20,$A$16:$A$20,A11) -> 2.82 | D11: =AVERAGEIF($A$16:$A$20,A11,$B$16:$B$20) -> 2.82 | E11: =_xlfn.MAXIFS($B$16:$B$20,$A$16:$A$20,A11) -> 2.82 | F11: =D11/D10-1 -> 0 | G11: =D11/$D$7-1 -> 0.036764706
F12: SUBIDA TOTAL | G12: =D11/D7-1 -> 0.036764706
A14: DETALLE DE PRECIOS (una línea por precio distinto anotado en el Excel del mes)
A15: MES | B15: PRECIO | C15: CANTIDAD | D15: PRODUCTO (tal cual en el Excel) | E15: ARCHIVO ORIGEN
A16: ENERO | B16: 2.72 | C16: 36 | D16: SEÑORIO DE FITERO ROBLE | E16: ALBARANES MAYO 2026
A17: FEBRERO | B17: 2.72 | C17: 30 | D17: SEÑORIO DE FITERO ROBLE | E17: ALBARANES MAYO 2026
A18: MAYO | B18: 2.82 | C18: 132 | D18: SEÑORIO DE FITERO ROBLE | E18: ALBARANES MAYO 2026
A19: JULIO | B19: 2.82 | D19: SEÑORIO DE FITERO ROBLE | E19: ALBARANES JULIO 2026 v3
A20: AGOSTO | B20: 2.82 | D20: SEÑORIO DE FITERO ROBLE | E20: ALBARANES AGOSTO 2026 v1

Sheet CORIMBO
A1: CORIMBO | I1: ← Volver al resumen
A2: Proveedor: MUNDELA · Categoría: ENVASADO / BEBIDA / OTROS
A3: Nombres en albaranes: CORIMBO
A4: Producto envasado / tarifa: cualquier subida de precio unitario entre el primer y el último mes con compras se considera SUBIDA.
A6: MES | B6: Nº PRECIOS | C6: PRECIO MÍN. | D6: PRECIO MEDIO | E6: PRECIO MÁX. | F6: VAR. vs MES ANTERIOR | G6: VAR. vs PRIMER MES
A7: ENERO | B7: =COUNTIF($A$16:$A$20,A7) -> 1 | C7: =_xlfn.MINIFS($B$16:$B$20,$A$16:$A$20,A7) -> 13.42 | D7: =AVERAGEIF($A$16:$A$20,A7,$B$16:$B$20) -> 13.42 | E7: =_xlfn.MAXIFS($B$16:$B$20,$A$16:$A$20,A7) -> 13.42
A8: FEBRERO | B8: =COUNTIF($A$16:$A$20,A8) -> 1 | C8: =_xlfn.MINIFS($B$16:$B$20,$A$16:$A$20,A8) -> 13.42 | D8: =AVERAGEIF($A$16:$A$20,A8,$B$16:$B$20) -> 13.42 | E8: =_xlfn.MAXIFS($B$16:$B$20,$A$16:$A$20,A8) -> 13.42 | F8: =D8/D7-1 -> 0 | G8: =D8/$D$7-1 -> 0
A9: MAYO | B9: =COUNTIF($A$16:$A$20,A9) -> 1 | C9: =_xlfn.MINIFS($B$16:$B$20,$A$16:$A$20,A9) -> 13.91 | D9: =AVERAGEIF($A$16:$A$20,A9,$B$16:$B$20) -> 13.91 | E9: =_xlfn.MAXIFS($B$16:$B$20,$A$16:$A$20,A9) -> 13.91 | F9: =D9/D8-1 -> 0.036512668 | G9: =D9/$D$7-1 -> 0.036512668
A10: JULIO | B10: =COUNTIF($A$16:$A$20,A10) -> 1 | C10: =_xlfn.MINIFS($B$16:$B$20,$A$16:$A$20,A10) -> 13.91 | D10: =AVERAGEIF($A$16:$A$20,A10,$B$16:$B$20) -> 13.91 | E10: =_xlfn.MAXIFS($B$16:$B$20,$A$16:$A$20,A10) -> 13.91 | F10: =D10/D9-1 -> 0 | G10: =D10/$D$7-1 -> 0.036512668
A11: AGOSTO | B11: =COUNTIF($A$16:$A$20,A11) -> 1 | C11: =_xlfn.MINIFS($B$16:$B$20,$A$16:$A$20,A11) -> 13.91 | D11: =AVERAGEIF($A$16:$A$20,A11,$B$16:$B$20) -> 13.91 | E11: =_xlfn.MAXIFS($B$16:$B$20,$A$16:$A$20,A11) -> 13.91 | F11: =D11/D10-1 -> 0 | G11: =D11/$D$7-1 -> 0.036512668
F12: SUBIDA TOTAL | G12: =D11/D7-1 -> 0.036512668
A14: DETALLE DE PRECIOS (una línea por precio distinto anotado en el Excel del mes)
A15: MES | B15: PRECIO | C15: CANTIDAD | D15: PRODUCTO (tal cual en el Excel) | E15: ARCHIVO ORIGEN
A16: ENERO | B16: 13.42 | C16: 78 | D16: CORIMBO | E16: ALBARANES MAYO 2026
A17: FEBRERO | B17: 13.42 | C17: 78 | D17: CORIMBO | E17: ALBARANES MAYO 2026
A18: MAYO | B18: 13.91 | C18: 66 | D18: CORIMBO | E18: ALBARANES MAYO 2026
A19: JULIO | B19: 13.91 | D19: CORIMBO | E19: ALBARANES JULIO 2026 v3
A20: AGOSTO | B20: 13.91 | D20: CORIMBO | E20: ALBARANES AGOSTO 2026 v1

Sheet SCHWEPPES TONICA VIDRIO 20CL
A1: SCHWEPPES TONICA VIDRIO 20CL | I1: ← Volver al resumen
A2: Proveedor: VOLDIS · Categoría: ENVASADO / BEBIDA / OTROS
A3: Nombres en albaranes: SCHWEPPES TONICA VIDRIO RET 20CL CAJA 28U | SCHWEPPES TONICA VIDRIO RET 20CL CAJA 28UDS
A4: Producto envasado / tarifa: cualquier subida de precio unitario entre el primer y el último mes con compras se considera SUBIDA.
A6: MES | B6: Nº PRECIOS | C6: PRECIO MÍN. | D6: PRECIO MEDIO | E6: PRECIO MÁX. | F6: VAR. vs MES ANTERIOR | G6: VAR. vs PRIMER MES
A7: ENERO | B7: =COUNTIF($A$15:$A$18,A7) -> 1 | C7: =_xlfn.MINIFS($B$15:$B$18,$A$15:$A$18,A7) -> 30.8 | D7: =AVERAGEIF($A$15:$A$18,A7,$B$15:$B$18) -> 30.8 | E7: =_xlfn.MAXIFS($B$15:$B$18,$A$15:$A$18,A7) -> 30.8
A8: FEBRERO | B8: =COUNTIF($A$15:$A$18,A8) -> 1 | C8: =_xlfn.MINIFS($B$15:$B$18,$A$15:$A$18,A8) -> 31.92 | D8: =AVERAGEIF($A$15:$A$18,A8,$B$15:$B$18) -> 31.92 | E8: =_xlfn.MAXIFS($B$15:$B$18,$A$15:$A$18,A8) -> 31.92 | F8: =D8/D7-1 -> 0.036363636 | G8: =D8/$D$7-1 -> 0.036363636
A9: MAYO | B9: =COUNTIF($A$15:$A$18,A9) -> 1 | C9: =_xlfn.MINIFS($B$15:$B$18,$A$15:$A$18,A9) -> 31.92 | D9: =AVERAGEIF($A$15:$A$18,A9,$B$15:$B$18) -> 31.92 | E9: =_xlfn.MAXIFS($B$15:$B$18,$A$15:$A$18,A9) -> 31.92 | F9: =D9/D8-1 -> 0 | G9: =D9/$D$7-1 -> 0.036363636
A10: JULIO | B10: =COUNTIF($A$15:$A$18,A10) -> 1 | C10: =_xlfn.MINIFS($B$15:$B$18,$A$15:$A$18,A10) -> 31.92 | D10: =AVERAGEIF($A$15:$A$18,A10,$B$15:$B$18) -> 31.92 | E10: =_xlfn.MAXIFS($B$15:$B$18,$A$15:$A$18,A10) -> 31.92 | F10: =D10/D9-1 -> 0 | G10: =D10/$D$7-1 -> 0.036363636
F11: SUBIDA TOTAL | G11: =D10/D7-1 -> 0.036363636
A13: DETALLE DE PRECIOS (una línea por precio distinto anotado en el Excel del mes)
A14: MES | B14: PRECIO | C14: CANTIDAD | D14: PRODUCTO (tal cual en el Excel) | E14: ARCHIVO ORIGEN
A15: ENERO | B15: 30.8 | C15: 32 | D15: SCHWEPPES TONICA VIDRIO RET 20CL CAJA 28UDS | E15: ALBARANES MAYO 2026
A16: FEBRERO | B16: 31.92 | C16: 37 | D16: SCHWEPPES TONICA VIDRIO RET 20CL CAJA 28UDS | E16: ALBARANES MAYO 2026
A17: MAYO | B17: 31.92 | C17: 34 | D17: SCHWEPPES TONICA VIDRIO RET 20CL CAJA 28UDS | E17: ALBARANES MAYO 2026
A18: JULIO | B18: 31.92 | C18: 31 | D18: SCHWEPPES TONICA VIDRIO RET 20CL CAJA 28U | E18: ALBARANES JULIO 2026 v3

Sheet RODA RESERVA 3 4
A1: RODA RESERVA 3/4 | I1: ← Volver al resumen
A2: Proveedor: MUNDELA · Categoría: ENVASADO / BEBIDA / OTROS
A3: Nombres en albaranes: RODA RESERVA 3/4
A4: Producto envasado / tarifa: cualquier subida de precio unitario entre el primer y el último mes con compras se considera SUBIDA.
A6: MES | B6: Nº PRECIOS | C6: PRECIO MÍN. | D6: PRECIO MEDIO | E6: PRECIO MÁX. | F6: VAR. vs MES ANTERIOR | G6: VAR. vs PRIMER MES
A7: ENERO | B7: =COUNTIF($A$15:$A$18,A7) -> 1 | C7: =_xlfn.MINIFS($B$15:$B$18,$A$15:$A$18,A7) -> 20.63 | D7: =AVERAGEIF($A$15:$A$18,A7,$B$15:$B$18) -> 20.63 | E7: =_xlfn.MAXIFS($B$15:$B$18,$A$15:$A$18,A7) -> 20.63
A8: FEBRERO | B8: =COUNTIF($A$15:$A$18,A8) -> 1 | C8: =_xlfn.MINIFS($B$15:$B$18,$A$15:$A$18,A8) -> 20.63 | D8: =AVERAGEIF($A$15:$A$18,A8,$B$15:$B$18) -> 20.63 | E8: =_xlfn.MAXIFS($B$15:$B$18,$A$15:$A$18,A8) -> 20.63 | F8: =D8/D7-1 -> 0 | G8: =D8/$D$7-1 -> 0
A9: MAYO | B9: =COUNTIF($A$15:$A$18,A9) -> 1 | C9: =_xlfn.MINIFS($B$15:$B$18,$A$15:$A$18,A9) -> 21.38 | D9: =AVERAGEIF($A$15:$A$18,A9,$B$15:$B$18) -> 21.38 | E9: =_xlfn.MAXIFS($B$15:$B$18,$A$15:$A$18,A9) -> 21.38 | F9: =D9/D8-1 -> 0.036354823 | G9: =D9/$D$7-1 -> 0.036354823
A10: JULIO | B10: =COUNTIF($A$15:$A$18,A10) -> 1 | C10: =_xlfn.MINIFS($B$15:$B$18,$A$15:$A$18,A10) -> 21.38 | D10: =AVERAGEIF($A$15:$A$18,A10,$B$15:$B$18) -> 21.38 | E10: =_xlfn.MAXIFS($B$15:$B$18,$A$15:$A$18,A10) -> 21.38 | F10: =D10/D9-1 -> 0 | G10: =D10/$D$7-1 -> 0.036354823
F11: SUBIDA TOTAL | G11: =D10/D7-1 -> 0.036354823
A13: DETALLE DE PRECIOS (una línea por precio distinto anotado en el Excel del mes)
A14: MES | B14: PRECIO | C14: CANTIDAD | D14: PRODUCTO (tal cual en el Excel) | E14: ARCHIVO ORIGEN
A15: ENERO | B15: 20.63 | C15: 36 | D15: RODA RESERVA 3/4 | E15: ALBARANES MAYO 2026
A16: FEBRERO | B16: 20.63 | C16: 12 | D16: RODA RESERVA 3/4 | E16: ALBARANES MAYO 2026
A17: MAYO | B17: 21.38 | C17: 12 | D17: RODA RESERVA 3/4 | E17: ALBARANES MAYO 2026
A18: JULIO | B18: 21.38 | D18: RODA RESERVA 3/4 | E18: ALBARANES JULIO 2026 v3

Sheet ALBARINO MAR FRADES
A1: ALBARINO MAR FRADES | I1: ← Volver al resumen
A2: Proveedor: DITEMA (DIST. TENA) · Categoría: ENVASADO / BEBIDA / OTROS
A3: Nombres en albaranes: ALBARIÑO MAR DE FRADES
A4: Producto envasado / tarifa: cualquier subida de precio unitario entre el primer y el último mes con compras se considera SUBIDA.
A6: MES | B6: Nº PRECIOS | C6: PRECIO MÍN. | D6: PRECIO MEDIO | E6: PRECIO MÁX. | F6: VAR. vs MES ANTERIOR | G6: VAR. vs PRIMER MES
A7: ENERO | B7: =COUNTIF($A$16:$A$20,A7) -> 1 | C7: =_xlfn.MINIFS($B$16:$B$20,$A$16:$A$20,A7) -> 11.02 | D7: =AVERAGEIF($A$16:$A$20,A7,$B$16:$B$20) -> 11.02 | E7: =_xlfn.MAXIFS($B$16:$B$20,$A$16:$A$20,A7) -> 11.02
A8: FEBRERO | B8: =COUNTIF($A$16:$A$20,A8) -> 1 | C8: =_xlfn.MINIFS($B$16:$B$20,$A$16:$A$20,A8) -> 11.02 | D8: =AVERAGEIF($A$16:$A$20,A8,$B$16:$B$20) -> 11.02 | E8: =_xlfn.MAXIFS($B$16:$B$20,$A$16:$A$20,A8) -> 11.02 | F8: =D8/D7-1 -> 0 | G8: =D8/$D$7-1 -> 0
A9: MAYO | B9: =COUNTIF($A$16:$A$20,A9) -> 1 | C9: =_xlfn.MINIFS($B$16:$B$20,$A$16:$A$20,A9) -> 11.42 | D9: =AVERAGEIF($A$16:$A$20,A9,$B$16:$B$20) -> 11.42 | E9: =_xlfn.MAXIFS($B$16:$B$20,$A$16:$A$20,A9) -> 11.42 | F9: =D9/D8-1 -> 0.036297641 | G9: =D9/$D$7-1 -> 0.036297641
A10: JULIO | B10: =COUNTIF($A$16:$A$20,A10) -> 1 | C10: =_xlfn.MINIFS($B$16:$B$20,$A$16:$A$20,A10) -> 11.42 | D10: =AVERAGEIF($A$16:$A$20,A10,$B$16:$B$20) -> 11.42 | E10: =_xlfn.MAXIFS($B$16:$B$20,$A$16:$A$20,A10) -> 11.42 | F10: =D10/D9-1 -> 0 | G10: =D10/$D$7-1 -> 0.036297641
A11: AGOSTO | B11: =COUNTIF($A$16:$A$20,A11) -> 1 | C11: =_xlfn.MINIFS($B$16:$B$20,$A$16:$A$20,A11) -> 11.42 | D11: =AVERAGEIF($A$16:$A$20,A11,$B$16:$B$20) -> 11.42 | E11: =_xlfn.MAXIFS($B$16:$B$20,$A$16:$A$20,A11) -> 11.42 | F11: =D11/D10-1 -> 0 | G11: =D11/$D$7-1 -> 0.036297641
F12: SUBIDA TOTAL | G12: =D11/D7-1 -> 0.036297641
A14: DETALLE DE PRECIOS (una línea por precio distinto anotado en el Excel del mes)
A15: MES | B15: PRECIO | C15: CANTIDAD | D15: PRODUCTO (tal cual en el Excel) | E15: ARCHIVO ORIGEN
A16: ENERO | B16: 11.02 | C16: 108 | D16: ALBARIÑO MAR DE FRADES | E16: ALBARANES MAYO 2026
A17: FEBRERO | B17: 11.02 | C17: 126 | D17: ALBARIÑO MAR DE FRADES | E17: ALBARANES MAYO 2026
A18: MAYO | B18: 11.42 | C18: 192 | D18: ALBARIÑO MAR DE FRADES | E18: ALBARANES MAYO 2026
A19: JULIO | B19: 11.42 | D19: ALBARIÑO MAR DE FRADES | E19: ALBARANES JULIO 2026 v3
A20: AGOSTO | B20: 11.42 | D20: ALBARIÑO MAR DE FRADES | E20: ALBARANES AGOSTO 2026 v1

Sheet VINA MAYOR VERDEJO
A1: VINA MAYOR VERDEJO | I1: ← Volver al resumen
A2: Proveedor: MUNDELA · Categoría: ENVASADO / BEBIDA / OTROS
A3: Nombres en albaranes: VIÑA MAYOR VERDEJO
A4: Producto envasado / tarifa: cualquier subida de precio unitario entre el primer y el último mes con compras se considera SUBIDA.
A6: MES | B6: Nº PRECIOS | C6: PRECIO MÍN. | D6: PRECIO MEDIO | E6: PRECIO MÁX. | F6: VAR. vs MES ANTERIOR | G6: VAR. vs PRIMER MES
A7: ENERO | B7: =COUNTIF($A$14:$A$16,A7) -> 1 | C7: =_xlfn.MINIFS($B$14:$B$16,$A$14:$A$16,A7) -> 5.88 | D7: =AVERAGEIF($A$14:$A$16,A7,$B$14:$B$16) -> 5.88 | E7: =_xlfn.MAXIFS($B$14:$B$16,$A$14:$A$16,A7) -> 5.88
A8: FEBRERO | B8: =COUNTIF($A$14:$A$16,A8) -> 1 | C8: =_xlfn.MINIFS($B$14:$B$16,$A$14:$A$16,A8) -> 5.88 | D8: =AVERAGEIF($A$14:$A$16,A8,$B$14:$B$16) -> 5.88 | E8: =_xlfn.MAXIFS($B$14:$B$16,$A$14:$A$16,A8) -> 5.88 | F8: =D8/D7-1 -> 0 | G8: =D8/$D$7-1 -> 0
A9: MAYO | B9: =COUNTIF($A$14:$A$16,A9) -> 1 | C9: =_xlfn.MINIFS($B$14:$B$16,$A$14:$A$16,A9) -> 6.08 | D9: =AVERAGEIF($A$14:$A$16,A9,$B$14:$B$16) -> 6.08 | E9: =_xlfn.MAXIFS($B$14:$B$16,$A$14:$A$16,A9) -> 6.08 | F9: =D9/D8-1 -> 0.034013605 | G9: =D9/$D$7-1 -> 0.034013605
F10: SUBIDA TOTAL | G10: =D9/D7-1 -> 0.034013605
A12: DETALLE DE PRECIOS (una línea por precio distinto anotado en el Excel del mes)
A13: MES | B13: PRECIO | C13: CANTIDAD | D13: PRODUCTO (tal cual en el Excel) | E13: ARCHIVO ORIGEN
A14: ENERO | B14: 5.88 | C14: 72 | D14: VIÑA MAYOR VERDEJO | E14: ALBARANES MAYO 2026
A15: FEBRERO | B15: 5.88 | C15: 72 | D15: VIÑA MAYOR VERDEJO | E15: ALBARANES MAYO 2026
A16: MAYO | B16: 6.08 | C16: 48 | D16: VIÑA MAYOR VERDEJO | E16: ALBARANES MAYO 2026

Sheet SEVEN UP FREE VIDRIO 20CL
A1: SEVEN UP FREE VIDRIO 20CL | I1: ← Volver al resumen
A2: Proveedor: VOLDIS · Categoría: ENVASADO / BEBIDA / OTROS
A3: Nombres en albaranes: SEVEN UP FREE VIDRIO RET 20CL CAJA 24U
A4: Producto envasado / tarifa: cualquier subida de precio unitario entre el primer y el último mes con compras se considera SUBIDA.
A6: MES | B6: Nº PRECIOS | C6: PRECIO MÍN. | D6: PRECIO MEDIO | E6: PRECIO MÁX. | F6: VAR. vs MES ANTERIOR | G6: VAR. vs PRIMER MES
A7: ENERO | B7: =COUNTIF($A$14:$A$16,A7) -> 1 | C7: =_xlfn.MINIFS($B$14:$B$16,$A$14:$A$16,A7) -> 22.56 | D7: =AVERAGEIF($A$14:$A$16,A7,$B$14:$B$16) -> 22.56 | E7: =_xlfn.MAXIFS($B$14:$B$16,$A$14:$A$16,A7) -> 22.56
A8: FEBRERO | B8: =COUNTIF($A$14:$A$16,A8) -> 1 | C8: =_xlfn.MINIFS($B$14:$B$16,$A$14:$A$16,A8) -> 23.28 | D8: =AVERAGEIF($A$14:$A$16,A8,$B$14:$B$16) -> 23.28 | E8: =_xlfn.MAXIFS($B$14:$B$16,$A$14:$A$16,A8) -> 23.28 | F8: =D8/D7-1 -> 0.031914894 | G8: =D8/$D$7-1 -> 0.031914894
A9: MAYO | B9: =COUNTIF($A$14:$A$16,A9) -> 1 | C9: =_xlfn.MINIFS($B$14:$B$16,$A$14:$A$16,A9) -> 23.28 | D9: =AVERAGEIF($A$14:$A$16,A9,$B$14:$B$16) -> 23.28 | E9: =_xlfn.MAXIFS($B$14:$B$16,$A$14:$A$16,A9) -> 23.28 | F9: =D9/D8-1 -> 0 | G9: =D9/$D$7-1 -> 0.031914894
F10: SUBIDA TOTAL | G10: =D9/D7-1 -> 0.031914894
A12: DETALLE DE PRECIOS (una línea por precio distinto anotado en el Excel del mes)
A13: MES | B13: PRECIO | C13: CANTIDAD | D13: PRODUCTO (tal cual en el Excel) | E13: ARCHIVO ORIGEN
A14: ENERO | B14: 22.56 | C14: 7 | D14: SEVEN UP FREE VIDRIO RET 20CL CAJA 24U | E14: ALBARANES MAYO 2026
A15: FEBRERO | B15: 23.28 | C15: 3 | D15: SEVEN UP FREE VIDRIO RET 20CL CAJA 24U | E15: ALBARANES MAYO 2026
A16: MAYO | B16: 23.28 | D16: SEVEN UP FREE VIDRIO RET 20CL CAJA 24U | E16: ALBARANES MAYO 2026

Sheet LIPTON ZERO LIMON VIDRIO 35C
A1: LIPTON ZERO LIMON VIDRIO 35CL | I1: ← Volver al resumen
A2: Proveedor: VOLDIS · Categoría: ENVASADO / BEBIDA / OTROS
A3: Nombres en albaranes: LIPTON ZERO LIMON VIDRIO RET 35CL CAJA 24U
A4: Producto envasado / tarifa: cualquier subida de precio unitario entre el primer y el último mes con compras se considera SUBIDA.
A6: MES | B6: Nº PRECIOS | C6: PRECIO MÍN. | D6: PRECIO MEDIO | E6: PRECIO MÁX. | F6: VAR. vs MES ANTERIOR | G6: VAR. vs PRIMER MES
A7: ENERO | B7: =COUNTIF($A$15:$A$18,A7) -> 1 | C7: =_xlfn.MINIFS($B$15:$B$18,$A$15:$A$18,A7) -> 31.92 | D7: =AVERAGEIF($A$15:$A$18,A7,$B$15:$B$18) -> 31.92 | E7: =_xlfn.MAXIFS($B$15:$B$18,$A$15:$A$18,A7) -> 31.92
A8: FEBRERO | B8: =COUNTIF($A$15:$A$18,A8) -> 1 | C8: =_xlfn.MINIFS($B$15:$B$18,$A$15:$A$18,A8) -> 32.88 | D8: =AVERAGEIF($A$15:$A$18,A8,$B$15:$B$18) -> 32.88 | E8: =_xlfn.MAXIFS($B$15:$B$18,$A$15:$A$18,A8) -> 32.88 | F8: =D8/D7-1 -> 0.030075188 | G8: =D8/$D$7-1 -> 0.030075188
A9: MAYO | B9: =COUNTIF($A$15:$A$18,A9) -> 1 | C9: =_xlfn.MINIFS($B$15:$B$18,$A$15:$A$18,A9) -> 32.88 | D9: =AVERAGEIF($A$15:$A$18,A9,$B$15:$B$18) -> 32.88 | E9: =_xlfn.MAXIFS($B$15:$B$18,$A$15:$A$18,A9) -> 32.88 | F9: =D9/D8-1 -> 0 | G9: =D9/$D$7-1 -> 0.030075188
A10: JULIO | B10: =COUNTIF($A$15:$A$18,A10) -> 1 | C10: =_xlfn.MINIFS($B$15:$B$18,$A$15:$A$18,A10) -> 32.88 | D10: =AVERAGEIF($A$15:$A$18,A10,$B$15:$B$18) -> 32.88 | E10: =_xlfn.MAXIFS($B$15:$B$18,$A$15:$A$18,A10) -> 32.88 | F10: =D10/D9-1 -> 0 | G10: =D10/$D$7-1 -> 0.030075188
F11: SUBIDA TOTAL | G11: =D10/D7-1 -> 0.030075188
A13: DETALLE DE PRECIOS (una línea por precio distinto anotado en el Excel del mes)
A14: MES | B14: PRECIO | C14: CANTIDAD | D14: PRODUCTO (tal cual en el Excel) | E14: ARCHIVO ORIGEN
A15: ENERO | B15: 31.92 | C15: 5 | D15: LIPTON ZERO LIMON VIDRIO RET 35CL CAJA 24U | E15: ALBARANES MAYO 2026
A16: FEBRERO | B16: 32.88 | C16: 4 | D16: LIPTON ZERO LIMON VIDRIO RET 35CL CAJA 24U | E16: ALBARANES MAYO 2026
A17: MAYO | B17: 32.88 | C17: 3 | D17: LIPTON ZERO LIMON VIDRIO RET 35CL CAJA 24U | E17: ALBARANES MAYO 2026
A18: JULIO | B18: 32.88 | C18: 5 | D18: LIPTON ZERO LIMON VIDRIO RET 35CL CAJA 24U | E18: ALBARANES JULIO 2026 v3

Sheet R B EDI LIM EARLY HARVEST RO
A1: R B EDI LIM EARLY HARVEST ROSADO | I1: ← Volver al resumen
A2: Proveedor: MUNDELA · Categoría: ENVASADO / BEBIDA / OTROS
A3: Nombres en albaranes: R.B. EDI.LIM EARLY HARVEST ROSADO | R.B. EDI.LIM. EARLY HARVEST ROSADO
A4: Producto envasado / tarifa: cualquier subida de precio unitario entre el primer y el último mes con compras se considera SUBIDA.
A6: MES | B6: Nº PRECIOS | C6: PRECIO MÍN. | D6: PRECIO MEDIO | E6: PRECIO MÁX. | F6: VAR. vs MES ANTERIOR | G6: VAR. vs PRIMER MES
A7: ENERO | B7: =COUNTIF($A$15:$A$18,A7) -> 1 | C7: =_xlfn.MINIFS($B$15:$B$18,$A$15:$A$18,A7) -> 7.69 | D7: =AVERAGEIF($A$15:$A$18,A7,$B$15:$B$18) -> 7.69 | E7: =_xlfn.MAXIFS($B$15:$B$18,$A$15:$A$18,A7) -> 7.69
A8: FEBRERO | B8: =COUNTIF($A$15:$A$18,A8) -> 1 | C8: =_xlfn.MINIFS($B$15:$B$18,$A$15:$A$18,A8) -> 7.69 | D8: =AVERAGEIF($A$15:$A$18,A8,$B$15:$B$18) -> 7.69 | E8: =_xlfn.MAXIFS($B$15:$B$18,$A$15:$A$18,A8) -> 7.69 | F8: =D8/D7-1 -> 0 | G8: =D8/$D$7-1 -> 0
A9: MAYO | B9: =COUNTIF($A$15:$A$18,A9) -> 1 | C9: =_xlfn.MINIFS($B$15:$B$18,$A$15:$A$18,A9) -> 7.88 | D9: =AVERAGEIF($A$15:$A$18,A9,$B$15:$B$18) -> 7.88 | E9: =_xlfn.MAXIFS($B$15:$B$18,$A$15:$A$18,A9) -> 7.88 | F9: =D9/D8-1 -> 0.024707412 | G9: =D9/$D$7-1 -> 0.024707412
A10: JULIO | B10: =COUNTIF($A$15:$A$18,A10) -> 1 | C10: =_xlfn.MINIFS($B$15:$B$18,$A$15:$A$18,A10) -> 7.88 | D10: =AVERAGEIF($A$15:$A$18,A10,$B$15:$B$18) -> 7.88 | E10: =_xlfn.MAXIFS($B$15:$B$18,$A$15:$A$18,A10) -> 7.88 | F10: =D10/D9-1 -> 0 | G10: =D10/$D$7-1 -> 0.024707412
F11: SUBIDA TOTAL | G11: =D10/D7-1 -> 0.024707412
A13: DETALLE DE PRECIOS (una línea por precio distinto anotado en el Excel del mes)
A14: MES | B14: PRECIO | C14: CANTIDAD | D14: PRODUCTO (tal cual en el Excel) | E14: ARCHIVO ORIGEN
A15: ENERO | B15: 7.69 | C15: 24 | D15: R.B. EDI.LIM EARLY HARVEST ROSADO | E15: ALBARANES MAYO 2026
A16: FEBRERO | B16: 7.69 | C16: 48 | D16: R.B. EDI.LIM EARLY HARVEST ROSADO | E16: ALBARANES MAYO 2026
A17: MAYO | B17: 7.88 | C17: 12 | D17: R.B. EDI.LIM EARLY HARVEST ROSADO | E17: ALBARANES MAYO 2026
A18: JULIO | B18: 7.88 | D18: R.B. EDI.LIM. EARLY HARVEST ROSADO | E18: ALBARANES JULIO 2026 v3

Sheet POMMERY ROYAL BRUT 3 4
A1: POMMERY ROYAL BRUT 3/4 | I1: ← Volver al resumen
A2: Proveedor: DITEMA (DIST. TENA) · Categoría: ENVASADO / BEBIDA / OTROS
A3: Nombres en albaranes: POMMERY ROYAL BRUT 3/4
A4: Producto envasado / tarifa: cualquier subida de precio unitario entre el primer y el último mes con compras se considera SUBIDA.
A6: MES | B6: Nº PRECIOS | C6: PRECIO MÍN. | D6: PRECIO MEDIO | E6: PRECIO MÁX. | F6: VAR. vs MES ANTERIOR | G6: VAR. vs PRIMER MES
A7: ENERO | B7: =COUNTIF($A$14:$A$16,A7) -> 1 | C7: =_xlfn.MINIFS($B$14:$B$16,$A$14:$A$16,A7) -> 35.49 | D7: =AVERAGEIF($A$14:$A$16,A7,$B$14:$B$16) -> 35.49 | E7: =_xlfn.MAXIFS($B$14:$B$16,$A$14:$A$16,A7) -> 35.49
A8: FEBRERO | B8: =COUNTIF($A$14:$A$16,A8) -> 1 | C8: =_xlfn.MINIFS($B$14:$B$16,$A$14:$A$16,A8) -> 35.49 | D8: =AVERAGEIF($A$14:$A$16,A8,$B$14:$B$16) -> 35.49 | E8: =_xlfn.MAXIFS($B$14:$B$16,$A$14:$A$16,A8) -> 35.49 | F8: =D8/D7-1 -> 0 | G8: =D8/$D$7-1 -> 0
A9: MAYO | B9: =COUNTIF($A$14:$A$16,A9) -> 1 | C9: =_xlfn.MINIFS($B$14:$B$16,$A$14:$A$16,A9) -> 36.35 | D9: =AVERAGEIF($A$14:$A$16,A9,$B$14:$B$16) -> 36.35 | E9: =_xlfn.MAXIFS($B$14:$B$16,$A$14:$A$16,A9) -> 36.35 | F9: =D9/D8-1 -> 0.024232178 | G9: =D9/$D$7-1 -> 0.024232178
F10: SUBIDA TOTAL | G10: =D9/D7-1 -> 0.024232178
A12: DETALLE DE PRECIOS (una línea por precio distinto anotado en el Excel del mes)
A13: MES | B13: PRECIO | C13: CANTIDAD | D13: PRODUCTO (tal cual en el Excel) | E13: ARCHIVO ORIGEN
A14: ENERO | B14: 35.49 | C14: 18 | D14: POMMERY ROYAL BRUT 3/4 | E14: ALBARANES MAYO 2026
A15: FEBRERO | B15: 35.49 | C15: 12 | D15: POMMERY ROYAL BRUT 3/4 | E15: ALBARANES MAYO 2026
A16: MAYO | B16: 36.35 | C16: 12 | D16: POMMERY ROYAL BRUT 3/4 | E16: ALBARANES MAYO 2026

Sheet GODELLO MAR FRADES
A1: GODELLO MAR FRADES | I1: ← Volver al resumen
A2: Proveedor: DITEMA (DIST. TENA) · Categoría: ENVASADO / BEBIDA / OTROS
A3: Nombres en albaranes: GODELLO DE MAR DE FRADES
A4: Producto envasado / tarifa: cualquier subida de precio unitario entre el primer y el último mes con compras se considera SUBIDA.
A6: MES | B6: Nº PRECIOS | C6: PRECIO MÍN. | D6: PRECIO MEDIO | E6: PRECIO MÁX. | F6: VAR. vs MES ANTERIOR | G6: VAR. vs PRIMER MES
A7: FEBRERO | B7: =COUNTIF($A$13:$A$14,A7) -> 1 | C7: =_xlfn.MINIFS($B$13:$B$14,$A$13:$A$14,A7) -> 17.63 | D7: =AVERAGEIF($A$13:$A$14,A7,$B$13:$B$14) -> 17.63 | E7: =_xlfn.MAXIFS($B$13:$B$14,$A$13:$A$14,A7) -> 17.63
A8: MAYO | B8: =COUNTIF($A$13:$A$14,A8) -> 1 | C8: =_xlfn.MINIFS($B$13:$B$14,$A$13:$A$14,A8) -> 18.03 | D8: =AVERAGEIF($A$13:$A$14,A8,$B$13:$B$14) -> 18.03 | E8: =_xlfn.MAXIFS($B$13:$B$14,$A$13:$A$14,A8) -> 18.03 | F8: =D8/D7-1 -> 0.022688599 | G8: =D8/$D$7-1 -> 0.022688599
F9: SUBIDA TOTAL | G9: =D8/D7-1 -> 0.022688599
A11: DETALLE DE PRECIOS (una línea por precio distinto anotado en el Excel del mes)
A12: MES | B12: PRECIO | C12: CANTIDAD | D12: PRODUCTO (tal cual en el Excel) | E12: ARCHIVO ORIGEN
A13: FEBRERO | B13: 17.63 | C13: 12 | D13: GODELLO DE MAR DE FRADES | E13: ALBARANES MAYO 2026
A14: MAYO | B14: 18.03 | C14: 18 | D14: GODELLO DE MAR DE FRADES | E14: ALBARANES MAYO 2026

Sheet SCHWEPPES LIMON LOW CAL VIDR
A1: SCHWEPPES LIMON LOW CAL VIDRIO 20CL | I1: ← Volver al resumen
A2: Proveedor: VOLDIS · Categoría: ENVASADO / BEBIDA / OTROS
A3: Nombres en albaranes: SCHWEPPES LIMON LOW CAL VIDRIO RET 20CL | SCHWEPPES LIMON LOW CAL VIDRIO RET 20CL CAJA 28U
A4: Producto envasado / tarifa: cualquier subida de precio unitario entre el primer y el último mes con compras se considera SUBIDA.
A6: MES | B6: Nº PRECIOS | C6: PRECIO MÍN. | D6: PRECIO MEDIO | E6: PRECIO MÁX. | F6: VAR. vs MES ANTERIOR | G6: VAR. vs PRIMER MES
A7: ENERO | B7: =COUNTIF($A$15:$A$18,A7) -> 1 | C7: =_xlfn.MINIFS($B$15:$B$18,$A$15:$A$18,A7) -> 25.48 | D7: =AVERAGEIF($A$15:$A$18,A7,$B$15:$B$18) -> 25.48 | E7: =_xlfn.MAXIFS($B$15:$B$18,$A$15:$A$18,A7) -> 25.48
A8: FEBRERO | B8: =COUNTIF($A$15:$A$18,A8) -> 1 | C8: =_xlfn.MINIFS($B$15:$B$18,$A$15:$A$18,A8) -> 26.04 | D8: =AVERAGEIF($A$15:$A$18,A8,$B$15:$B$18) -> 26.04 | E8: =_xlfn.MAXIFS($B$15:$B$18,$A$15:$A$18,A8) -> 26.04 | F8: =D8/D7-1 -> 0.021978022 | G8: =D8/$D$7-1 -> 0.021978022
A9: MAYO | B9: =COUNTIF($A$15:$A$18,A9) -> 1 | C9: =_xlfn.MINIFS($B$15:$B$18,$A$15:$A$18,A9) -> 26.04 | D9: =AVERAGEIF($A$15:$A$18,A9,$B$15:$B$18) -> 26.04 | E9: =_xlfn.MAXIFS($B$15:$B$18,$A$15:$A$18,A9) -> 26.04 | F9: =D9/D8-1 -> 0 | G9: =D9/$D$7-1 -> 0.021978022
A10: JULIO | B10: =COUNTIF($A$15:$A$18,A10) -> 1 | C10: =_xlfn.MINIFS($B$15:$B$18,$A$15:$A$18,A10) -> 26.04 | D10: =AVERAGEIF($A$15:$A$18,A10,$B$15:$B$18) -> 26.04 | E10: =_xlfn.MAXIFS($B$15:$B$18,$A$15:$A$18,A10) -> 26.04 | F10: =D10/D9-1 -> 0 | G10: =D10/$D$7-1 -> 0.021978022
F11: SUBIDA TOTAL | G11: =D10/D7-1 -> 0.021978022
A13: DETALLE DE PRECIOS (una línea por precio distinto anotado en el Excel del mes)
A14: MES | B14: PRECIO | C14: CANTIDAD | D14: PRODUCTO (tal cual en el Excel) | E14: ARCHIVO ORIGEN
A15: ENERO | B15: 25.48 | C15: 4 | D15: SCHWEPPES LIMON LOW CAL VIDRIO RET 20CL CAJA 28U | E15: ALBARANES MAYO 2026
A16: FEBRERO | B16: 26.04 | C16: 6 | D16: SCHWEPPES LIMON LOW CAL VIDRIO RET 20CL CAJA 28U | E16: ALBARANES MAYO 2026
A17: MAYO | B17: 26.04 | C17: 10 | D17: SCHWEPPES LIMON LOW CAL VIDRIO RET 20CL CAJA 28U | E17: ALBARANES MAYO 2026
A18: JULIO | B18: 26.04 | C18: 7 | D18: SCHWEPPES LIMON LOW CAL VIDRIO RET 20CL | E18: ALBARANES JULIO 2026 v3

Sheet SCHWEPPES NARANJA LOW CAL VI
A1: SCHWEPPES NARANJA LOW CAL VIDRIO 20CL | I1: ← Volver al resumen
A2: Proveedor: VOLDIS · Categoría: ENVASADO / BEBIDA / OTROS
A3: Nombres en albaranes: SCHWEPPES NARANJA LOW CAL VIDRIO RET 20CL
A4: Producto envasado / tarifa: cualquier subida de precio unitario entre el primer y el último mes con compras se considera SUBIDA.
A6: MES | B6: Nº PRECIOS | C6: PRECIO MÍN. | D6: PRECIO MEDIO | E6: PRECIO MÁX. | F6: VAR. vs MES ANTERIOR | G6: VAR. vs PRIMER MES
A7: ENERO | B7: =COUNTIF($A$15:$A$18,A7) -> 1 | C7: =_xlfn.MINIFS($B$15:$B$18,$A$15:$A$18,A7) -> 25.48 | D7: =AVERAGEIF($A$15:$A$18,A7,$B$15:$B$18) -> 25.48 | E7: =_xlfn.MAXIFS($B$15:$B$18,$A$15:$A$18,A7) -> 25.48
A8: FEBRERO | B8: =COUNTIF($A$15:$A$18,A8) -> 1 | C8: =_xlfn.MINIFS($B$15:$B$18,$A$15:$A$18,A8) -> 26.04 | D8: =AVERAGEIF($A$15:$A$18,A8,$B$15:$B$18) -> 26.04 | E8: =_xlfn.MAXIFS($B$15:$B$18,$A$15:$A$18,A8) -> 26.04 | F8: =D8/D7-1 -> 0.021978022 | G8: =D8/$D$7-1 -> 0.021978022
A9: MAYO | B9: =COUNTIF($A$15:$A$18,A9) -> 1 | C9: =_xlfn.MINIFS($B$15:$B$18,$A$15:$A$18,A9) -> 26.04 | D9: =AVERAGEIF($A$15:$A$18,A9,$B$15:$B$18) -> 26.04 | E9: =_xlfn.MAXIFS($B$15:$B$18,$A$15:$A$18,A9) -> 26.04 | F9: =D9/D8-1 -> 0 | G9: =D9/$D$7-1 -> 0.021978022
A10: JULIO | B10: =COUNTIF($A$15:$A$18,A10) -> 1 | C10: =_xlfn.MINIFS($B$15:$B$18,$A$15:$A$18,A10) -> 26.04 | D10: =AVERAGEIF($A$15:$A$18,A10,$B$15:$B$18) -> 26.04 | E10: =_xlfn.MAXIFS($B$15:$B$18,$A$15:$A$18,A10) -> 26.04 | F10: =D10/D9-1 -> 0 | G10: =D10/$D$7-1 -> 0.021978022
F11: SUBIDA TOTAL | G11: =D10/D7-1 -> 0.021978022
A13: DETALLE DE PRECIOS (una línea por precio distinto anotado en el Excel del mes)
A14: MES | B14: PRECIO | C14: CANTIDAD | D14: PRODUCTO (tal cual en el Excel) | E14: ARCHIVO ORIGEN
A15: ENERO | B15: 25.48 | C15: 2 | D15: SCHWEPPES NARANJA LOW CAL VIDRIO RET 20CL | E15: ALBARANES MAYO 2026
A16: FEBRERO | B16: 26.04 | C16: 2 | D16: SCHWEPPES NARANJA LOW CAL VIDRIO RET 20CL | E16: ALBARANES MAYO 2026
A17: MAYO | B17: 26.04 | C17: 3 | D17: SCHWEPPES NARANJA LOW CAL VIDRIO RET 20CL | E17: ALBARANES MAYO 2026
A18: JULIO | B18: 26.04 | C18: 1 | D18: SCHWEPPES NARANJA LOW CAL VIDRIO RET 20CL | E18: ALBARANES JULIO 2026 v3

Sheet CUAD A O SUAVE GUADALIMAR 5L
A1: CUAD A O SUAVE GUADALIMAR 5L | I1: ← Volver al resumen
A2: Proveedor: MAGOASE · Categoría: ENVASADO / BEBIDA / OTROS
A3: Nombres en albaranes: BID. PET CUAD. A.O. SUAVE GUADALIMAR 5L
A4: Producto envasado / tarifa: cualquier subida de precio unitario entre el primer y el último mes con compras se considera SUBIDA.
A6: MES | B6: Nº PRECIOS | C6: PRECIO MÍN. | D6: PRECIO MEDIO | E6: PRECIO MÁX. | F6: VAR. vs MES ANTERIOR | G6: VAR. vs PRIMER MES
A7: ENERO | B7: =COUNTIF($A$17:$A$25,A7) -> 1 | C7: =_xlfn.MINIFS($B$17:$B$25,$A$17:$A$25,A7) -> 23.95 | D7: =AVERAGEIF($A$17:$A$25,A7,$B$17:$B$25) -> 23.95 | E7: =_xlfn.MAXIFS($B$17:$B$25,$A$17:$A$25,A7) -> 23.95
A8: FEBRERO | B8: =COUNTIF($A$17:$A$25,A8) -> 2 | C8: =_xlfn.MINIFS($B$17:$B$25,$A$17:$A$25,A8) -> 23.95 | D8: =AVERAGEIF($A$17:$A$25,A8,$B$17:$B$25) -> 24.95 | E8: =_xlfn.MAXIFS($B$17:$B$25,$A$17:$A$25,A8) -> 25.95 | F8: =D8/D7-1 -> 0.041753653 | G8: =D8/$D$7-1 -> 0.041753653
A9: ABRIL | B9: =COUNTIF($A$17:$A$25,A9) -> 2 | C9: =_xlfn.MINIFS($B$17:$B$25,$A$17:$A$25,A9) -> 23.95 | D9: =AVERAGEIF($A$17:$A$25,A9,$B$17:$B$25) -> 24.95 | E9: =_xlfn.MAXIFS($B$17:$B$25,$A$17:$A$25,A9) -> 25.95 | F9: =D9/D8-1 -> 0 | G9: =D9/$D$7-1 -> 0.041753653
A10: MAYO | B10: =COUNTIF($A$17:$A$25,A10) -> 1 | C10: =_xlfn.MINIFS($B$17:$B$25,$A$17:$A$25,A10) -> 23.95 | D10: =AVERAGEIF($A$17:$A$25,A10,$B$17:$B$25) -> 23.95 | E10: =_xlfn.MAXIFS($B$17:$B$25,$A$17:$A$25,A10) -> 23.95 | F10: =D10/D9-1 -> -0.04008016 | G10: =D10/$D$7-1 -> 0
A11: JULIO | B11: =COUNTIF($A$17:$A$25,A11) -> 1 | C11: =_xlfn.MINIFS($B$17:$B$25,$A$17:$A$25,A11) -> 23.95 | D11: =AVERAGEIF($A$17:$A$25,A11,$B$17:$B$25) -> 23.95 | E11: =_xlfn.MAXIFS($B$17:$B$25,$A$17:$A$25,A11) -> 23.95 | F11: =D11/D10-1 -> 0 | G11: =D11/$D$7-1 -> 0
A12: AGOSTO | B12: =COUNTIF($A$17:$A$25,A12) -> 2 | C12: =_xlfn.MINIFS($B$17:$B$25,$A$17:$A$25,A12) -> 23.95 | D12: =AVERAGEIF($A$17:$A$25,A12,$B$17:$B$25) -> 24.45 | E12: =_xlfn.MAXIFS($B$17:$B$25,$A$17:$A$25,A12) -> 24.95 | F12: =D12/D11-1 -> 0.020876827 | G12: =D12/$D$7-1 -> 0.020876827
F13: SUBIDA TOTAL | G13: =D12/D7-1 -> 0.020876827
A15: DETALLE DE PRECIOS (una línea por precio distinto anotado en el Excel del mes)
A16: MES | B16: PRECIO | C16: CANTIDAD | D16: PRODUCTO (tal cual en el Excel) | E16: ARCHIVO ORIGEN
A17: ENERO | B17: 23.95 | C17: 42 | D17: BID. PET CUAD. A.O. SUAVE GUADALIMAR 5L | E17: ALBARANES MAYO 2026
A18: FEBRERO | B18: 23.95 | C18: 36 | D18: BID. PET CUAD. A.O. SUAVE GUADALIMAR 5L | E18: ALBARANES MAYO 2026
A19: FEBRERO | B19: 25.95 | C19: 3 | D19: BID. PET CUAD. A.O. SUAVE GUADALIMAR 5L | E19: ALBARANES MAYO 2026
A20: ABRIL | B20: 23.95 | C20: 45 | D20: BID. PET CUAD. A.O. SUAVE GUADALIMAR 5L | E20: ALBARANES MAYO 2026
A21: ABRIL | B21: 25.95 | C21: 0 | D21: BID. PET CUAD. A.O. SUAVE GUADALIMAR 5L | E21: ALBARANES MAYO 2026
A22: MAYO | B22: 23.95 | C22: 45 | D22: BID. PET CUAD. A.O. SUAVE GUADALIMAR 5L | E22: ALBARANES MAYO 2026
A23: JULIO | B23: 23.95 | D23: BID. PET CUAD. A.O. SUAVE GUADALIMAR 5L | E23: ALBARANES JULIO 2026 v3
A24: AGOSTO | B24: 23.95 | D24: BID. PET CUAD. A.O. SUAVE GUADALIMAR 5L | E24: ALBARANES AGOSTO 2026 v1
A25: AGOSTO | B25: 24.95 | D25: BID. PET CUAD. A.O. SUAVE GUADALIMAR 5L | E25: ALBARANES AGOSTO 2026 v1

Sheet VINAGRE JEREZ RESERVA AL MOS
A1: VINAGRE JEREZ RESERVA AL MOSCATEL | I1: ← Volver al resumen
A2: Proveedor: MUNDELA · Categoría: ENVASADO / BEBIDA / OTROS
A3: Nombres en albaranes: VINAGRE DE JEREZ REERVA AL MOSCATEL | VINAGRE DE JEREZ RESERVA AL MOSCATEL
A4: Producto envasado / tarifa: cualquier subida de precio unitario entre el primer y el último mes con compras se considera SUBIDA.
A6: MES | B6: Nº PRECIOS | C6: PRECIO MÍN. | D6: PRECIO MEDIO | E6: PRECIO MÁX. | F6: VAR. vs MES ANTERIOR | G6: VAR. vs PRIMER MES
A7: ENERO | B7: =COUNTIF($A$16:$A$20,A7) -> 1 | C7: =_xlfn.MINIFS($B$16:$B$20,$A$16:$A$20,A7) -> 5.33 | D7: =AVERAGEIF($A$16:$A$20,A7,$B$16:$B$20) -> 5.33 | E7: =_xlfn.MAXIFS($B$16:$B$20,$A$16:$A$20,A7) -> 5.33
A8: FEBRERO | B8: =COUNTIF($A$16:$A$20,A8) -> 1 | C8: =_xlfn.MINIFS($B$16:$B$20,$A$16:$A$20,A8) -> 5.33 | D8: =AVERAGEIF($A$16:$A$20,A8,$B$16:$B$20) -> 5.33 | E8: =_xlfn.MAXIFS($B$16:$B$20,$A$16:$A$20,A8) -> 5.33 | F8: =D8/D7-1 -> 0 | G8: =D8/$D$7-1 -> 0
A9: MAYO | B9: =COUNTIF($A$16:$A$20,A9) -> 1 | C9: =_xlfn.MINIFS($B$16:$B$20,$A$16:$A$20,A9) -> 5.44 | D9: =AVERAGEIF($A$16:$A$20,A9,$B$16:$B$20) -> 5.44 | E9: =_xlfn.MAXIFS($B$16:$B$20,$A$16:$A$20,A9) -> 5.44 | F9: =D9/D8-1 -> 0.020637899 | G9: =D9/$D$7-1 -> 0.020637899
A10: JULIO | B10: =COUNTIF($A$16:$A$20,A10) -> 1 | C10: =_xlfn.MINIFS($B$16:$B$20,$A$16:$A$20,A10) -> 5.44 | D10: =AVERAGEIF($A$16:$A$20,A10,$B$16:$B$20) -> 5.44 | E10: =_xlfn.MAXIFS($B$16:$B$20,$A$16:$A$20,A10) -> 5.44 | F10: =D10/D9-1 -> 0 | G10: =D10/$D$7-1 -> 0.020637899
A11: AGOSTO | B11: =COUNTIF($A$16:$A$20,A11) -> 1 | C11: =_xlfn.MINIFS($B$16:$B$20,$A$16:$A$20,A11) -> 5.44 | D11: =AVERAGEIF($A$16:$A$20,A11,$B$16:$B$20) -> 5.44 | E11: =_xlfn.MAXIFS($B$16:$B$20,$A$16:$A$20,A11) -> 5.44 | F11: =D11/D10-1 -> 0 | G11: =D11/$D$7-1 -> 0.020637899
F12: SUBIDA TOTAL | G12: =D11/D7-1 -> 0.020637899
A14: DETALLE DE PRECIOS (una línea por precio distinto anotado en el Excel del mes)
A15: MES | B15: PRECIO | C15: CANTIDAD | D15: PRODUCTO (tal cual en el Excel) | E15: ARCHIVO ORIGEN
A16: ENERO | B16: 5.33 | C16: 6 | D16: VINAGRE DE JEREZ REERVA AL MOSCATEL | E16: ALBARANES MAYO 2026
A17: FEBRERO | B17: 5.33 | C17: 12 | D17: VINAGRE DE JEREZ REERVA AL MOSCATEL | E17: ALBARANES MAYO 2026
A18: MAYO | B18: 5.44 | C18: 12 | D18: VINAGRE DE JEREZ REERVA AL MOSCATEL | E18: ALBARANES MAYO 2026
A19: JULIO | B19: 5.44 | D19: VINAGRE DE JEREZ RESERVA AL MOSCATEL | E19: ALBARANES JULIO 2026 v3
A20: AGOSTO | B20: 5.44 | D20: VINAGRE DE JEREZ RESERVA AL MOSCATEL | E20: ALBARANES AGOSTO 2026 v1

Sheet FLOR ALCACHOFA CONFITADA EN
A1: FLOR ALCACHOFA CONFITADA EN AOVE | I1: ← Volver al resumen
A2: Proveedor: FCO JAVIER LABRADOR · Categoría: ENVASADO / BEBIDA / OTROS
A3: Nombres en albaranes: FLOR DE ALCACHOFA CONFITADA EN AOVE 20UDS
A4: Producto envasado / tarifa: cualquier subida de precio unitario entre el primer y el último mes con compras se considera SUBIDA.
A6: MES | B6: Nº PRECIOS | C6: PRECIO MÍN. | D6: PRECIO MEDIO | E6: PRECIO MÁX. | F6: VAR. vs MES ANTERIOR | G6: VAR. vs PRIMER MES
A7: ENERO | B7: =COUNTIF($A$15:$A$18,A7) -> 1 | C7: =_xlfn.MINIFS($B$15:$B$18,$A$15:$A$18,A7) -> 22.45 | D7: =AVERAGEIF($A$15:$A$18,A7,$B$15:$B$18) -> 22.45 | E7: =_xlfn.MAXIFS($B$15:$B$18,$A$15:$A$18,A7) -> 22.45
A8: FEBRERO | B8: =COUNTIF($A$15:$A$18,A8) -> 1 | C8: =_xlfn.MINIFS($B$15:$B$18,$A$15:$A$18,A8) -> 22.45 | D8: =AVERAGEIF($A$15:$A$18,A8,$B$15:$B$18) -> 22.45 | E8: =_xlfn.MAXIFS($B$15:$B$18,$A$15:$A$18,A8) -> 22.45 | F8: =D8/D7-1 -> 0 | G8: =D8/$D$7-1 -> 0
A9: ABRIL | B9: =COUNTIF($A$15:$A$18,A9) -> 1 | C9: =_xlfn.MINIFS($B$15:$B$18,$A$15:$A$18,A9) -> 22.9 | D9: =AVERAGEIF($A$15:$A$18,A9,$B$15:$B$18) -> 22.9 | E9: =_xlfn.MAXIFS($B$15:$B$18,$A$15:$A$18,A9) -> 22.9 | F9: =D9/D8-1 -> 0.020044543 | G9: =D9/$D$7-1 -> 0.020044543
A10: MAYO | B10: =COUNTIF($A$15:$A$18,A10) -> 1 | C10: =_xlfn.MINIFS($B$15:$B$18,$A$15:$A$18,A10) -> 22.9 | D10: =AVERAGEIF($A$15:$A$18,A10,$B$15:$B$18) -> 22.9 | E10: =_xlfn.MAXIFS($B$15:$B$18,$A$15:$A$18,A10) -> 22.9 | F10: =D10/D9-1 -> 0 | G10: =D10/$D$7-1 -> 0.020044543
F11: SUBIDA TOTAL | G11: =D10/D7-1 -> 0.020044543
A13: DETALLE DE PRECIOS (una línea por precio distinto anotado en el Excel del mes)
A14: MES | B14: PRECIO | C14: CANTIDAD | D14: PRODUCTO (tal cual en el Excel) | E14: ARCHIVO ORIGEN
A15: ENERO | B15: 22.45 | C15: 4 | D15: FLOR DE ALCACHOFA CONFITADA EN AOVE 20UDS | E15: ALBARANES MAYO 2026
A16: FEBRERO | B16: 22.45 | C16: 12 | D16: FLOR DE ALCACHOFA CONFITADA EN AOVE 20UDS | E16: ALBARANES MAYO 2026
A17: ABRIL | B17: 22.9 | C17: 24 | D17: FLOR DE ALCACHOFA CONFITADA EN AOVE 20UDS | E17: ALBARANES MAYO 2026
A18: MAYO | B18: 22.9 | C18: 8 | D18: FLOR DE ALCACHOFA CONFITADA EN AOVE 20UDS | E18: ALBARANES MAYO 2026

Sheet BARBADILLO VI MOSCATO FRIZZA
A1: BARBADILLO VI MOSCATO FRIZZANTE | I1: ← Volver al resumen
A2: Proveedor: MUNDELA · Categoría: ENVASADO / BEBIDA / OTROS
A3: Nombres en albaranes: BARBADILLO VI MOSCATO FRIZZANTE
A4: Producto envasado / tarifa: cualquier subida de precio unitario entre el primer y el último mes con compras se considera SUBIDA.
A6: MES | B6: Nº PRECIOS | C6: PRECIO MÍN. | D6: PRECIO MEDIO | E6: PRECIO MÁX. | F6: VAR. vs MES ANTERIOR | G6: VAR. vs PRIMER MES
A7: FEBRERO | B7: =COUNTIF($A$15:$A$18,A7) -> 1 | C7: =_xlfn.MINIFS($B$15:$B$18,$A$15:$A$18,A7) -> 5.52 | D7: =AVERAGEIF($A$15:$A$18,A7,$B$15:$B$18) -> 5.52 | E7: =_xlfn.MAXIFS($B$15:$B$18,$A$15:$A$18,A7) -> 5.52
A8: MAYO | B8: =COUNTIF($A$15:$A$18,A8) -> 1 | C8: =_xlfn.MINIFS($B$15:$B$18,$A$15:$A$18,A8) -> 5.63 | D8: =AVERAGEIF($A$15:$A$18,A8,$B$15:$B$18) -> 5.63 | E8: =_xlfn.MAXIFS($B$15:$B$18,$A$15:$A$18,A8) -> 5.63 | F8: =D8/D7-1 -> 0.019927536 | G8: =D8/$D$7-1 -> 0.019927536
A9: JULIO | B9: =COUNTIF($A$15:$A$18,A9) -> 1 | C9: =_xlfn.MINIFS($B$15:$B$18,$A$15:$A$18,A9) -> 5.63 | D9: =AVERAGEIF($A$15:$A$18,A9,$B$15:$B$18) -> 5.63 | E9: =_xlfn.MAXIFS($B$15:$B$18,$A$15:$A$18,A9) -> 5.63 | F9: =D9/D8-1 -> 0 | G9: =D9/$D$7-1 -> 0.019927536
A10: AGOSTO | B10: =COUNTIF($A$15:$A$18,A10) -> 1 | C10: =_xlfn.MINIFS($B$15:$B$18,$A$15:$A$18,A10) -> 5.63 | D10: =AVERAGEIF($A$15:$A$18,A10,$B$15:$B$18) -> 5.63 | E10: =_xlfn.MAXIFS($B$15:$B$18,$A$15:$A$18,A10) -> 5.63 | F10: =D10/D9-1 -> 0 | G10: =D10/$D$7-1 -> 0.019927536
F11: SUBIDA TOTAL | G11: =D10/D7-1 -> 0.019927536
A13: DETALLE DE PRECIOS (una línea por precio distinto anotado en el Excel del mes)
A14: MES | B14: PRECIO | C14: CANTIDAD | D14: PRODUCTO (tal cual en el Excel) | E14: ARCHIVO ORIGEN
A15: FEBRERO | B15: 5.52 | C15: 18 | D15: BARBADILLO VI MOSCATO FRIZZANTE | E15: ALBARANES MAYO 2026
A16: MAYO | B16: 5.63 | C16: 12 | D16: BARBADILLO VI MOSCATO FRIZZANTE | E16: ALBARANES MAYO 2026
A17: JULIO | B17: 5.63 | D17: BARBADILLO VI MOSCATO FRIZZANTE | E17: ALBARANES JULIO 2026 v3
A18: AGOSTO | B18: 5.63 | D18: BARBADILLO VI MOSCATO FRIZZANTE | E18: ALBARANES AGOSTO 2026 v1

Sheet MAESTRO DOBEL DIAMANTE REPOS
A1: MAESTRO DOBEL DIAMANTE REPOSADO 0,70 | I1: ← Volver al resumen
A2: Proveedor: SUBMARINER · Categoría: ENVASADO / BEBIDA / OTROS
A3: Nombres en albaranes: MAESTRO DOBEL DIAMANTE REPOSADO 0,70 | MAESTRO DOBEL DIAMANTE REPOSADO 0.70
A4: Producto envasado / tarifa: cualquier subida de precio unitario entre el primer y el último mes con compras se considera SUBIDA.
A6: MES | B6: Nº PRECIOS | C6: PRECIO MÍN. | D6: PRECIO MEDIO | E6: PRECIO MÁX. | F6: VAR. vs MES ANTERIOR | G6: VAR. vs PRIMER MES
A7: ENERO | B7: =COUNTIF($A$16:$A$20,A7) -> 1 | C7: =_xlfn.MINIFS($B$16:$B$20,$A$16:$A$20,A7) -> 54.14 | D7: =AVERAGEIF($A$16:$A$20,A7,$B$16:$B$20) -> 54.14 | E7: =_xlfn.MAXIFS($B$16:$B$20,$A$16:$A$20,A7) -> 54.14
A8: FEBRERO | B8: =COUNTIF($A$16:$A$20,A8) -> 1 | C8: =_xlfn.MINIFS($B$16:$B$20,$A$16:$A$20,A8) -> 54.14 | D8: =AVERAGEIF($A$16:$A$20,A8,$B$16:$B$20) -> 54.14 | E8: =_xlfn.MAXIFS($B$16:$B$20,$A$16:$A$20,A8) -> 54.14 | F8: =D8/D7-1 -> 0 | G8: =D8/$D$7-1 -> 0
A9: MAYO | B9: =COUNTIF($A$16:$A$20,A9) -> 1 | C9: =_xlfn.MINIFS($B$16:$B$20,$A$16:$A$20,A9) -> 55.17 | D9: =AVERAGEIF($A$16:$A$20,A9,$B$16:$B$20) -> 55.17 | E9: =_xlfn.MAXIFS($B$16:$B$20,$A$16:$A$20,A9) -> 55.17 | F9: =D9/D8-1 -> 0.019024751 | G9: =D9/$D$7-1 -> 0.019024751
A10: JULIO | B10: =COUNTIF($A$16:$A$20,A10) -> 1 | C10: =_xlfn.MINIFS($B$16:$B$20,$A$16:$A$20,A10) -> 55.17 | D10: =AVERAGEIF($A$16:$A$20,A10,$B$16:$B$20) -> 55.17 | E10: =_xlfn.MAXIFS($B$16:$B$20,$A$16:$A$20,A10) -> 55.17 | F10: =D10/D9-1 -> 0 | G10: =D10/$D$7-1 -> 0.019024751
A11: AGOSTO | B11: =COUNTIF($A$16:$A$20,A11) -> 1 | C11: =_xlfn.MINIFS($B$16:$B$20,$A$16:$A$20,A11) -> 55.17 | D11: =AVERAGEIF($A$16:$A$20,A11,$B$16:$B$20) -> 55.17 | E11: =_xlfn.MAXIFS($B$16:$B$20,$A$16:$A$20,A11) -> 55.17 | F11: =D11/D10-1 -> 0 | G11: =D11/$D$7-1 -> 0.019024751
F12: SUBIDA TOTAL | G12: =D11/D7-1 -> 0.019024751
A14: DETALLE DE PRECIOS (una línea por precio distinto anotado en el Excel del mes)
A15: MES | B15: PRECIO | C15: CANTIDAD | D15: PRODUCTO (tal cual en el Excel) | E15: ARCHIVO ORIGEN
A16: ENERO | B16: 54.14 | C16: 3 | D16: MAESTRO DOBEL DIAMANTE REPOSADO 0,70 | E16: ALBARANES MAYO 2026
A17: FEBRERO | B17: 54.14 | C17: 2 | D17: MAESTRO DOBEL DIAMANTE REPOSADO 0,70 | E17: ALBARANES MAYO 2026
A18: MAYO | B18: 55.17 | C18: 3 | D18: MAESTRO DOBEL DIAMANTE REPOSADO 0,70 | E18: ALBARANES MAYO 2026
A19: JULIO | B19: 55.17 | C19: 2 | D19: MAESTRO DOBEL DIAMANTE REPOSADO 0.70 | E19: ALBARANES JULIO 2026 v3
A20: AGOSTO | B20: 55.17 | C20: 2 | D20: MAESTRO DOBEL DIAMANTE REPOSADO 0.70 | E20: ALBARANES AGOSTO 2026 v1

Sheet IZAGUIRRE BOX 20L
A1: IZAGUIRRE BOX 20L | I1: ← Volver al resumen
A2: Proveedor: EIF DISTRIBUCIONES · Categoría: ENVASADO / BEBIDA / OTROS
A3: Nombres en albaranes: IZAGUIRRE BOX 20L
A4: Producto envasado / tarifa: cualquier subida de precio unitario entre el primer y el último mes con compras se considera SUBIDA.
A6: MES | B6: Nº PRECIOS | C6: PRECIO MÍN. | D6: PRECIO MEDIO | E6: PRECIO MÁX. | F6: VAR. vs MES ANTERIOR | G6: VAR. vs PRIMER MES
A7: ENERO | B7: =COUNTIF($A$15:$A$19,A7) -> 2 | C7: =_xlfn.MINIFS($B$15:$B$19,$A$15:$A$19,A7) -> 116.18 | D7: =AVERAGEIF($A$15:$A$19,A7,$B$15:$B$19) -> 118.165 | E7: =_xlfn.MAXIFS($B$15:$B$19,$A$15:$A$19,A7) -> 120.15
A8: FEBRERO | B8: =COUNTIF($A$15:$A$19,A8) -> 1 | C8: =_xlfn.MINIFS($B$15:$B$19,$A$15:$A$19,A8) -> 116.18 | D8: =AVERAGEIF($A$15:$A$19,A8,$B$15:$B$19) -> 116.18 | E8: =_xlfn.MAXIFS($B$15:$B$19,$A$15:$A$19,A8) -> 116.18 | F8: =D8/D7-1 -> -0.016798544 | G8: =D8/$D$7-1 -> -0.016798544
A9: JULIO | B9: =COUNTIF($A$15:$A$19,A9) -> 1 | C9: =_xlfn.MINIFS($B$15:$B$19,$A$15:$A$19,A9) -> 120.15 | D9: =AVERAGEIF($A$15:$A$19,A9,$B$15:$B$19) -> 120.15 | E9: =_xlfn.MAXIFS($B$15:$B$19,$A$15:$A$19,A9) -> 120.15 | F9: =D9/D8-1 -> 0.034171114 | G9: =D9/$D$7-1 -> 0.016798544
A10: AGOSTO | B10: =COUNTIF($A$15:$A$19,A10) -> 1 | C10: =_xlfn.MINIFS($B$15:$B$19,$A$15:$A$19,A10) -> 120.15 | D10: =AVERAGEIF($A$15:$A$19,A10,$B$15:$B$19) -> 120.15 | E10: =_xlfn.MAXIFS($B$15:$B$19,$A$15:$A$19,A10) -> 120.15 | F10: =D10/D9-1 -> 0 | G10: =D10/$D$7-1 -> 0.016798544
F11: SUBIDA TOTAL | G11: =D10/D7-1 -> 0.016798544
A13: DETALLE DE PRECIOS (una línea por precio distinto anotado en el Excel del mes)
A14: MES | B14: PRECIO | C14: CANTIDAD | D14: PRODUCTO (tal cual en el Excel) | E14: ARCHIVO ORIGEN
A15: ENERO | B15: 116.18 | C15: 4 | D15: IZAGUIRRE BOX 20L | E15: ALBARANES MAYO 2026
A16: ENERO | B16: 120.15 | C16: 4 | D16: IZAGUIRRE BOX 20L | E16: ALBARANES MAYO 2026
A17: FEBRERO | B17: 116.18 | C17: 3 | D17: IZAGUIRRE BOX 20L | E17: ALBARANES MAYO 2026
A18: JULIO | B18: 120.15 | C18: 2 | D18: IZAGUIRRE BOX 20L | E18: ALBARANES JULIO 2026 v3
A19: AGOSTO | B19: 120.15 | C19: 1 | D19: IZAGUIRRE BOX 20L | E19: ALBARANES AGOSTO 2026 v1

Sheet MACALLAN 12
A1: MACALLAN 12 | I1: ← Volver al resumen
A2: Proveedor: SUBMARINER · Categoría: ENVASADO / BEBIDA / OTROS
A3: Nombres en albaranes: MACALLAN 12
A4: Producto envasado / tarifa: cualquier subida de precio unitario entre el primer y el último mes con compras se considera SUBIDA.
A6: MES | B6: Nº PRECIOS | C6: PRECIO MÍN. | D6: PRECIO MEDIO | E6: PRECIO MÁX. | F6: VAR. vs MES ANTERIOR | G6: VAR. vs PRIMER MES
A7: FEBRERO | B7: =COUNTIF($A$14:$A$16,A7) -> 1 | C7: =_xlfn.MINIFS($B$14:$B$16,$A$14:$A$16,A7) -> 55.2 | D7: =AVERAGEIF($A$14:$A$16,A7,$B$14:$B$16) -> 55.2 | E7: =_xlfn.MAXIFS($B$14:$B$16,$A$14:$A$16,A7) -> 55.2
A8: MAYO | B8: =COUNTIF($A$14:$A$16,A8) -> 1 | C8: =_xlfn.MINIFS($B$14:$B$16,$A$14:$A$16,A8) -> 56.01 | D8: =AVERAGEIF($A$14:$A$16,A8,$B$14:$B$16) -> 56.01 | E8: =_xlfn.MAXIFS($B$14:$B$16,$A$14:$A$16,A8) -> 56.01 | F8: =D8/D7-1 -> 0.014673913 | G8: =D8/$D$7-1 -> 0.014673913
A9: JULIO | B9: =COUNTIF($A$14:$A$16,A9) -> 1 | C9: =_xlfn.MINIFS($B$14:$B$16,$A$14:$A$16,A9) -> 56.01 | D9: =AVERAGEIF($A$14:$A$16,A9,$B$14:$B$16) -> 56.01 | E9: =_xlfn.MAXIFS($B$14:$B$16,$A$14:$A$16,A9) -> 56.01 | F9: =D9/D8-1 -> 0 | G9: =D9/$D$7-1 -> 0.014673913
F10: SUBIDA TOTAL | G10: =D9/D7-1 -> 0.014673913
A12: DETALLE DE PRECIOS (una línea por precio distinto anotado en el Excel del mes)
A13: MES | B13: PRECIO | C13: CANTIDAD | D13: PRODUCTO (tal cual en el Excel) | E13: ARCHIVO ORIGEN
A14: FEBRERO | B14: 55.2 | C14: 3 | D14: MACALLAN 12 | E14: ALBARANES MAYO 2026
A15: MAYO | B15: 56.01 | C15: 6 | D15: MACALLAN 12 | E15: ALBARANES MAYO 2026
A16: JULIO | B16: 56.01 | C16: 3 | D16: MACALLAN 12 | E16: ALBARANES JULIO 2026 v3

Sheet ABSOLUT 0,70
A1: ABSOLUT 0,70 | I1: ← Volver al resumen
A2: Proveedor: SUBMARINER · Categoría: ENVASADO / BEBIDA / OTROS
A3: Nombres en albaranes: ABSOLUT 0,70L
A4: Producto envasado / tarifa: cualquier subida de precio unitario entre el primer y el último mes con compras se considera SUBIDA.
A6: MES | B6: Nº PRECIOS | C6: PRECIO MÍN. | D6: PRECIO MEDIO | E6: PRECIO MÁX. | F6: VAR. vs MES ANTERIOR | G6: VAR. vs PRIMER MES
A7: ENERO | B7: =COUNTIF($A$16:$A$20,A7) -> 1 | C7: =_xlfn.MINIFS($B$16:$B$20,$A$16:$A$20,A7) -> 11.68 | D7: =AVERAGEIF($A$16:$A$20,A7,$B$16:$B$20) -> 11.68 | E7: =_xlfn.MAXIFS($B$16:$B$20,$A$16:$A$20,A7) -> 11.68
A8: FEBRERO | B8: =COUNTIF($A$16:$A$20,A8) -> 1 | C8: =_xlfn.MINIFS($B$16:$B$20,$A$16:$A$20,A8) -> 11.68 | D8: =AVERAGEIF($A$16:$A$20,A8,$B$16:$B$20) -> 11.68 | E8: =_xlfn.MAXIFS($B$16:$B$20,$A$16:$A$20,A8) -> 11.68 | F8: =D8/D7-1 -> 0 | G8: =D8/$D$7-1 -> 0
A9: MAYO | B9: =COUNTIF($A$16:$A$20,A9) -> 1 | C9: =_xlfn.MINIFS($B$16:$B$20,$A$16:$A$20,A9) -> 11.85 | D9: =AVERAGEIF($A$16:$A$20,A9,$B$16:$B$20) -> 11.85 | E9: =_xlfn.MAXIFS($B$16:$B$20,$A$16:$A$20,A9) -> 11.85 | F9: =D9/D8-1 -> 0.014554795 | G9: =D9/$D$7-1 -> 0.014554795
A10: JULIO | B10: =COUNTIF($A$16:$A$20,A10) -> 1 | C10: =_xlfn.MINIFS($B$16:$B$20,$A$16:$A$20,A10) -> 11.85 | D10: =AVERAGEIF($A$16:$A$20,A10,$B$16:$B$20) -> 11.85 | E10: =_xlfn.MAXIFS($B$16:$B$20,$A$16:$A$20,A10) -> 11.85 | F10: =D10/D9-1 -> 0 | G10: =D10/$D$7-1 -> 0.014554795
A11: AGOSTO | B11: =COUNTIF($A$16:$A$20,A11) -> 1 | C11: =_xlfn.MINIFS($B$16:$B$20,$A$16:$A$20,A11) -> 11.85 | D11: =AVERAGEIF($A$16:$A$20,A11,$B$16:$B$20) -> 11.85 | E11: =_xlfn.MAXIFS($B$16:$B$20,$A$16:$A$20,A11) -> 11.85 | F11: =D11/D10-1 -> 0 | G11: =D11/$D$7-1 -> 0.014554795
F12: SUBIDA TOTAL | G12: =D11/D7-1 -> 0.014554795
A14: DETALLE DE PRECIOS (una línea por precio distinto anotado en el Excel del mes)
A15: MES | B15: PRECIO | C15: CANTIDAD | D15: PRODUCTO (tal cual en el Excel) | E15: ARCHIVO ORIGEN
A16: ENERO | B16: 11.68 | C16: 18 | D16: ABSOLUT 0,70L | E16: ALBARANES MAYO 2026
A17: FEBRERO | B17: 11.68 | C17: 12 | D17: ABSOLUT 0,70L | E17: ALBARANES MAYO 2026
A18: MAYO | B18: 11.85 | C18: 18 | D18: ABSOLUT 0,70L | E18: ALBARANES MAYO 2026
A19: JULIO | B19: 11.85 | C19: 18 | D19: ABSOLUT 0,70L | E19: ALBARANES JULIO 2026 v3
A20: AGOSTO | B20: 11.85 | D20: ABSOLUT 0,70L | E20: ALBARANES AGOSTO 2026 v1

Sheet BARCELO ANEJO
A1: BARCELO ANEJO | I1: ← Volver al resumen
A2: Proveedor: EIF DISTRIBUCIONES · Categoría: ENVASADO / BEBIDA / OTROS
A3: Nombres en albaranes: BARCELO AÑEJO
A4: Producto envasado / tarifa: cualquier subida de precio unitario entre el primer y el último mes con compras se considera SUBIDA.
A6: MES | B6: Nº PRECIOS | C6: PRECIO MÍN. | D6: PRECIO MEDIO | E6: PRECIO MÁX. | F6: VAR. vs MES ANTERIOR | G6: VAR. vs PRIMER MES
A7: ENERO | B7: =COUNTIF($A$15:$A$19,A7) -> 2 | C7: =_xlfn.MINIFS($B$15:$B$19,$A$15:$A$19,A7) -> 12.56 | D7: =AVERAGEIF($A$15:$A$19,A7,$B$15:$B$19) -> 12.56 | E7: =_xlfn.MAXIFS($B$15:$B$19,$A$15:$A$19,A7) -> 12.56
A8: FEBRERO | B8: =COUNTIF($A$15:$A$19,A8) -> 1 | C8: =_xlfn.MINIFS($B$15:$B$19,$A$15:$A$19,A8) -> 12.56 | D8: =AVERAGEIF($A$15:$A$19,A8,$B$15:$B$19) -> 12.56 | E8: =_xlfn.MAXIFS($B$15:$B$19,$A$15:$A$19,A8) -> 12.56 | F8: =D8/D7-1 -> 0 | G8: =D8/$D$7-1 -> 0
A9: JULIO | B9: =COUNTIF($A$15:$A$19,A9) -> 1 | C9: =_xlfn.MINIFS($B$15:$B$19,$A$15:$A$19,A9) -> 12.72 | D9: =AVERAGEIF($A$15:$A$19,A9,$B$15:$B$19) -> 12.72 | E9: =_xlfn.MAXIFS($B$15:$B$19,$A$15:$A$19,A9) -> 12.72 | F9: =D9/D8-1 -> 0.012738854 | G9: =D9/$D$7-1 -> 0.012738854
A10: AGOSTO | B10: =COUNTIF($A$15:$A$19,A10) -> 1 | C10: =_xlfn.MINIFS($B$15:$B$19,$A$15:$A$19,A10) -> 12.72 | D10: =AVERAGEIF($A$15:$A$19,A10,$B$15:$B$19) -> 12.72 | E10: =_xlfn.MAXIFS($B$15:$B$19,$A$15:$A$19,A10) -> 12.72 | F10: =D10/D9-1 -> 0 | G10: =D10/$D$7-1 -> 0.012738854
F11: SUBIDA TOTAL | G11: =D10/D7-1 -> 0.012738854
A13: DETALLE DE PRECIOS (una línea por precio distinto anotado en el Excel del mes)
A14: MES | B14: PRECIO | C14: CANTIDAD | D14: PRODUCTO (tal cual en el Excel) | E14: ARCHIVO ORIGEN
A15: ENERO | B15: 12.56 | C15: 36 | D15: BARCELO AÑEJO | E15: ALBARANES MAYO 2026
A16: ENERO | B16: 12.56 | D16: BARCELO AÑEJO | E16: ALBARANES MAYO 2026
A17: FEBRERO | B17: 12.56 | C17: 36 | D17: BARCELO AÑEJO | E17: ALBARANES MAYO 2026
A18: JULIO | B18: 12.72 | C18: 12 | D18: BARCELO AÑEJO | E18: ALBARANES JULIO 2026 v3
A19: AGOSTO | B19: 12.72 | C19: 12 | D19: BARCELO AÑEJO | E19: ALBARANES AGOSTO 2026 v1

Sheet A GIRASOL ALTO OLEICO
A1: A GIRASOL ALTO OLEICO | I1: ← Volver al resumen
A2: Proveedor: MAGOASE · Categoría: ENVASADO / BEBIDA / OTROS
A3: Nombres en albaranes: BID. PET A. GIRASOL ALTO OLEICO GUADALSOL 25L - RECTANGULAR | BID. PET A.GIRASOL ALTO OLEICO
A4: Producto envasado / tarifa: cualquier subida de precio unitario entre el primer y el último mes con compras se considera SUBIDA.
A6: MES | B6: Nº PRECIOS | C6: PRECIO MÍN. | D6: PRECIO MEDIO | E6: PRECIO MÁX. | F6: VAR. vs MES ANTERIOR | G6: VAR. vs PRIMER MES
A7: ENERO | B7: =COUNTIF($A$17:$A$23,A7) -> 1 | C7: =_xlfn.MINIFS($B$17:$B$23,$A$17:$A$23,A7) -> 44.95 | D7: =AVERAGEIF($A$17:$A$23,A7,$B$17:$B$23) -> 44.95 | E7: =_xlfn.MAXIFS($B$17:$B$23,$A$17:$A$23,A7) -> 44.95
A8: FEBRERO | B8: =COUNTIF($A$17:$A$23,A8) -> 1 | C8: =_xlfn.MINIFS($B$17:$B$23,$A$17:$A$23,A8) -> 44.95 | D8: =AVERAGEIF($A$17:$A$23,A8,$B$17:$B$23) -> 44.95 | E8: =_xlfn.MAXIFS($B$17:$B$23,$A$17:$A$23,A8) -> 44.95 | F8: =D8/D7-1 -> 0 | G8: =D8/$D$7-1 -> 0
A9: ABRIL | B9: =COUNTIF($A$17:$A$23,A9) -> 1 | C9: =_xlfn.MINIFS($B$17:$B$23,$A$17:$A$23,A9) -> 44.95 | D9: =AVERAGEIF($A$17:$A$23,A9,$B$17:$B$23) -> 44.95 | E9: =_xlfn.MAXIFS($B$17:$B$23,$A$17:$A$23,A9) -> 44.95 | F9: =D9/D8-1 -> 0 | G9: =D9/$D$7-1 -> 0
A10: MAYO | B10: =COUNTIF($A$17:$A$23,A10) -> 1 | C10: =_xlfn.MINIFS($B$17:$B$23,$A$17:$A$23,A10) -> 44.95 | D10: =AVERAGEIF($A$17:$A$23,A10,$B$17:$B$23) -> 44.95 | E10: =_xlfn.MAXIFS($B$17:$B$23,$A$17:$A$23,A10) -> 44.95 | F10: =D10/D9-1 -> 0 | G10: =D10/$D$7-1 -> 0
A11: JULIO | B11: =COUNTIF($A$17:$A$23,A11) -> 1 | C11: =_xlfn.MINIFS($B$17:$B$23,$A$17:$A$23,A11) -> 44.95 | D11: =AVERAGEIF($A$17:$A$23,A11,$B$17:$B$23) -> 44.95 | E11: =_xlfn.MAXIFS($B$17:$B$23,$A$17:$A$23,A11) -> 44.95 | F11: =D11/D10-1 -> 0 | G11: =D11/$D$7-1 -> 0
A12: AGOSTO | B12: =COUNTIF($A$17:$A$23,A12) -> 2 | C12: =_xlfn.MINIFS($B$17:$B$23,$A$17:$A$23,A12) -> 44.95 | D12: =AVERAGEIF($A$17:$A$23,A12,$B$17:$B$23) -> 45.45 | E12: =_xlfn.MAXIFS($B$17:$B$23,$A$17:$A$23,A12) -> 45.95 | F12: =D12/D11-1 -> 0.011123471 | G12: =D12/$D$7-1 -> 0.011123471
F13: SUBIDA TOTAL | G13: =D12/D7-1 -> 0.011123471
A15: DETALLE DE PRECIOS (una línea por precio distinto anotado en el Excel del mes)
A16: MES | B16: PRECIO | C16: CANTIDAD | D16: PRODUCTO (tal cual en el Excel) | E16: ARCHIVO ORIGEN
A17: ENERO | B17: 44.95 | C17: 9 | D17: BID. PET A. GIRASOL ALTO OLEICO GUADALSOL 25L - RECTANGULAR | E17: ALBARANES MAYO 2026
A18: FEBRERO | B18: 44.95 | C18: 9 | D18: BID. PET A. GIRASOL ALTO OLEICO GUADALSOL 25L - RECTANGULAR | E18: ALBARANES MAYO 2026
A19: ABRIL | B19: 44.95 | C19: 10 | D19: BID. PET A. GIRASOL ALTO OLEICO GUADALSOL 25L - RECTANGULAR | E19: ALBARANES MAYO 2026
A20: MAYO | B20: 44.95 | C20: 12 | D20: BID. PET A. GIRASOL ALTO OLEICO GUADALSOL 25L - RECTANGULAR | E20: ALBARANES MAYO 2026
A21: JULIO | B21: 44.95 | D21: BID. PET A.GIRASOL ALTO OLEICO | E21: ALBARANES JULIO 2026 v3
A22: AGOSTO | B22: 44.95 | D22: BID. PET A.GIRASOL ALTO OLEICO | E22: ALBARANES AGOSTO 2026 v1
A23: AGOSTO | B23: 45.95 | D23: BID. PET A.GIRASOL ALTO OLEICO | E23: ALBARANES AGOSTO 2026 v1

Sheet HAVANA 7 ANOS
A1: HAVANA 7 ANOS | I1: ← Volver al resumen
A2: Proveedor: SUBMARINER · Categoría: ENVASADO / BEBIDA / OTROS
A3: Nombres en albaranes: HAVANA 7 AÑOS NR | HAVANA 7 AÑOS RN
A4: Producto envasado / tarifa: cualquier subida de precio unitario entre el primer y el último mes con compras se considera SUBIDA.
A6: MES | B6: Nº PRECIOS | C6: PRECIO MÍN. | D6: PRECIO MEDIO | E6: PRECIO MÁX. | F6: VAR. vs MES ANTERIOR | G6: VAR. vs PRIMER MES
A7: ENERO | B7: =COUNTIF($A$15:$A$18,A7) -> 1 | C7: =_xlfn.MINIFS($B$15:$B$18,$A$15:$A$18,A7) -> 18.65 | D7: =AVERAGEIF($A$15:$A$18,A7,$B$15:$B$18) -> 18.65 | E7: =_xlfn.MAXIFS($B$15:$B$18,$A$15:$A$18,A7) -> 18.65
A8: FEBRERO | B8: =COUNTIF($A$15:$A$18,A8) -> 1 | C8: =_xlfn.MINIFS($B$15:$B$18,$A$15:$A$18,A8) -> 18.65 | D8: =AVERAGEIF($A$15:$A$18,A8,$B$15:$B$18) -> 18.65 | E8: =_xlfn.MAXIFS($B$15:$B$18,$A$15:$A$18,A8) -> 18.65 | F8: =D8/D7-1 -> 0 | G8: =D8/$D$7-1 -> 0
A9: MAYO | B9: =COUNTIF($A$15:$A$18,A9) -> 1 | C9: =_xlfn.MINIFS($B$15:$B$18,$A$15:$A$18,A9) -> 18.65 | D9: =AVERAGEIF($A$15:$A$18,A9,$B$15:$B$18) -> 18.65 | E9: =_xlfn.MAXIFS($B$15:$B$18,$A$15:$A$18,A9) -> 18.65 | F9: =D9/D8-1 -> 0 | G9: =D9/$D$7-1 -> 0
A10: JULIO | B10: =COUNTIF($A$15:$A$18,A10) -> 1 | C10: =_xlfn.MINIFS($B$15:$B$18,$A$15:$A$18,A10) -> 18.81 | D10: =AVERAGEIF($A$15:$A$18,A10,$B$15:$B$18) -> 18.81 | E10: =_xlfn.MAXIFS($B$15:$B$18,$A$15:$A$18,A10) -> 18.81 | F10: =D10/D9-1 -> 0.0085790885 | G10: =D10/$D$7-1 -> 0.0085790885
F11: SUBIDA TOTAL | G11: =D10/D7-1 -> 0.0085790885
A13: DETALLE DE PRECIOS (una línea por precio distinto anotado en el Excel del mes)
A14: MES | B14: PRECIO | C14: CANTIDAD | D14: PRODUCTO (tal cual en el Excel) | E14: ARCHIVO ORIGEN
A15: ENERO | B15: 18.65 | C15: 2 | D15: HAVANA 7 AÑOS RN | E15: ALBARANES MAYO 2026
A16: FEBRERO | B16: 18.65 | C16: 7 | D16: HAVANA 7 AÑOS RN | E16: ALBARANES MAYO 2026
A17: MAYO | B17: 18.65 | D17: HAVANA 7 AÑOS RN | E17: ALBARANES MAYO 2026
A18: JULIO | B18: 18.81 | C18: 6 | D18: HAVANA 7 AÑOS NR | E18: ALBARANES JULIO 2026 v3

Sheet BEEFEATER 0,70
A1: BEEFEATER 0,70 | I1: ← Volver al resumen
A2: Proveedor: SUBMARINER · Categoría: ENVASADO / BEBIDA / OTROS
A3: Nombres en albaranes: BEEFEATER 0,70L NR
A4: Producto envasado / tarifa: cualquier subida de precio unitario entre el primer y el último mes con compras se considera SUBIDA.
A6: MES | B6: Nº PRECIOS | C6: PRECIO MÍN. | D6: PRECIO MEDIO | E6: PRECIO MÁX. | F6: VAR. vs MES ANTERIOR | G6: VAR. vs PRIMER MES
A7: ENERO | B7: =COUNTIF($A$15:$A$19,A7) -> 2 | C7: =_xlfn.MINIFS($B$15:$B$19,$A$15:$A$19,A7) -> 12.2 | D7: =AVERAGEIF($A$15:$A$19,A7,$B$15:$B$19) -> 12.2 | E7: =_xlfn.MAXIFS($B$15:$B$19,$A$15:$A$19,A7) -> 12.2
A8: FEBRERO | B8: =COUNTIF($A$15:$A$19,A8) -> 1 | C8: =_xlfn.MINIFS($B$15:$B$19,$A$15:$A$19,A8) -> 12.2 | D8: =AVERAGEIF($A$15:$A$19,A8,$B$15:$B$19) -> 12.2 | E8: =_xlfn.MAXIFS($B$15:$B$19,$A$15:$A$19,A8) -> 12.2 | F8: =D8/D7-1 -> 0 | G8: =D8/$D$7-1 -> 0
A9: MAYO | B9: =COUNTIF($A$15:$A$19,A9) -> 1 | C9: =_xlfn.MINIFS($B$15:$B$19,$A$15:$A$19,A9) -> 12.3 | D9: =AVERAGEIF($A$15:$A$19,A9,$B$15:$B$19) -> 12.3 | E9: =_xlfn.MAXIFS($B$15:$B$19,$A$15:$A$19,A9) -> 12.3 | F9: =D9/D8-1 -> 0.0081967213 | G9: =D9/$D$7-1 -> 0.0081967213
A10: JULIO | B10: =COUNTIF($A$15:$A$19,A10) -> 1 | C10: =_xlfn.MINIFS($B$15:$B$19,$A$15:$A$19,A10) -> 12.3 | D10: =AVERAGEIF($A$15:$A$19,A10,$B$15:$B$19) -> 12.3 | E10: =_xlfn.MAXIFS($B$15:$B$19,$A$15:$A$19,A10) -> 12.3 | F10: =D10/D9-1 -> 0 | G10: =D10/$D$7-1 -> 0.0081967213
F11: SUBIDA TOTAL | G11: =D10/D7-1 -> 0.0081967213
A13: DETALLE DE PRECIOS (una línea por precio distinto anotado en el Excel del mes)
A14: MES | B14: PRECIO | C14: CANTIDAD | D14: PRODUCTO (tal cual en el Excel) | E14: ARCHIVO ORIGEN
A15: ENERO | B15: 12.2 | C15: 18 | D15: BEEFEATER 0,70L NR | E15: ALBARANES MAYO 2026
A16: ENERO | B16: 12.2 | C16: 1 | D16: BEEFEATER 0,70L NR | E16: ALBARANES ENERO 2026
A17: FEBRERO | B17: 12.2 | C17: 20 | D17: BEEFEATER 0,70L NR | E17: ALBARANES MAYO 2026
A18: MAYO | B18: 12.3 | C18: 12 | D18: BEEFEATER 0,70L NR | E18: ALBARANES MAYO 2026
A19: JULIO | B19: 12.3 | C19: 18 | D19: BEEFEATER 0,70L NR | E19: ALBARANES JULIO 2026 v3

Sheet TRUS CRIANZA 3 4
A1: TRUS CRIANZA 3/4 | I1: ← Volver al resumen
A2: Proveedor: DITEMA (DIST. TENA) · Categoría: ENVASADO / BEBIDA / OTROS
A3: Nombres en albaranes: TRUS CRIANZA 3/4
A4: Producto envasado / tarifa: cualquier subida de precio unitario entre el primer y el último mes con compras se considera SUBIDA.
A6: MES | B6: Nº PRECIOS | C6: PRECIO MÍN. | D6: PRECIO MEDIO | E6: PRECIO MÁX. | F6: VAR. vs MES ANTERIOR | G6: VAR. vs PRIMER MES
A7: ENERO | B7: =COUNTIF($A$14:$A$16,A7) -> 1 | C7: =_xlfn.MINIFS($B$14:$B$16,$A$14:$A$16,A7) -> 9.71 | D7: =AVERAGEIF($A$14:$A$16,A7,$B$14:$B$16) -> 9.71 | E7: =_xlfn.MAXIFS($B$14:$B$16,$A$14:$A$16,A7) -> 9.71
A8: FEBRERO | B8: =COUNTIF($A$14:$A$16,A8) -> 1 | C8: =_xlfn.MINIFS($B$14:$B$16,$A$14:$A$16,A8) -> 9.71 | D8: =AVERAGEIF($A$14:$A$16,A8,$B$14:$B$16) -> 9.71 | E8: =_xlfn.MAXIFS($B$14:$B$16,$A$14:$A$16,A8) -> 9.71 | F8: =D8/D7-1 -> 0 | G8: =D8/$D$7-1 -> 0
A9: MAYO | B9: =COUNTIF($A$14:$A$16,A9) -> 1 | C9: =_xlfn.MINIFS($B$14:$B$16,$A$14:$A$16,A9) -> 9.78 | D9: =AVERAGEIF($A$14:$A$16,A9,$B$14:$B$16) -> 9.78 | E9: =_xlfn.MAXIFS($B$14:$B$16,$A$14:$A$16,A9) -> 9.78 | F9: =D9/D8-1 -> 0.0072090628 | G9: =D9/$D$7-1 -> 0.0072090628
F10: SUBIDA TOTAL | G10: =D9/D7-1 -> 0.0072090628
A12: DETALLE DE PRECIOS (una línea por precio distinto anotado en el Excel del mes)
A13: MES | B13: PRECIO | C13: CANTIDAD | D13: PRODUCTO (tal cual en el Excel) | E13: ARCHIVO ORIGEN
A14: ENERO | B14: 9.71 | C14: 36 | D14: TRUS CRIANZA 3/4 | E14: ALBARANES MAYO 2026
A15: FEBRERO | B15: 9.71 | C15: 6 | D15: TRUS CRIANZA 3/4 | E15: ALBARANES MAYO 2026
A16: MAYO | B16: 9.78 | C16: 18 | D16: TRUS CRIANZA 3/4 | E16: ALBARANES MAYO 2026

Sheet BRUGAL 0,70
A1: BRUGAL 0,70 | I1: ← Volver al resumen
A2: Proveedor: SUBMARINER · Categoría: ENVASADO / BEBIDA / OTROS
A3: Nombres en albaranes: BRUGAL 0,70L NR
A4: Producto envasado / tarifa: cualquier subida de precio unitario entre el primer y el último mes con compras se considera SUBIDA.
A6: MES | B6: Nº PRECIOS | C6: PRECIO MÍN. | D6: PRECIO MEDIO | E6: PRECIO MÁX. | F6: VAR. vs MES ANTERIOR | G6: VAR. vs PRIMER MES
A7: ENERO | B7: =COUNTIF($A$15:$A$18,A7) -> 1 | C7: =_xlfn.MINIFS($B$15:$B$18,$A$15:$A$18,A7) -> 11.6 | D7: =AVERAGEIF($A$15:$A$18,A7,$B$15:$B$18) -> 11.6 | E7: =_xlfn.MAXIFS($B$15:$B$18,$A$15:$A$18,A7) -> 11.6
A8: FEBRERO | B8: =COUNTIF($A$15:$A$18,A8) -> 1 | C8: =_xlfn.MINIFS($B$15:$B$18,$A$15:$A$18,A8) -> 11.6 | D8: =AVERAGEIF($A$15:$A$18,A8,$B$15:$B$18) -> 11.6 | E8: =_xlfn.MAXIFS($B$15:$B$18,$A$15:$A$18,A8) -> 11.6 | F8: =D8/D7-1 -> 0 | G8: =D8/$D$7-1 -> 0
A9: MAYO | B9: =COUNTIF($A$15:$A$18,A9) -> 1 | C9: =_xlfn.MINIFS($B$15:$B$18,$A$15:$A$18,A9) -> 11.66 | D9: =AVERAGEIF($A$15:$A$18,A9,$B$15:$B$18) -> 11.66 | E9: =_xlfn.MAXIFS($B$15:$B$18,$A$15:$A$18,A9) -> 11.66 | F9: =D9/D8-1 -> 0.0051724138 | G9: =D9/$D$7-1 -> 0.0051724138
A10: JULIO | B10: =COUNTIF($A$15:$A$18,A10) -> 1 | C10: =_xlfn.MINIFS($B$15:$B$18,$A$15:$A$18,A10) -> 11.66 | D10: =AVERAGEIF($A$15:$A$18,A10,$B$15:$B$18) -> 11.66 | E10: =_xlfn.MAXIFS($B$15:$B$18,$A$15:$A$18,A10) -> 11.66 | F10: =D10/D9-1 -> 0 | G10: =D10/$D$7-1 -> 0.0051724138
F11: SUBIDA TOTAL | G11: =D10/D7-1 -> 0.0051724138
A13: DETALLE DE PRECIOS (una línea por precio distinto anotado en el Excel del mes)
A14: MES | B14: PRECIO | C14: CANTIDAD | D14: PRODUCTO (tal cual en el Excel) | E14: ARCHIVO ORIGEN
A15: ENERO | B15: 11.6 | C15: 24 | D15: BRUGAL 0,70L NR | E15: ALBARANES MAYO 2026
A16: FEBRERO | B16: 11.6 | C16: 18 | D16: BRUGAL 0,70L NR | E16: ALBARANES MAYO 2026
A17: MAYO | B17: 11.66 | C17: 12 | D17: BRUGAL 0,70L NR | E17: ALBARANES MAYO 2026
A18: JULIO | B18: 11.66 | C18: 10 | D18: BRUGAL 0,70L NR | E18: ALBARANES JULIO 2026 v3

Sheet LARIOS ESPECIAL 12
A1: LARIOS ESPECIAL 12 | I1: ← Volver al resumen
A2: Proveedor: SUBMARINER · Categoría: ENVASADO / BEBIDA / OTROS
A3: Nombres en albaranes: LARIOS ESPECIAL 12 NR
A4: Producto envasado / tarifa: cualquier subida de precio unitario entre el primer y el último mes con compras se considera SUBIDA.
A6: MES | B6: Nº PRECIOS | C6: PRECIO MÍN. | D6: PRECIO MEDIO | E6: PRECIO MÁX. | F6: VAR. vs MES ANTERIOR | G6: VAR. vs PRIMER MES
A7: ENERO | B7: =COUNTIF($A$13:$A$14,A7) -> 1 | C7: =_xlfn.MINIFS($B$13:$B$14,$A$13:$A$14,A7) -> 12.06 | D7: =AVERAGEIF($A$13:$A$14,A7,$B$13:$B$14) -> 12.06 | E7: =_xlfn.MAXIFS($B$13:$B$14,$A$13:$A$14,A7) -> 12.06
A8: JULIO | B8: =COUNTIF($A$13:$A$14,A8) -> 1 | C8: =_xlfn.MINIFS($B$13:$B$14,$A$13:$A$14,A8) -> 12.12 | D8: =AVERAGEIF($A$13:$A$14,A8,$B$13:$B$14) -> 12.12 | E8: =_xlfn.MAXIFS($B$13:$B$14,$A$13:$A$14,A8) -> 12.12 | F8: =D8/D7-1 -> 0.0049751244 | G8: =D8/$D$7-1 -> 0.0049751244
F9: SUBIDA TOTAL | G9: =D8/D7-1 -> 0.0049751244
A11: DETALLE DE PRECIOS (una línea por precio distinto anotado en el Excel del mes)
A12: MES | B12: PRECIO | C12: CANTIDAD | D12: PRODUCTO (tal cual en el Excel) | E12: ARCHIVO ORIGEN
A13: ENERO | B13: 12.06 | C13: 3 | D13: LARIOS ESPECIAL 12 NR | E13: ALBARANES MAYO 2026
A14: JULIO | B14: 12.12 | C14: 6 | D14: LARIOS ESPECIAL 12 NR | E14: ALBARANES JULIO 2026 v3

Sheet LARIOS 1L
A1: LARIOS 1L | I1: ← Volver al resumen
A2: Proveedor: SUBMARINER · Categoría: ENVASADO / BEBIDA / OTROS
A3: Nombres en albaranes: LARIOS 1L NR
A4: Producto envasado / tarifa: cualquier subida de precio unitario entre el primer y el último mes con compras se considera SUBIDA.
A6: MES | B6: Nº PRECIOS | C6: PRECIO MÍN. | D6: PRECIO MEDIO | E6: PRECIO MÁX. | F6: VAR. vs MES ANTERIOR | G6: VAR. vs PRIMER MES
A7: ENERO | B7: =COUNTIF($A$14:$A$16,A7) -> 1 | C7: =_xlfn.MINIFS($B$14:$B$16,$A$14:$A$16,A7) -> 10.27 | D7: =AVERAGEIF($A$14:$A$16,A7,$B$14:$B$16) -> 10.27 | E7: =_xlfn.MAXIFS($B$14:$B$16,$A$14:$A$16,A7) -> 10.27
A8: JULIO | B8: =COUNTIF($A$14:$A$16,A8) -> 1 | C8: =_xlfn.MINIFS($B$14:$B$16,$A$14:$A$16,A8) -> 10.32 | D8: =AVERAGEIF($A$14:$A$16,A8,$B$14:$B$16) -> 10.32 | E8: =_xlfn.MAXIFS($B$14:$B$16,$A$14:$A$16,A8) -> 10.32 | F8: =D8/D7-1 -> 0.0048685492 | G8: =D8/$D$7-1 -> 0.0048685492
A9: AGOSTO | B9: =COUNTIF($A$14:$A$16,A9) -> 1 | C9: =_xlfn.MINIFS($B$14:$B$16,$A$14:$A$16,A9) -> 10.32 | D9: =AVERAGEIF($A$14:$A$16,A9,$B$14:$B$16) -> 10.32 | E9: =_xlfn.MAXIFS($B$14:$B$16,$A$14:$A$16,A9) -> 10.32 | F9: =D9/D8-1 -> 0 | G9: =D9/$D$7-1 -> 0.0048685492
F10: SUBIDA TOTAL | G10: =D9/D7-1 -> 0.0048685492
A12: DETALLE DE PRECIOS (una línea por precio distinto anotado en el Excel del mes)
A13: MES | B13: PRECIO | C13: CANTIDAD | D13: PRODUCTO (tal cual en el Excel) | E13: ARCHIVO ORIGEN
A14: ENERO | B14: 10.27 | C14: 2 | D14: LARIOS 1L NR | E14: ALBARANES MAYO 2026
A15: JULIO | B15: 10.32 | C15: 2 | D15: LARIOS 1L NR | E15: ALBARANES JULIO 2026 v3
A16: AGOSTO | B16: 10.32 | C16: 1 | D16: LARIOS 1L NR | E16: ALBARANES AGOSTO 2026 v1

Sheet SEAGRAMS 0,70
A1: SEAGRAMS 0,70 | I1: ← Volver al resumen
A2: Proveedor: SUBMARINER · Categoría: ENVASADO / BEBIDA / OTROS
A3: Nombres en albaranes: SEAGRAMS 0,70L NR
A4: Producto envasado / tarifa: cualquier subida de precio unitario entre el primer y el último mes con compras se considera SUBIDA.
A6: MES | B6: Nº PRECIOS | C6: PRECIO MÍN. | D6: PRECIO MEDIO | E6: PRECIO MÁX. | F6: VAR. vs MES ANTERIOR | G6: VAR. vs PRIMER MES
A7: ENERO | B7: =COUNTIF($A$15:$A$19,A7) -> 2 | C7: =_xlfn.MINIFS($B$15:$B$19,$A$15:$A$19,A7) -> 13.32 | D7: =AVERAGEIF($A$15:$A$19,A7,$B$15:$B$19) -> 13.32 | E7: =_xlfn.MAXIFS($B$15:$B$19,$A$15:$A$19,A7) -> 13.32
A8: FEBRERO | B8: =COUNTIF($A$15:$A$19,A8) -> 1 | C8: =_xlfn.MINIFS($B$15:$B$19,$A$15:$A$19,A8) -> 13.32 | D8: =AVERAGEIF($A$15:$A$19,A8,$B$15:$B$19) -> 13.32 | E8: =_xlfn.MAXIFS($B$15:$B$19,$A$15:$A$19,A8) -> 13.32 | F8: =D8/D7-1 -> 0 | G8: =D8/$D$7-1 -> 0
A9: MAYO | B9: =COUNTIF($A$15:$A$19,A9) -> 1 | C9: =_xlfn.MINIFS($B$15:$B$19,$A$15:$A$19,A9) -> 13.38 | D9: =AVERAGEIF($A$15:$A$19,A9,$B$15:$B$19) -> 13.38 | E9: =_xlfn.MAXIFS($B$15:$B$19,$A$15:$A$19,A9) -> 13.38 | F9: =D9/D8-1 -> 0.0045045045 | G9: =D9/$D$7-1 -> 0.0045045045
